Workbook

Sheet Instructions
A1: Holding-Accuracy and Reasoning-Grounding Annotation Workbook
A3: Purpose | B3: Complete the proposal's missing human-validation strand by checking whether each generated legal proposition states an authority's holding accurately and whether the draft's application is supported by the linked retrieval evidence.
A5: Step | B5: Required action
A6: 1. Sample | B6: Review only rows marked yes in Annotations.in_validation_sample. The deterministic stratified sample contains 50 of 59 judgments: 29 real-case inputs and 21 synthetic-case inputs (seed 748).
A7: 2. Unit | B7: Each annotation row is one cited authority/application unit. The 50 sampled judgments contain 98 such units.
A8: 3. Holding source | B8: Open the authoritative_source_url and identify the authoritative paragraph(s) that state the legal proposition actually decided.
A9: 4. Holding label | B9: yes = generated principle materially matches the source; partial = core idea is right but incomplete/overbroad; no = materially wrong or attributed to the wrong authority; unclear = source cannot resolve confidently; n/a = legislation/rule or no judicial holding.
A10: 5. Grounding evidence | B10: Filter Retrieved Evidence by the row's search_id. Record the relevant rank, case ID and chunk ID in retrieved_evidence_R1/R2.
A11: 6. Grounding label | B11: yes = the generated application is directly supported by linked retrieved material; partial = some support but an important step is unsupported; no = unsupported, contradicted or based on an unrelated source; unclear = exported evidence is insufficient; n/a = no application/grounding assessment applies.
A12: 7. Evidence notes | B12: Give a short factual reason for every label. Do not treat corpus presence alone as proof that a source was retrieved.
A13: 8. Confidence | B13: Use 1 (low) to 5 (high).
A14: 9. Reviewer 2 | B14: A second reviewer independently completes the R2 fields without reading R1 labels. Agreement and Cohen's kappa then calculate automatically.
A15: 10. Adjudication | B15: Resolve disagreements after both independent reviews; record final labels and a brief note.
... A22: Workbook status | B22: Prefilled blue cells are evidence from the audit pipeline. Pale-yellow cells are for human annotation. Do not overwrite prefilled evidence.

Sheet Sample Register
A1: Reproducible 50-Judgment Validation Sample
A2: Total judgments | B2: 59 | C2: Sampled judgments | D2: 50 | E2: Real sampled | F2: 29 | G2: Synthetic sampled | H2: 21 | I2: Sampled citation units | J2: 98 | K2: Seed | L2: 748 | M2: Method | N2: SHA-256 rank within input type | O2: Status | P2: Ready for annotation
A3: Purpose | B3: Approximately 50 generated outputs, as proposed | C3: Selection | D3: Stratified to preserve the observed real/synthetic judgment ratio | E3: Sampling unit | F3: draft_id | G3: Annotation unit | H3: citation occurrence | I3: Repeated runs | J3: Retained but not independent | K3: Primary sheets | L3: Annotations + Retrieved Evidence | M3: Agreement | N3: R1/R2 labels | O3: Do not edit | P3: Prefilled evidence
A5: sample_order | B5: in_validation_sample | C5: draft_id | D5: case_doc_id | E5: case_title | F5: input_type | G5: model_used | H5: generated_at | I5: search_id | J5: searched_at | K5: link_method | L5: citation_count | M5: average_similarity | N5: top_retrieved_case | O5: retrieved_result_count | P5: annotation_status
A6: 1 | B6: yes | C6: cmst45vlc000h04l7f6nlqawg | D6: skeleton-args-ca2015008373-db13b0c8e36da3c2 | E6: Crossfield Trading Ltd v Northern Commercial Bank Plc | F6: synthetic | G6: gpt-4o-mini | H6: 2026-08-14 15:40:27.31 | I6: cmst43r4x000b04l747yntyz2 | J6: 2026-08-14 15:38:48.135 | K6: latest_search_before_draft | L6: 1 | M6: 0.67510093 | N6: Crestsign Ltd v National Westminster Bank Plc & Anor [2015] EWCA Civ 986 | O6: 20 | P6: =IF(B6="no","not sampled",IF(COUNTIFS(Annotations!$C$2:$C$116,C6,Annotations!$AT$2:$AT$116,"complete")=COUNTIF(Annotations!$C$2:$C$116,C6),"complete","pending")) -> complete
A7: 2 | B7: yes | C7: cmmxpdot1000h04i8q3aleh7a | D7: karpasitis-v-hertfordshire-county-council | E7: Karpasitis v Hertfordshire County Council | F7: real | G7: gpt-4o-mini | H7: 2026-03-19 16:47:14.388 | I7: cmmxp9veu000b04i838upwih8 | J7: 2026-03-19 16:44:16.211 | K7: latest_search_before_draft | L7: 1 | M7: 0.69000792 | N7: Gorringe v. Calderdale Metropolitan Borough Council | O7: 20 | P7: =IF(B7="no","not sampled",IF(COUNTIFS(Annotations!$C$2:$C$116,C7,Annotations!$AT$2:$AT$116,"complete")=COUNTIF(Annotations!$C$2:$C$116,C7),"complete","pending")) -> complete
A8: 3 | B8: yes | C8: cmm0ckscr000t04i312fc6edg | D8: skeleton-args-ca2018006090-aa90566cb5f6b5de | E8: Appellant: [Name Undisclosed] v Respondent: [Name Undisclosed] | F8: synthetic | G8: gpt-4o-mini | H8: 2026-02-24 08:32:26.762 | I8: cmm0chr9w000n04i37bx1uiqp | J8: 2026-02-24 08:30:05.313 | K8: latest_search_before_draft | L8: 2 | M8: 0.67713532 | N8: Creggy v Barnett & Anor [2016] EWCA Civ 1004 (Court of Appeal (Civil Division)) | O8: 10 | P8: =IF(B8="no","not sampled",IF(COUNTIFS(Annotations!$C$2:$C$116,C8,Annotations!$AT$2:$AT$116,"complete")=COUNTIF(Annotations!$C$2:$C$116,C8),"complete","pending")) -> complete
A9: 4 | B9: yes | C9: cmst419ew000k04ladhs06s0r | D9: skeleton-args-ca2015000120-c8bbd9c0f403a8f6 | E9: Lila Sharma v Meridian Financial Services Ltd | F9: synthetic | G9: gpt-4o-mini | H9: 2026-08-14 15:36:51.942 | I9: cmst3ztkq000e04labxjacu4p | J9: 2026-08-14 15:35:44.67 | K9: latest_search_before_draft | L9: 2 | M9: 0.71589964 | N9: Kalu v Brighton and Sussex University Hospitals NHS Trust & Ors [2015] EWCA Civ 897 | O9: 20 | P9: =IF(B9="no","not sampled",IF(COUNTIFS(Annotations!$C$2:$C$116,C9,Annotations!$AT$2:$AT$116,"complete")=COUNTIF(Annotations!$C$2:$C$116,C9),"complete","pending")) -> complete
A10: 5 | B10: yes | C10: cmmc4a8zu000h04jx2w3r0hzo | D10: ca-2024-000255-ellis-v-ssj-appellant-skeleton | E10: R (Fajr Ellis) v Secretary of State for Justice | F10: real | G10: gpt-4o-mini | H10: 2026-03-04 14:13:32.296 | I10: cmmc48b4h000b04jxrxrp3idf | J10: 2026-03-04 14:12:01.647 | K10: latest_search_before_draft | L10: 2 | M10: 0.68496763 | N10: Bristow v The Secretary of State for Justice & Anor [2015] EWCA Civ 1170 | O10: 10 | P10: =IF(B10="no","not sampled",IF(COUNTIFS(Annotations!$C$2:$C$116,C10,Annotations!$AT$2:$AT$116,"complete")=COUNTIF(Annotations!$C$2:$C$116,C10),"complete","pending")) -> complete
A11: 6 | B11: yes | C11: cms1u865i000904jxu5huyjg5 | D11: ca-2024-001541-the-king-on-the-application-of-respondent-skeleton | E11: Transport Action Network Limited v Secretary of State for Transport | F11: real | G11: gpt-4o-mini | H11: 2026-07-26 13:32:31.396 | I11: cms1u714o000304jxq0x5fnl6 | J11: 2026-07-26 13:31:38.105 | K11: latest_search_before_draft | L11: 2 | M11: 0.65644003 | N11: The Howard League for Penal Reform and Prisoners' Advice Service v The Lord Chancellor | O11: 20 | P11: =IF(B11="no","not sampled",IF(COUNTIFS(Annotations!$C$2:$C$116,C11,Annotations!$AT$2:$AT$116,"complete")=COUNTIF(Annotations!$C$2:$C$116,C11),"complete","pending")) -> complete
A12: 7 | B12: yes | C12: cmomnx9nj000304jkyxxg2b0k | D12: greenfields--iow--limited-v-isle-of-wight-council---westridge-village-limited | E12: Greenfields (IOW) Limited v Isle of Wight Council & Westridge Village Limited | F12: real | G12: gpt-4o-mini | H12: 2026-05-01 08:40:25.371 | I12: cmmxtwenv000304jr7vxcmpae | J12: 2026-03-19 18:53:46.044 | K12: latest_search_before_draft | L12: 2 | M12: 0.72857795 | N12: Regina v. London Borough of Hammersmith and Fulham (Burkett) [2002] UKHL 23 | O12: 20 | P12: =IF(B12="no","not sampled",IF(COUNTIFS(Annotations!$C$2:$C$116,C12,Annotations!$AT$2:$AT$116,"complete")=COUNTIF(Annotations!$C$2:$C$116,C12),"complete","pending")) -> complete
A13: 8 | B13: yes | C13: cmmcal70d000h04k3e11w997v | D13: ew-cases-EWCA-Civ-2024-1110 | E13: UnipolSai Assicurazioni S.p.A. v Covéa Insurance Plc | F13: real | G13: gpt-4o-mini | H13: 2026-03-04 17:10:00.635 | I13: cmmcaho67000b04k3d50f98in | J13: 2026-03-04 17:07:16.148 | K13: latest_search_before_draft | L13: 2 | M13: 0.66443149 | N13: Al Mana Lifestyle Trading LLC & Ors v United Fidelity Insurance Company PSC & Ors [2023] EWCA Civ 61 | O13: 20 | P13: =IF(B13="no","not sampled",IF(COUNTIFS(Annotations!$C$2:$C$116,C13,Annotations!$AT$2:$AT$116,"complete")=COUNTIF(Annotations!$C$2:$C$116,C13),"complete","pending")) -> complete
A14: 9 | B14: yes | C14: cmm0k3nj8000h04l412ruhfxj | D14: skeleton-args-ca2024001234-346b2d683b5c2099 | E14: Transport Action Network Limited v Secretary of State for Transport | F14: synthetic | G14: gpt-4o-mini | H14: 2026-02-24 12:03:04.29 | I14: cmm0k0854000b04l440eijrw0 | J14: 2026-02-24 12:00:24.289 | K14: latest_search_before_draft | L14: 2 | M14: 0.6690264 | N14: Finch On Behalf of the Weald Action Group, R (On the Application Of) v Surrey County Council & Ors [2022] EWCA Civ 187 | O14: 10 | P14: =IF(B14="no","not sampled",IF(COUNTIFS(Annotations!$C$2:$C$116,C14,Annotations!$AT$2:$AT$116,"complete")=COUNTIF(Annotations!$C$2:$C$116,C14),"complete","pending")) -> complete
A15: 10 | B15: yes | C15: cmmafut12000904l4kjskwky4 | D15: skeleton-args-ca2025000412-e17d5e10793fe216 | E15: R (Harrison) v Secretary of State for Justice | F15: synthetic | G15: gpt-4o-mini | H15: 2026-03-03 10:01:54.804 | I15: cmmafsf07000304l4huaorple | J15: 2026-03-03 10:00:03.207 | K15: latest_search_before_draft | L15: 1 | M15: 0.64864108 | N15: The Howard League for Penal Reform and Prisoners' Advice Service v The Lord Chancellor | O15: 10 | P15: =IF(B15="no","not sampled",IF(COUNTIFS(Annotations!$C$2:$C$116,C15,Annotations!$AT$2:$AT$116,"complete")=COUNTIF(Annotations!$C$2:$C$116,C15),"complete","pending")) -> complete
A16: 11 | B16: yes | C16: cmmrr64va000h04jvzuquhz2y | D16: ca-2024-000255-ellis-v-ssj-appellant-skeleton | E16: Fajr Ellis v Secretary of State for Justice | F16: real | G16: gpt-4o-mini | H16: 2026-03-15 12:50:44.132 | I16: cmmrr3vbb000b04jvglqzb8az | J16: 2026-03-15 12:48:58.332 | K16: latest_search_before_draft | L16: 2 | M16: 0.69141448 | N16: Bristow v The Secretary of State for Justice & Anor [2015] EWCA Civ 1170 | O16: 20 | P16: =IF(B16="no","not sampled",IF(COUNTIFS(Annotations!$C$2:$C$116,C16,Annotations!$AT$2:$AT$116,"complete")=COUNTIF(Annotations!$C$2:$C$116,C16),"complete","pending")) -> complete
A17: 12 | B17: yes | C17: cmst4kl1t000h04js7g8j67zy | D17: skeleton-args-ca2019005474-f7265b45a4e3f0ae | E17: Heritage Brewing Company Ltd v Traditional Ales Holdings Plc | F17: synthetic | G17: gpt-4o-mini | H17: 2026-08-14 15:51:53.487 | I17: cmst4iu9u000b04jsb3vxyexj | J17: 2026-08-14 15:50:32.032 | K17: latest_search_before_draft | L17: 2 | M17: 0.71757606 | N17: Maier & Anor v Asos Plc & Anor [2015] EWCA Civ 220 | O17: 20 | P17: =IF(B17="no","not sampled",IF(COUNTIFS(Annotations!$C$2:$C$116,C17,Annotations!$AT$2:$AT$116,"complete")=COUNTIF(Annotations!$C$2:$C$116,C17),"complete","pending")) -> complete
... A55: 50 | B55: yes | C55: cmmjsmua2000q04jstd4i8p7c | D55: ca-2024-000255-ellis-v-ssj-appellant-skeleton | E55: Fajr Ellis v Secretary of State for Justice | F55: real | G55: gpt-4o-mini | H55: 2026-03-09 23:09:33.769 | I55: cmmjsjnvz000k04js5ptftolc | J55: 2026-03-09 23:07:05.425 | K55: latest_search_before_draft | L55: 1 | M55: 0.72093931 | N55: Velyo Velev v. Bulgaria (Application No. 16032/07) | O55: 20 | P55: =IF(B55="no","not sampled",IF(COUNTIFS(Annotations!$C$2:$C$116,C55,Annotations!$AT$2:$AT$116,"complete")=COUNTIF(Annotations!$C$2:$C$116,C55),"complete","pending")) -> complete
B56: no | C56: cmlzrzxca000304l2qk1vevzx | D56: skeleton-args-ca2023002207-ce0aafdf6d7e5716 | E56: Karpasitis v Hertfordshire County Council | F56: synthetic | G56: gpt-4o-mini | H56: 2026-02-23 22:56:21.127 | I56: cmlzry90i000b04laxzwy3gcm | J56: 2026-02-23 22:55:02.859 | K56: latest_search_before_draft | L56: 2 | M56: 0.67972329 | N56: Brown & Ors v South West Lakes Trust & Ors [2022] EWCA Civ 18 | O56: 10 | P56: =IF(B56="no","not sampled",IF(COUNTIFS(Annotations!$C$2:$C$116,C56,Annotations!$AT$2:$AT$116,"complete")=COUNTIF(Annotations!$C$2:$C$116,C56),"complete","pending")) -> not sampled
B57: no | C57: cmm3b1g6j000j04jt8w2u9z6w | D57: skeleton-args-ca2025000412-e17d5e10793fe216 | E57: R (Harrison) v Secretary of State for Justice | F57: synthetic | G57: gpt-4o-mini | H57: 2026-02-26 10:12:43.433 | I57: cmm3azb8t000d04jtx7he2awl | J57: 2026-02-26 10:11:03.637 | K57: latest_search_before_draft | L57: 2 | M57: 0.63831415 | N57: Tigere, R (On the Application Of) v Secretary of State for Business, Innovation And Skills | O57: 10 | P57: =IF(B57="no","not sampled",IF(COUNTIFS(Annotations!$C$2:$C$116,C57,Annotations!$AT$2:$AT$116,"complete")=COUNTIF(Annotations!$C$2:$C$116,C57),"complete","pending")) -> not sampled
B58: no | C58: cmmdkjytd000304jl24cdxqvp | D58: skeleton-args-ca2023004634-299a4a730fe1f43a | E58: Metropolitan Property Holdings Ltd v Artisan Coffee Co Ltd | F58: synthetic | G58: gpt-4o-mini | H58: 2026-03-05 14:36:45.694 | I58: cmmdjmbqo000b04js13axm03c | J58: 2026-03-05 14:10:36.041 | K58: latest_search_before_draft | L58: 3 | M58: 0.71504954 | N58: Freifeld & Anor v West Kensington Court Ltd [2015] EWCA Civ 806 | O58: 20 | P58: =IF(B58="no","not sampled",IF(COUNTIFS(Annotations!$C$2:$C$116,C58,Annotations!$AT$2:$AT$116,"complete")=COUNTIF(Annotations!$C$2:$C$116,C58),"complete","pending")) -> not sampled
B59: no | C59: cmsbr6p4p001704l4z7u6108h | D59: ca-2024-000806-hippodrome-casino-ltd-v-hmrc-appellant-skeleton | E59: Hippodrome Casino Ltd v HM Revenue and Customs | F59: real | G59: gpt-4o-mini | H59: 2026-08-02 12:05:05.592 | I59: cmsbr5rlu001104l45rnkob9p | J59: 2026-08-02 12:04:22.059 | K59: latest_search_before_draft | L59: 1 | M59: 0.69269881 | N59: Volkswagen Financial Services (UK) Ltd v HM Revenue & Customs | O59: 20 | P59: =IF(B59="no","not sampled",IF(COUNTIFS(Annotations!$C$2:$C$116,C59,Annotations!$AT$2:$AT$116,"complete")=COUNTIF(Annotations!$C$2:$C$116,C59),"complete","pending")) -> not sampled
B60: no | C60: cmsbsp3em001104ji2u62id7q | D60: ca-2024-000624 and ca-2024-000625-the-royal-embassy-of-saudi-arabia-appellant-skeleton | E60: Abir Alhayali v The Royal Embassy of Saudi Arabia (Cultural Bureau) | F60: real | G60: gpt-4o-mini | H60: 2026-08-02 12:47:23.517 | I60: cmsbso1ez000v04jiujckeft7 | J60: 2026-08-02 12:46:34.18 | K60: latest_search_before_draft | L60: 2 | M60: 0.67225626 | N60: Argentum Exploration Limited v The Silver and all persons claiming to be interested in and/or to have rights in respect of, the Silver [2022] EWCA Civ 1318 | O60: 20 | P60: =IF(B60="no","not sampled",IF(COUNTIFS(Annotations!$C$2:$C$116,C60,Annotations!$AT$2:$AT$116,"complete")=COUNTIF(Annotations!$C$2:$C$116,C60),"complete","pending")) -> not sampled
B61: no | C61: cmsbsqcqm001d04ji3ses9ih9 | D61: ca-2024-000624 and ca-2024-000625-the-royal-embassy-of-saudi-arabia-appellant-skeleton | E61: Abir Alhayali v The Royal Embassy of Saudi Arabia (Cultural Bureau) | F61: real | G61: gpt-4o-mini | H61: 2026-08-02 12:48:22.269 | I61: cmsbsp6wa001704jitdvkybp9 | J61: 2026-08-02 12:47:27.952 | K61: latest_search_before_draft | L61: 1 | M61: 0.67225238 | N61: Argentum Exploration Limited v The Silver and all persons claiming to be interested in and/or to have rights in respect of, the Silver [2022] EWCA Civ 1318 | O61: 20 | P61: =IF(B61="no","not sampled",IF(COUNTIFS(Annotations!$C$2:$C$116,C61,Annotations!$AT$2:$AT$116,"complete")=COUNTIF(Annotations!$C$2:$C$116,C61),"complete","pending")) -> not sampled
B62: no | C62: cmsbszs77002304ji6ldkbjce | D62: ca-2024-0023525 & ca-2024-002295-modernatx-inc-v-pfizer-limited-others-respondent-skeleton | E62: Modernatx, Inc. v Pfizer Limited & BioNTech | F62: real | G62: gpt-4o-mini | H62: 2026-08-02 12:55:42.21 | I62: cmsbsuhsv001r04jiv19ukl8u | J62: 2026-08-02 12:51:35.366 | K62: latest_search_before_draft | L62: 2 | M62: 0.68141346 | N62: Philip Morris Products, S.A. v Nicoventures Trading Limited & Anor (Re Invalidity of Patents) [2022] EWCA Civ 1638 | O62: 20 | P62: =IF(B62="no","not sampled",IF(COUNTIFS(Annotations!$C$2:$C$116,C62,Annotations!$AT$2:$AT$116,"complete")=COUNTIF(Annotations!$C$2:$C$116,C62),"complete","pending")) -> not sampled
B63: no | C63: cmsbt3hfa002904ji8k6b026n | D63: ca-2024-0023525 & ca-2024-002295-modernatx-inc-v-pfizer-limited-others-respondent-skeleton | E63: Modernatx, Inc. v Pfizer Limited & Others | F63: real | G63: gpt-4o-mini | H63: 2026-08-02 12:58:34.869 | I63: cmsbsuhsv001r04jiv19ukl8u | J63: 2026-08-02 12:51:35.366 | K63: latest_search_before_draft | L63: 2 | M63: 0.68141346 | N63: Philip Morris Products, S.A. v Nicoventures Trading Limited & Anor (Re Invalidity of Patents) [2022] EWCA Civ 1638 | O63: 20 | P63: =IF(B63="no","not sampled",IF(COUNTIFS(Annotations!$C$2:$C$116,C63,Annotations!$AT$2:$AT$116,"complete")=COUNTIF(Annotations!$C$2:$C$116,C63),"complete","pending")) -> not sampled
B64: no | C64: cmst4fdgx001l04l7p4wrw7w7 | D64: skeleton-args-ca2025001247-4e7222cd1e12236a | E64: Dr. Thornton v GlobalTech Solutions Ltd | F64: synthetic | G64: gpt-4o-mini | H64: 2026-08-14 15:47:50.383 | I64: cmst4drgk001f04l70ut5a3k0 | J64: 2026-08-14 15:46:35.115 | K64: latest_search_before_draft | L64: 2 | M64: 0.6615028 | N64: Chesterton Global Ltd & Anor v Nurmohamed & Anor | O64: 20 | P64: =IF(B64="no","not sampled",IF(COUNTIFS(Annotations!$C$2:$C$116,C64,Annotations!$AT$2:$AT$116,"complete")=COUNTIF(Annotations!$C$2:$C$116,C64),"complete","pending")) -> not sampled

Sheet Annotations
A1: sample_order | B1: in_validation_sample | C1: draft_id | D1: case_doc_id | E1: input_type | F1: citation_index | G1: citation | H1: citation_type | I1: generated_principle | J1: generated_application | K1: binding_authority | L1: citation_verification_status | M1: citation_in_linked_retrieval | N1: citation_in_corpus_registry | O1: external_case_exists | P1: external_citation_correct | Q1: authoritative_source_url | R1: search_id | S1: retrieved_case_ids | T1: retrieved_case_titles | U1: reviewer_id_R1 | V1: holding_accuracy_R1 | W1: source_paragraphs_R1 | X1: holding_evidence_R1 | Y1: reasoning_grounding_R1 | Z1: retrieved_evidence_R1 | AA1: grounding_evidence_R1 | AB1: reviewer_confidence_R1 | AC1: reviewer_date_R1 | AD1: reviewer_id_R2 | AE1: holding_accuracy_R2 | AF1: source_paragraphs_R2 | AG1: holding_evidence_R2 | AH1: reasoning_grounding_R2 | AI1: retrieved_evidence_R2 | AJ1: grounding_evidence_R2 | AK1: reviewer_confidence_R2 | AL1: reviewer_date_R2 | AM1: R3_reasoning_grounding | AN1: R3_grounding_evidence | AO1: holding_agreement | AP1: grounding_agreement | AQ1: adjudicated_holding_accuracy | AR1: adjudicated_reasoning_grounding | AS1: adjudication_notes | AT1: annotation_status
A2: 1 | B2: yes | C2: cmst45vlc000h04l7f6nlqawg | D2: skeleton-args-ca2015008373-db13b0c8e36da3c2 | E2: synthetic | F2: 1 | G2: [2000] 1 WLR 377 | H2: case_law | I2: Duty to provide adequate reasons for decisions in financial services contexts. | J2: Involves ensuring clients fully understand the risks associated with financial products sold. | K2: binding | L2: not_found_in_corpus_registry | M2: no | N2: no | O2: yes | P2: yes | Q2: https://www.bailii.org/ew/cases/EWCA/Civ/1999/811.html | R2: cmst43r4x000b04l747yntyz2 | S2: a1fcbe31-60cf-480d-aa88-19492f68df24 || 187b7b96-3c95-4093-96a7-389bc96a5dea || 5efa7b7e-80f2-4a0e-ad80-5ab0db7a9c17 || 0c0d315b-921c-4764-bbf2-256f21063551 || 4bab60a4-405b-418a-b7ed-7995d0a7b4d5 || 83821fb0-ba9c-43e6-bb47-76a85327b471 || e3367bf1-963c-47c9-aea9-8dc4a1dc25bc || a30b2ade-6e0c-4b33-a0cd-099ae990e876 || 8fd0b714-5fa9-43cf-9e51-5c74a6e3d911 || ee25b714-a850-4788-bcd3-623a5cbe4ede || b4e5eb9c-82c1-4910-beaf-c30269939bbe || 727d863a-b385-45df-96e6-d8dba00144f9 || fcbf3975-3755-45fa-9124-191d1a392003 || 50f3324e-7e20-444c-b5c6-18d53dfb80ed || c31d4c82-88f9-42c8-968b-efc3ee876ec7 || ab7f6563-ffbc-46f8-a354-e1a0f0fdf80b || c21e0bef-b8ff-4f7a-8747-96ed5c2813e1 || e55b2bcd-c806-49f1-8b91-647450f700cf || fc3a7d73-0542-421b-9be1-12f07edcfd92 || edb9880b-ba30-4e1e-a2b3-52b1d6fb2f64 | T2: Crestsign Ltd v National Westminster Bank Plc & Anor [2015] EWCA Civ 986 || Saville v Central Capital Ltd [2014] EWCA Civ 337 || Deutsche Bank AG v Unitech Global Limited & Ors [2016] EWCA Civ 119 || The Financial Conduct Authority v Ferreira [2022] EWCA Civ 397 || WW Property Investments Ltd v National Westminster Bank Plc [2016] EWCA Civ 1142 (Court of Appeal, Civil Division) || CGL Group Ltd & Ors v The Royal Bank of Scotland Plc & National Westminster Bank Plc & Ors || The Financial Conduct Authority v Capital Alternatives Ltd & Ors || Property Alliance Group Ltd v The Royal Bank of Scotland Plc [2018] EWCA Civ 355 || Banco Santander Totta SA v Companhia Carris De Ferro De Lisboa SA & Ors [2016] EWCA Civ 1267 || Electro Mechanical Installations Ltd v Royal Bank of Scotland [2014] EWCA Civ 77 || Asset Land Investment Plc & Anor v The Financial Conduct Authority (FCA) || Philipp v Barclays Bank UK Plc [2022] EWCA Civ 318 || Wood v Sureterm Direct Ltd & Capita Insurance Services Ltd [2015] EWCA Civ 839 || MTR Bailey Trading Ltd v Barclays Bank Plc [2015] EWCA Civ 667 || Figurasin & Anor v Central Capital Ltd [2014] EWCA Civ 504 || Calland v Financial Conduct Authority [2015] EWCA Civ 192 || Crossfield v Jackson [2014] EWCA Civ 1548 || O'Sullivan v Financial Services Authority [2015] EWCA Civ 896 || Group Seven Ltd & Anor v Allied Investment Corporation Ltd & Ors [2015] EWCA Civ 631 || Napier Park European Credit Opportunities Fund Ltd v Harbourmaster Pro-Rata Clo 2 B.V. & Ors [2014] EWCA Civ 984 | U2: R1 | V2: partial | W2: [2000] 1 WLR 377, 381G–382D (Henry LJ) | X2: Flannery establishes a judicial duty to give adequate reasons, particularly when resolving competing expert evidence. The generated principle preserves the general duty but incorrectly reframes it as a financial-services duty. | Y2: no | Z2: No supporting Flannery passage was retrieved. Closest results: rank 1, case ID a1fcbe31-60cf-480d-aa88-19492f68df24, chunk a1fcbe31-60cf-480d-aa88-19492f68df24_legal_classification; rank 15, case ID c31d4c82-88f9-42c8-968b-efc3ee876ec7, chunk c31d4c82-88f9-42c8-968b-efc3ee876ec7_legal_classification. | AA2: The cited authority was not retrieved. The retrieved passages concern financial-product disclosure and mis-selling generally, but they do not establish a duty to ensure that clients fully understand product risks or support the application attributed to Flannery. | AB2: 4 | AC2: 46250 | AD2: R2 | AE2: partial | AF2: 381G-382C (Henry LJ) | AG2: Ratio is the professional judge's general duty to give reasons (Henry LJ, four general comments; exceptions noted for magistrates and summary costs discretion). The duty-to-give-reasons kernel is faithful, but the judgment does not confine the duty to financial services; it arose in a valuer's negligence claim over a mortgage valuation. Context substituted rather than preserved. "Adequate" also imports the later English v Emery Reimbold standard; Flannery itself makes the required extent subject-matter dependent (comment 3). | AH2: no | AI2: search cmst43r4x...; 20 records, ranks 1-3 Crestsign / Saville / Deutsche Bank v Unitech; 16 of 20 matched on legal_classification chunks; cited authority absent | AJ2: 20 records returned; cited authority absent. 16 of 20 matched on legal_classification chunks, which are area/keyword metadata rather than propositions, so supply no premise. Remaining chunks are an unrelated swaps outcome, two citation lists and a precedent-strength note. Retrieval contains financial mis-selling material (Crestsign, Saville, Figurasin, CGL v RBS) topically adjacent to the application, but nothing supporting a reasons-based duty or the transposition from the cited authority. | AK2: 4 | AL2: 46250 | AO2: =IF(OR(V2="",AE2=""),"",IF(V2=AE2,"agree","disagree")) -> agree | AP2: =IF(OR(Y2="",AH2=""),"",IF(Y2=AH2,"agree","disagree")) -> agree | AQ2: partial | AR2: no | AS2: Holding (partial): Ratio is the professional judge's general duty to give reasons (Henry LJ, four general comments; exceptions noted for magistrates and summary costs… Grounding (no): 20 records returned; cited authority absent. 16 of 20 matched on legal_classification chunks, which are area/keyword metadata rather than propositions, so supply no premise… | AT2: =IF(B2="no","not sampled",IF(AND(V2<>"",Y2<>""),"complete","pending")) -> complete
A3: 2 | B3: yes | C3: cmmxpdot1000h04i8q3aleh7a | D3: karpasitis-v-hertfordshire-county-council | E3: real | F3: 1 | G3: English v Emery Reimbold & Strick Ltd [2002] EWCA Civ 605 | H3: case_law | I3: A judgment must provide adequate reasons for its decision | J3: The principles of adequate reasoning apply to this case regarding the justification of the maintenance practices. | K3: binding | L3: in_corpus_not_retrieved | M3: no | N3: yes | O3: yes | P3: yes | Q3: https://www.bailii.org/ew/cases/EWCA/Civ/2002/605.html | R3: cmmxp9veu000b04i838upwih8 | S3: bc30491e-9ae6-48da-90d0-71d8a8069b22 || 52d20bb9-6964-44a6-9c32-d191ef76297c || 5a42b4bc-fe8f-47be-9b13-869933b2ddff || 70d43223-0ec6-458b-b052-bdc295e0d6ec || 4840c2e7-7326-456e-84e1-def231729686 || 40629bba-06c5-4cf4-b83a-bc0badbc4848 || 6948a4df-0a45-4ddc-ae3d-8eafee44976a || e16d7203-6f9e-4896-96e0-d021cb6f5579 || 0af9689e-f55a-4b42-8c7d-e7ef4d3d1bdc || 2eaaf060-799f-4573-a18a-86e5c14b158b || 70c75405-8cba-40e2-92ff-8302ea4f6789 || 1ae781af-c482-402d-b18c-8d4c33432b24 || 653f5240-7160-47e4-9009-db4466a660e2 || 4685ad0e-87e7-4f59-8991-823ab27d9393 || 54d149f2-2e02-477e-8541-b2bf222578d6 || 353163ab-c444-4186-a05c-4f5d73800a3f || 9adfee0f-c2c7-4caa-83ed-720a548a4aab || 7351e867-1c92-49d6-a602-686678f60a5f || 57bf779f-da1f-4ee4-a60c-89018cb3b828 || 2e37836d-c57c-4eb6-942a-5a1a3a46714f | T3: Gorringe v. Calderdale Metropolitan Borough Council || King Lifting Ltd v Oxfordshire County Council [2016] EWHC 1767 (QB) || Yetkin v London Borough of Newham ([2010] EWCA Civ 776) || Brown & Ors v South West Lakes Trust & Ors [2022] EWCA Civ 18 || Butcher v Southend-On-Sea Borough Council (2014) || Dunnage v Randall & UK Insurance Ltd [2015] EWCA Civ 673 || Scott v Gavigan [2016] EWCA Civ 544 || Edwards v London Borough of Sutton [2016] EWCA Civ 1005 || Hughes v Rattan (Rev1) [2022] EWCA Civ 107 || National Grid Electricity Transmission Plc v Arnold White Estates Ltd [2014] EWCA Civ 216 || Griffiths v Gwynedd County Council [2015] EWCA Civ 1440 || HXA v Surrey County Council; YXA v Wolverhampton City Council (England and Wales Court of Appeal (Civil Division)) || Liverpool Women's Hospital NHS Foundation Trust v Ronayne [2015] EWCA Civ 588 || Tindall & Anor v Chief Constable of Thames Valley Police & Anor [2022] EWCA Civ 25 || Union of Shop, Distributive and Allied Workers & Ors v Tesco Stores Ltd (2022) EWCA Civ 978 || Paul & Ors v The Royal Wolverhampton NHS Trust; Polmear v The Royal Wolverhampton NHS Trust; Purchase v Royal Cornwall Hospitals NHS Trust || Barton & Ors v Morris & Anor [2023] UKSC 3 || Howmet Limited v Economy Devices Limited & Ors [2016] EWCA Civ 847 || Beaumont & Anor v Ferrer [2016] EWCA Civ 768 || Benyatov v Credit Suisse (Securities) Europe Ltd [2023] EWCA Civ 140 | U3: R1 | V3: yes | W3: [2002] EWCA Civ 605, paras 1–2 and 15–20 | X3: The Court of Appeal confirmed that a judgment must provide sufficient reasons to make the basis of the decision apparent. The generated principle is a materially faithful summary of that duty. | Y3: no | Z3: English v Emery was not retrieved. Closest maintenance results: rank 1, Gorringe, case ID bc30491e-9ae6-48da-90d0-71d8a8069b22, chunk bc30491e-9ae6-48da-90d0-71d8a8069b22_legal_classification; rank 2, King Lifting, case ID 52d20bb9-6964-44a6-9c32-d191ef76297c, chunk 52d20bb9-6964-44a6-9c32-d191ef76297c_legal_classification; rank 11, Griffiths, case ID 70c75405-8cba-40e2-92ff-8302ea4f6789, chunk 70c75405-8cba-40e2-92ff-8302ea4f6789_legal_classification. | AA3: The cited authority was present in the corpus but was not retrieved for this generation. The retrieved passages concern highway-maintenance duties and negligence, not the judicial duty to give adequate reasons. They do not support applying English v Emery to the justification of maintenance practices. | AB3: 5 | AC3: 46250 | AD3: R2 | AE3: yes | AF3: [16], [19]; see also [25] | AG3: Faithful one-line statement of the ratio (Lord Phillips MR at [16], [19]): the judgment must make apparent to the parties why one won and the other lost. Adequacy is case-dependent and there is no duty to address every argument ([19]), but those limits qualify the extent of the duty rather than the proposition asserted. No wrong context or duty-holder introduced. | AH3: no | AI3: search cmmxp9veu000b04i838upwih8; 20 records; cited authority absent (in corpus, not retrieved); 14/20 matched on citations_precedents chunks; ranks 1-3 Gorringe v Calderdale, King Lifting v Oxfordshire, Yetkin v Newham (legal_classification); rank 14 Tindall (legal_reasoning) | AJ3: English absent from linked retrieval. 14 of 20 records matched on citations_precedents chunks, which are bare lists of cited authorities and supply no proposition. Remainder are highway/occupiers' liability classification (Gorringe, King Lifting, Yetkin, Griffiths v Gwynedd) plus one omissions-liability reasoning chunk (Tindall). Highway-maintenance material is present, but nothing supports the reasons-adequacy principle invoked, and the application transposes a judge's duty to explain a judgment into the authority's justification of its maintenance regime. | AK3: 4 | AL3: 46251 | AO3: =IF(OR(V3="",AE3=""),"",IF(V3=AE3,"agree","disagree")) -> agree | AP3: =IF(OR(Y3="",AH3=""),"",IF(Y3=AH3,"agree","disagree")) -> agree | AQ3: yes | AR3: no | AS3: Holding (yes): Faithful one-line statement of the ratio (Lord Phillips MR at [16], [19]): the judgment must make apparent to the parties why one won and the other… Grounding (no): English absent from linked retrieval. 14 of 20 records matched on citations_precedents chunks, which are bare lists of cited authorities and supply no proposition. Remainder are… | AT3: =IF(B3="no","not sampled",IF(AND(V3<>"",Y3<>""),"complete","pending")) -> complete
A4: 3 | B4: yes | C4: cmm0ckscr000t04i312fc6edg | D4: skeleton-args-ca2018006090-aa90566cb5f6b5de | E4: synthetic | F4: 1 | G4: Armitage v Nurse [1998] Ch 241 | H4: case_law | I4: Establishes that a trustee must comply with fiduciary obligations. | J4: Reiterates the need for independent transactions to avoid self-dealing. | K4: binding | L4: not_found_in_corpus_registry | M4: no | N4: no | O4: yes | P4: yes | Q4: https://www.bailii.org/ew/cases/EWCA/Civ/1997/1279.html | R4: cmm0chr9w000n04i37bx1uiqp | S4: 4f894b7c-50f6-46f4-b08a-7d5f549411bb || 63f1ceea-1ae6-4e29-9f3b-c354ab3fba11 || af98350e-e553-4a58-8a45-9d7b2067b530 || 0f564d6f-98e5-402b-abc8-a39f1fa33427 || 5d67e6bf-5a94-4298-82ae-1f13fea951bc || a62a842c-af59-45c4-be74-800b0be5e691 || cbf9a2bb-7b6f-41be-ba0f-1a84a1e459e6 || 7d4b37f2-bfb0-4f96-a5c0-d63cd27e8dc3 || cfb9db03-44c0-4604-926a-a76e01575d88 || 8c2741c2-7eeb-471a-91de-bc6accd97a3c | T4: Creggy v Barnett & Anor [2016] EWCA Civ 1004 (Court of Appeal (Civil Division)) || Burnden Holdings (UK) Limited (in Liquidation) v Fielding & Anor [2016] EWCA Civ 557 || Santander UK Plc v R.A. Legal Solicitors [2014] EWCA Civ 183 || Cotton & Anor v Brudenell-Bruce, Earl of Cardigan & Ors [2014] EWCA Civ 1312 || Braintree District Council v Secretary of State for the Home Department & Anor [2023] EWCA Civ 727 (23 June 2023) || Hassam & Anor v Rabot & Anor; Briggs v Laditan [2023] EWCA Civ 19 || Gangat v Jassat & Anor [2022] EWCA Civ 604 || Davies v Ford & Ors [2023] EWCA Civ 167 || Floreat Investment Management Ltd v Churchill & Ors [2023] EWCA Civ 440 || Barnsley & Ors v Noble (Rev1) [2016] EWCA Civ 799 (Court of Appeal, Civil Division) | U4: R1 | V4: partial | W4: [1998] Ch 241, 253H–254B and 254E–256A (Millett LJ) | X4: Armitage concerned the scope and validity of trustee exemption clauses. It recognised an irreducible obligation to perform the trust honestly and in good faith, but permitted exemption from liability for other breaches. The generated principle is broadly related but omits this central context and overstates the holding as a general requirement to comply with all fiduciary obligations. | Y4: partial | Z4: Rank 10, Barnsley v Noble, case ID 8c2741c2-7eeb-471a-91de-bc6accd97a3c, chunk 8c2741c2-7eeb-471a-91de-bc6accd97a3c_case_analysis, discusses self-dealing, transaction and exoneration clauses and cites Armitage. Rank 4, Cotton v Brudenell-Bruce, case ID 0f564d6f-98e5-402b-abc8-a39f1fa33427, chunk 0f564d6f-98e5-402b-abc8-a39f1fa33427_case_analysis, concerns trustee conduct, property sales, honesty and disclosure. | AA4: The linked retrieval provides limited support that self-dealing and conflicts are relevant to trustee transactions. However, Armitage was not retrieved as a standalone case, and no passage establishes a requirement for “independent transactions.” The application therefore exceeds the retrieved evidence. | AB4: 4 | AC4: 46250 | AD4: R2 | AE4: partial | AF4: ~251-256 (Millett LJ: irreducible core; cl 15 exemption) | AG4: Principal issue was the validity of a trustee exemption clause (cl 15): liability for breach including gross negligence may be excluded, but not for fraud or dishonesty; an irreducible core of honesty and good faith survives (Millett LJ, ~251-256). The generated principle is a vague generality that omits that context and sits awkwardly with the ratio, since Armitage confirms duties of care can be excluded. | AH4: no | AI4: search cmm0chr9w000n04i37bx1uiqp; 10 records (cf 20 elsewhere); cited authority absent and not in corpus registry; 6/10 case_analysis, 3/10 procedural_history, 1/10 legal_reasoning; rank 10 Barnsley v Noble closest (exoneration clause applied to self-dealing); ranks 4 Cotton v Brudenell-Bruce, 9 Floreat (fiduciary duties) | AJ4: Armitage absent from retrieval and not in corpus registry. Only 10 records returned; 6 of 10 matched case_analysis chunks (precedent-strength and complexity scores, i.e. evaluative metadata rather than propositions) and 3 procedural_history chunks (court/judge/date listings, two unrelated: Braintree planning, Hassam whiplash). Rank 10 Barnsley v Noble references exoneration clauses applied to self-dealing and rank 4 Cotton v Brudenell-Bruce fiduciary duty, so fiduciary material is topically present, but no retrieved chunk states a self-dealing proposition. Application invokes the self-dealing rule, a doctrine distinct from the cited authority's ratio. | AK4: 3 | AL4: 46251 | AO4: =IF(OR(V4="",AE4=""),"",IF(V4=AE4,"agree","disagree")) -> agree | AP4: =IF(OR(Y4="",AH4=""),"",IF(Y4=AH4,"agree","disagree")) -> disagree | AQ4: partial | AR4: no | AS4: Holding (partial): Principal issue was the validity of a trustee exemption clause (cl 15): liability for breach including gross negligence may be excluded, but not for… Grounding (no): Armitage absent from retrieval and not in corpus registry. Only 10 records returned; 6 of 10 matched case_analysis chunks (precedent-strength and complexity scores, i.e. evaluative… | AT4: =IF(B4="no","not sampled",IF(AND(V4<>"",Y4<>""),"complete","pending")) -> complete
A5: 3 | B5: yes | C5: cmm0ckscr000t04i312fc6edg | D5: skeleton-args-ca2018006090-aa90566cb5f6b5de | E5: synthetic | F5: 2 | G5: Spread Trustee Co Ltd v Hutcheson [2011] UKPC 13 | H5: case_law | I5: Reiterates the necessity of diligent investment by trustees. | J5: Clarifies fiduciary duties and potential breaches based on performance metrics. | K5: binding | L5: not_found_in_corpus_registry | M5: no | N5: no | O5: yes | P5: yes | Q5: https://jcpc.uk/cases/jcpc-2010-0007 | R5: cmm0chr9w000n04i37bx1uiqp | S5: 4f894b7c-50f6-46f4-b08a-7d5f549411bb || 63f1ceea-1ae6-4e29-9f3b-c354ab3fba11 || af98350e-e553-4a58-8a45-9d7b2067b530 || 0f564d6f-98e5-402b-abc8-a39f1fa33427 || 5d67e6bf-5a94-4298-82ae-1f13fea951bc || a62a842c-af59-45c4-be74-800b0be5e691 || cbf9a2bb-7b6f-41be-ba0f-1a84a1e459e6 || 7d4b37f2-bfb0-4f96-a5c0-d63cd27e8dc3 || cfb9db03-44c0-4604-926a-a76e01575d88 || 8c2741c2-7eeb-471a-91de-bc6accd97a3c | T5: Creggy v Barnett & Anor [2016] EWCA Civ 1004 (Court of Appeal (Civil Division)) || Burnden Holdings (UK) Limited (in Liquidation) v Fielding & Anor [2016] EWCA Civ 557 || Santander UK Plc v R.A. Legal Solicitors [2014] EWCA Civ 183 || Cotton & Anor v Brudenell-Bruce, Earl of Cardigan & Ors [2014] EWCA Civ 1312 || Braintree District Council v Secretary of State for the Home Department & Anor [2023] EWCA Civ 727 (23 June 2023) || Hassam & Anor v Rabot & Anor; Briggs v Laditan [2023] EWCA Civ 19 || Gangat v Jassat & Anor [2022] EWCA Civ 604 || Davies v Ford & Ors [2023] EWCA Civ 167 || Floreat Investment Management Ltd v Churchill & Ors [2023] EWCA Civ 440 || Barnsley & Ors v Noble (Rev1) [2016] EWCA Civ 799 (Court of Appeal, Civil Division) | U5: R1 | V5: partial | W5: [3]–[5], [20]–[23], [80] | X5: [20] confirms the duty to act as a reasonable and prudent trustee with reasonable care and skill. However, [3]–[5] and [21]–[23] show that the appeal concerned exoneration from liability for gross negligence under Guernsey law. The Board did not determine whether the alleged investment conduct constituted a breach. The generated principle therefore captures a general duty-of-care idea but mischaracterises the case as an investment-diligence holding. | Y5: partial | Z5: Rank 10, Barnsley v Noble, chunk 8c2741c2-7eeb-471a-91de-bc6accd97a3c_case_analysis, discusses trustee exoneration clauses and fiduciary duties and lists Spread Trustee among the cited cases. | AA5: The retrieval provides limited support for the general fiduciary-duty/exoneration theme. It does not support assessing breaches through performance metrics, and the Spread Trustee judgment itself was not retrieved as a standalone authority. | AB5: 4 | AC5: 46250 | AD5: R2 | AE5: no | AF5: [54]-[61], [111]; Baroness Hale and Lord Kerr dissenting | AG5: Appeal from Guernsey. Sole issue was whether a trust deed could exclude a trustee's liability for gross negligence before the Trusts (Amendment) (Guernsey) Law 1990. Held 3-2 that Guernsey customary law and s.34(7) of the 1989 Law permitted such exclusion, the 1990 prohibition not being retrospective. The judgment says nothing about a duty of diligent investment; investment duties were not in issue. Proposition attributed is not established by the authority. | AH5: no | AI5: search cmm0chr9w000n04i37bx1uiqp (shared with citation_index 1); 10 records; cited authority absent and not in corpus registry; 6/10 case_analysis, 3/10 procedural_history, 1/10 legal_reasoning; nearest fiduciary material at ranks 4 Cotton v Brudenell-Bruce, 9 Floreat, 10 Barnsley v Noble; no investment or performance material at any rank | AJ5: Spread Trustee absent from retrieval and not in corpus registry. The 10 records concern limitation for trust claims (Creggy, Burnden), solicitors' handling of trust funds (Santander), trustee conduct in property sales (Cotton), dishonest assistance and constructive trusts (Floreat) and exoneration clauses (Barnsley), plus three procedural_history listings, two unrelated. Nothing addresses investment duties or performance-based assessment of breach, so the application's premise is absent from the linked retrieval entirely. | AK5: 4 | AL5: 46251 | AO5: =IF(OR(V5="",AE5=""),"",IF(V5=AE5,"agree","disagree")) -> disagree | AP5: =IF(OR(Y5="",AH5=""),"",IF(Y5=AH5,"agree","disagree")) -> disagree | AQ5: no | AR5: no | AS5: Holding (no): The appeal decided whether Guernsey law permitted exclusion of gross-negligence liability, not a duty of diligent investment; the attributed… Grounding (no): Spread Trustee absent from retrieval and not in corpus registry. The 10 records concern limitation for trust claims (Creggy, Burnden), solicitors' handling of trust funds… | AT5: =IF(B5="no","not sampled",IF(AND(V5<>"",Y5<>""),"complete","pending")) -> complete
A6: 4 | B6: yes | C6: cmst419ew000k04ladhs06s0r | D6: skeleton-args-ca2015000120-c8bbd9c0f403a8f6 | E6: synthetic | F6: 1 | G6: Shamoon v Chief Constable of the Royal Ulster Constabulary | H6: case_law | I6: Direct discrimination can be established by examining the circumstances surrounding the treatment of the employee. | J6: Applicable here as microaggressions create an environment of perceived discrimination. | K6: persuasive | L6: not_found_in_corpus_registry | M6: no | N6: no | O6: yes | P6: incomplete | Q6: https://publications.parliament.uk/pa/ld200203/ldjudgmt/jd030227/sham-1.htm | R6: cmst3ztkq000e04labxjacu4p | S6: b5913f39-0611-4550-b7a3-d97e1fc4f9c9 || 060fb5e3-4e14-487d-89e2-170c04ebf40c || 7b9b0d5a-dc61-43d4-9626-d82e18f8c8dd || 9ae4bb2e-75ef-4733-a35d-66d61620f6e5 || 3b44a16a-76b8-49d4-8f00-6e1767c46005 || 9106dcdb-cf09-4bda-8712-36474df03834 || 29190db1-6f4f-49a2-84d9-84e5a2091581 || 9505adbf-4b10-41b0-bc0d-d71d70aa9210 || 87fe7360-158a-49e4-8725-7a68e18ba9ac || 48b2068c-80e9-4d0c-81f5-46a177a4c560 || d6938848-6263-4913-8294-68c6e5aca496 || 9365ac87-002c-4767-beb5-daa394718251 || e740795c-9249-45f8-aba9-1ab82a3274ca || 4b1144b2-2c97-48a1-8fd0-8ebbb0e8a2ce || e099b583-4ed3-4598-a6cb-0f3565312f05 || d0274784-a003-4439-8e79-06947376b0e7 || b6038737-31bb-4cfe-ba4c-5199070a3616 || 71cd4995-e726-4ac0-861a-ef9b3e0c3f4d || 58d08b20-69c9-47be-8f81-5be69b31e088 || c7763be7-d3d8-4e78-acc8-2eae10851872 | T6: Kalu v Brighton and Sussex University Hospitals NHS Trust & Ors [2015] EWCA Civ 897 || Gaurilcikiene v Tesco Stores Ltd [2014] EWCA Civ 1213 || South Wales Police Authority v Johnson [2014] EWCA Civ 73 || Home Office (UK Border Agency) v Essop & Ors || Khan v Royal Mail Group Ltd & Ors [2014] EWCA Civ 1082 || Agbenowossi-Koffi v Donvand Ltd [2014] EWCA Civ 855 || Jafri v Lincoln College [2014] EWCA Civ 449 || Ayodele v Citylink Ltd & Anor || Coventry University v Mian [2014] EWCA Civ 1275 || Burrell v Micheldever Tyre Services Ltd || Xerox (UK) Ltd & Ors v Zeb [2017] EWCA Civ 2137 || Adeshina v St. George's University Hospitals NHS Foundation Trust & Ors [2017] EWCA Civ 257 || Gala Tent Ltd v Chambers & Anor [2015] EWCA Civ 1063 || Ahir v British Airways Plc [2017] EWCA Civ 1392 || Pye v Queen Mary University of London [2017] EWCA Civ 1820 || CLFIS (UK) Ltd v Reynolds || Shrestha v Genesis Housing Association Ltd [2015] EWCA Civ 94 || Rochford v WNS Global Services (UK) Ltd & Ors [2017] EWCA Civ 2205 || Kuznetsov v The Royal Bank of Scotland Plc || Bhardwaj v FDA & Ors [2015] EWCA Civ 658 | U6: R1 | V6: partial | W6: [3]–[12], [14]–[15] | X6: [3]–[4] identify the elements of direct discrimination as less favourable treatment on a prohibited ground, using an actual or hypothetical comparator whose circumstances are materially the same. [8]–[12] explain that the comparator and reason-why questions may be intertwined and that the tribunal may examine all the facts to determine why the treatment occurred. The generated principle captures the relevance of surrounding circumstances but omits the comparator, less-favourable-treatment and prohibited-ground requirements. | Y6: no | Z6: Rank 1 Kalu, chunk b5913f39-0611-4550-b7a3-d97e1fc4f9c9_case_analysis; rank 2 Gaurilcikiene, chunk 060fb5e3-4e14-487d-89e2-170c04ebf40c_case_analysis; and rank 3 South Wales Police Authority v Johnson, chunk 7b9b0d5a-dc61-43d4-9626-d82e18f8c8dd_case_analysis. These contain only general discussion of discrimination claims, evidence and burden of proof. | AA6: one of the retrieved passages mentions microaggressions, a discriminatory environment or facts establishing that the alleged treatment occurred because of a protected characteristic. A perceived discriminatory environment is also not, without more, the direct-discrimination test stated in Shamoon. | AB6: 4 | AC6: 46250 | AD6: R2 | AE6: partial | AF6: [7]-[12] (Lord Nicholls); [64]-[74] (Lord Hope); [110]-[136] (Lord Scott) | AG6: HL, NI appeal. Lord Nicholls's guidance is that tribunals may avoid the rigid two-stage less-favourable-treatment/comparator sequence and instead ask directly why the claimant was treated as she was, since the two questions are intertwined; the comparator must be someone whose relevant circumstances are the same (s.7 NI Order 1976 / RRA analogue). The generated principle captures the shift toward examining surrounding circumstances but omits the essentials: the requirement of less favourable treatment than a genuine comparator, the "reason why" question, and that the guidance concerns the order of tribunal enquiry rather than a free-standing route to establishing discrimination. Correct general idea, important test omitted. | AH6: no | AI6: search cmst3ztkq000e04labxjacu4p; 20 records, 20/20 case_analysis; cited authority absent and not in corpus registry; ranks 1-5 Kalu, Gaurilcikiene, South Wales Police v Johnson, Home Office v Essop, Khan v Royal Mail; sim band 0.706-0.735 | AJ6: Shamoon absent from retrieval and not in corpus registry. All 20 records matched on case_analysis chunks, which are precedent-strength and complexity scores (each ending "Confidence: 85%") rather than legal propositions, so none supplies a premise. The retrieved cases are discrimination and employment matters (Kalu, Gaurilcikiene, Essop, Khan, Ayodele) and are topically adjacent, but nothing addresses microaggressions, perceived discrimination, or a comparator/"reason why" analysis. The application also advances a proposition the cited authority does not support: Shamoon requires less favourable treatment than a comparator, not an environment of perceived discrimination. | AK6: 4 | AL6: 46251 | AO6: =IF(OR(V6="",AE6=""),"",IF(V6=AE6,"agree","disagree")) -> agree | AP6: =IF(OR(Y6="",AH6=""),"",IF(Y6=AH6,"agree","disagree")) -> agree | AQ6: partial | AR6: no | AS6: Holding (partial): HL, NI appeal. Lord Nicholls's guidance is that tribunals may avoid the rigid two-stage less-favourable-treatment/comparator sequence and instead ask… Grounding (no): Shamoon absent from retrieval and not in corpus registry. All 20 records matched on case_analysis chunks, which are precedent-strength and complexity scores (each ending… | AT6: =IF(B6="no","not sampled",IF(AND(V6<>"",Y6<>""),"complete","pending")) -> complete
A7: 4 | B7: yes | C7: cmst419ew000k04ladhs06s0r | D7: skeleton-args-ca2015000120-c8bbd9c0f403a8f6 | E7: synthetic | F7: 2 | G7: Igen Ltd v Wong | H7: case_law | I7: The burden of proof shifts to the employer when a claimant establishes a prima facie case. | J7: Relevant to the allegations of discrimination and the Respondent’s burden of explaining performance-related dismissals. | K7: binding | L7: not_found_in_corpus_registry | M7: no | N7: no | O7: yes | P7: incomplete | Q7: https://www.bailii.org/ew/cases/EWCA/Civ/2005/142.html | R7: cmst3ztkq000e04labxjacu4p | S7: b5913f39-0611-4550-b7a3-d97e1fc4f9c9 || 060fb5e3-4e14-487d-89e2-170c04ebf40c || 7b9b0d5a-dc61-43d4-9626-d82e18f8c8dd || 9ae4bb2e-75ef-4733-a35d-66d61620f6e5 || 3b44a16a-76b8-49d4-8f00-6e1767c46005 || 9106dcdb-cf09-4bda-8712-36474df03834 || 29190db1-6f4f-49a2-84d9-84e5a2091581 || 9505adbf-4b10-41b0-bc0d-d71d70aa9210 || 87fe7360-158a-49e4-8725-7a68e18ba9ac || 48b2068c-80e9-4d0c-81f5-46a177a4c560 || d6938848-6263-4913-8294-68c6e5aca496 || 9365ac87-002c-4767-beb5-daa394718251 || e740795c-9249-45f8-aba9-1ab82a3274ca || 4b1144b2-2c97-48a1-8fd0-8ebbb0e8a2ce || e099b583-4ed3-4598-a6cb-0f3565312f05 || d0274784-a003-4439-8e79-06947376b0e7 || b6038737-31bb-4cfe-ba4c-5199070a3616 || 71cd4995-e726-4ac0-861a-ef9b3e0c3f4d || 58d08b20-69c9-47be-8f81-5be69b31e088 || c7763be7-d3d8-4e78-acc8-2eae10851872 | T7: Kalu v Brighton and Sussex University Hospitals NHS Trust & Ors [2015] EWCA Civ 897 || Gaurilcikiene v Tesco Stores Ltd [2014] EWCA Civ 1213 || South Wales Police Authority v Johnson [2014] EWCA Civ 73 || Home Office (UK Border Agency) v Essop & Ors || Khan v Royal Mail Group Ltd & Ors [2014] EWCA Civ 1082 || Agbenowossi-Koffi v Donvand Ltd [2014] EWCA Civ 855 || Jafri v Lincoln College [2014] EWCA Civ 449 || Ayodele v Citylink Ltd & Anor || Coventry University v Mian [2014] EWCA Civ 1275 || Burrell v Micheldever Tyre Services Ltd || Xerox (UK) Ltd & Ors v Zeb [2017] EWCA Civ 2137 || Adeshina v St. George's University Hospitals NHS Foundation Trust & Ors [2017] EWCA Civ 257 || Gala Tent Ltd v Chambers & Anor [2015] EWCA Civ 1063 || Ahir v British Airways Plc [2017] EWCA Civ 1392 || Pye v Queen Mary University of London [2017] EWCA Civ 1820 || CLFIS (UK) Ltd v Reynolds || Shrestha v Genesis Housing Association Ltd [2015] EWCA Civ 94 || Rochford v WNS Global Services (UK) Ltd & Ors [2017] EWCA Civ 2205 || Kuznetsov v The Royal Bank of Scotland Plc || Bhardwaj v FDA & Ors [2015] EWCA Civ 658 | U7: R1 | V7: yes | W7: [71]–[76], especially [76] Annex items (1), (2) and (9)–(13) | X7: The guidance annexed at [76] provides that the claimant must first prove facts from which the tribunal could conclude, absent an adequate explanation, that unlawful discrimination occurred. Once those facts are proved, the burden passes to the respondent to prove that the treatment was in no sense based on the prohibited ground. The generated principle materially and accurately summarises this two-stage rule. | Y7: yes | Z7: Rank 3, South Wales Police Authority v Johnson, chunk 7b9b0d5a-dc61-43d4-9626-d82e18f8c8dd_case_analysis, discusses burden of proof and evidential sufficiency and expressly cites Igen. Rank 5, Khan v Royal Mail Group, chunk 3b44a16a-76b8-49d4-8f00-6e1767c46005_case_analysis, states that Igen and Madarassy govern discrimination burdens. Rank 8, Ayodele v Citylink, chunk 9505adbf-4b10-41b0-bc0d-d71d70aa9210_case_analysis, confirms the section 136 burden-of-proof framework and cites Igen. | AA7: The retrieved passages directly support applying the burden-shifting framework to employment discrimination allegations. Ranks 17 and 18 additionally concern employee conduct, dismissal and employer explanations. Read with the generated principle’s prima-facie-case condition, the application does not materially exceed the retrieval evidence. | AB7: 4 | AC7: 46251 | AD7: R2 | AE7: yes | AF7: ~[17]-[27] and revised Barton guidance at Annex (Peter Gibson LJ) — verify pinpoints on BAILII | AG7: CA, three conjoined appeals (Igen v Wong; Chamberlin Solicitors v Emokpae; Brunel University v Webster). Revised the Barton v Investec guidelines on the two-stage burden of proof under s.63A SDA 1975 / s.54A RRA 1976: the claimant must first prove facts from which the tribunal could conclude, absent an adequate explanation, that the respondent committed an unlawful act; the burden then passes to the respondent to prove it did not discriminate. The generated principle is a compressed but faithful statement of that shift. "Prima facie case" is not the judgment's own language and glosses the "could conclude" threshold later clarified in Madarassy v Nomura, but this is compression rather than an omitted limitation. | AH7: partial | AI7: search cmst3ztkq000e04labxjacu4p (shared with citation_index 1); 20 records, 20/20 case_analysis; cited authority absent as a record but named in rank 5 chunk text; rank 5 Khan v Royal Mail (references Igen Ltd v Wong and Madarassy v Nomura), rank 8 Ayodele v Citylink (burden of proof, s.136 Equality Act), rank 3 South Wales Police v Johnson (burden of proof in race discrimination), rank 4 Essop (indirect discrimination and burden of proof) | AJ7: Igen absent from retrieval as a record and not in corpus registry, but the linked retrieval is squarely on topic: four chunks concern the burden of proof in discrimination claims, and rank 5 names Igen v Wong and Madarassy expressly. That supplies genuine relevance to the application's claim that the respondent bears a burden of explanation. It is insufficient, however, because all 20 records are case_analysis precedent-strength commentary: they reference burden of proof as a subject descriptor without stating the two-stage test or any proposition from which the application's step could be drawn. Relevant but insufficient for the full application. | AK7: 3 | AL7: 46251 | AO7: =IF(OR(V7="",AE7=""),"",IF(V7=AE7,"agree","disagree")) -> agree | AP7: =IF(OR(Y7="",AH7=""),"",IF(Y7=AH7,"agree","disagree")) -> disagree | AQ7: yes | AR7: partial | AS7: Holding (yes): CA, three conjoined appeals (Igen v Wong; Chamberlin Solicitors v Emokpae; Brunel University v Webster). Revised the Barton v Investec guidelines on… Grounding (partial): Igen absent from retrieval as a record and not in corpus registry, but the linked retrieval is squarely on topic: four chunks concern the burden of proof in discrimination claims… | AT7: =IF(B7="no","not sampled",IF(AND(V7<>"",Y7<>""),"complete","pending")) -> complete
A8: 5 | B8: yes | C8: cmmc4a8zu000h04jx2w3r0hzo | D8: ca-2024-000255-ellis-v-ssj-appellant-skeleton | E8: real | F8: 1 | G8: R (Johnson) v SSHD | H8: case_law | I8: Threshold for breach of rights requires evaluation of proportionality against security concerns in prison settings. | J8: Evaluated the balance of rights against institutional security measures. | K8: binding | L8: not_found_in_corpus_registry | M8: no | N8: no | O8: ambiguous | P8: no | Q8: https://www.supremecourt.uk/cases/uksc-2016-0042 | R8: cmmc48b4h000b04jxrxrp3idf | S8: 1dbb4242-42ac-456f-989f-5098066d87ca || d60a5323-796e-4110-a6de-012ec16860c1 || 6704e94e-e6b0-4dfe-b4c9-c5d695bdc6aa || 9826ea30-d68f-4beb-b85e-e38b5e1c7cae || be44e528-bdba-4691-afcc-c607a89fd1dc || f78142fc-13ea-4fb5-9a5e-1efbdc8d3c38 || e99652af-372a-448f-8251-a215010e8b3a || de4a5f2b-b3c7-4369-9020-dcc807bb315b || 5bc05b2e-6b7d-4270-b799-9d29ed174d14 || 3e059541-8504-4163-a05b-ede4202b7675 | T8: Bristow v The Secretary of State for Justice & Anor [2015] EWCA Civ 1170 || The Howard League for Penal Reform and Prisoners' Advice Service v The Lord Chancellor || Pearce, R (On the Application Of) v Parole Board of England and Wales & Anor [2022] EWCA Civ 4 || C3 & Anor v The Secretary of State for Foreign, Commonwealth & Development Affairs [2023] EWCA Civ 444 || R (On the Application Of) v Secretary of State for the Home Department (Rev1) [2022] EWCA Civ 30 || AAA (Syria) & Ors v Secretary of State for the Home Department [2023] EWCA Civ 266 || Richards, R (On the Application Of) v The Environment Agency [2022] EWCA Civ 26 || Elkundi, R (On the Application Of) v Birmingham City Council [2022] EWCA Civ 601 || MD & Anor v Secretary of State for the Home Department [2022] EWCA Civ 336 || Cleeland, R (On the Application Of) v Criminal Cases Review Commission [2022] EWCA Civ 5 | U8: R1 | V8: no | W8: [1]–[2], [20]–[23], [27]–[35] | X8: [1]–[2] identify the case as concerning discriminatory denial of British citizenship and consequential deportation liability. [27]–[30] address Articles 8 and 14 and the proportionality of discrimination based on birth outside marriage. [34]–[35] hold that the present deportation distinction lacked justification. The case does not establish a threshold balancing prisoners’ rights against institutional security. | Y8: no | Z8: Rank 1, Bristow v Secretary of State for Justice, chunk 1dbb4242-42ac-456f-989f-5098066d87ca_legal_classification, contains only a broad classification covering prisoner rights, Article 14 and public law. Rank 2, Howard League for Penal Reform v Lord Chancellor, chunk d60a5323-796e-4110-a6de-012ec16860c1_case_analysis, concerns prisoners’ legal aid, fair-trial rights and access to justice. Ranks 3–10 are predominantly procedural histories unrelated to the asserted balancing exercise. | AA8: The retrieved material does not discuss institutional security measures or a proportionality balance between those measures and prisoners’ rights. General references to human rights and prison law are insufficient to support the generated application. | AB8: 4 | AC8: 46251 | AD8: R2 | AE8: unclear | AF8: n/a - authority not reliably identifiable | AG8: Citation is name-only with no year or report reference, and R (Johnson) v SSHD matches several distinct authorities. The URL recorded in column Q resolves to UKSC 2016-0042, R (Johnson) v SSHD [2016] UKSC 56, which concerns automatic deportation and Article 14 discrimination arising from illegitimacy at birth, not proportionality or prison security. The draft concerns Ellis v Secretary of State for Justice; prison conditions fall to the MoJ rather than the Home Office, so the named respondent is also inconsistent with the proposition. The intended authority cannot be determined without substituting a different case, which §10 prohibits. unclear under §4 (source cannot be reliably obtained), recorded rather than resolved. | AH8: no | AI8: search cmmc48b4h000b04jxrxrp3idf (shared with citation_index 2); 10 records; 8/10 procedural_history, rank 1 Bristow v SSJ (legal_classification: Administrative Law, Human Rights, Prison Law, Article 14 ECHR, Repatriation of Prisoners Act), rank 2 Howard League v Lord Chancellor (case_analysis: prisoner legal aid, ECHR fair trial, access to justice); sim band 0.678-0.697 | AJ8: Eight of ten records matched on procedural_history chunks listing court, judges, case numbers and hearing dates with no legal content. Ranks 1 and 2 are topically adjacent — prisoner rights, Article 14, ECHR — and are the strongest material in the retrieval, but rank 1 is a taxonomy chunk naming legal areas without stating any test, and rank 2 is precedent-strength commentary on legal aid. Nothing supplies a proportionality framework or any premise for balancing rights against institutional security. Assessed against the retrieval independently of the unresolved citation. | AK8: 2 | AL8: 46251 | AO8: =IF(OR(V8="",AE8=""),"",IF(V8=AE8,"agree","disagree")) -> disagree | AP8: =IF(OR(Y8="",AH8=""),"",IF(Y8=AH8,"agree","disagree")) -> agree | AQ8: no | AR8: no | AS8: Holding (no): The supplied authoritative source resolves to Johnson [2016] UKSC 56, which concerns deportation and Article 14 discrimination rather than prison… Grounding (no): Eight of ten records matched on procedural_history chunks listing court, judges, case numbers and hearing dates with no legal content. Ranks 1 and 2 are topically adjacent —… | AT8: =IF(B8="no","not sampled",IF(AND(V8<>"",Y8<>""),"complete","pending")) -> complete
A9: 5 | B9: yes | C9: cmmc4a8zu000h04jx2w3r0hzo | D9: ca-2024-000255-ellis-v-ssj-appellant-skeleton | E9: real | F9: 2 | G9: Flannery v Halifax Estate Agencies Ltd | H9: case_law | I9: Duty to provide reasons must be adequately respected even in administrative settings. | J9: Informs the need for transparency in administrative decisions affecting rights. | K9: binding | L9: not_found_in_corpus_registry | M9: no | N9: no | O9: yes | P9: yes | Q9: https://www.bailii.org/ew/cases/EWCA/Civ/1999/811.html | R9: cmmc48b4h000b04jxrxrp3idf | S9: 1dbb4242-42ac-456f-989f-5098066d87ca || d60a5323-796e-4110-a6de-012ec16860c1 || 6704e94e-e6b0-4dfe-b4c9-c5d695bdc6aa || 9826ea30-d68f-4beb-b85e-e38b5e1c7cae || be44e528-bdba-4691-afcc-c607a89fd1dc || f78142fc-13ea-4fb5-9a5e-1efbdc8d3c38 || e99652af-372a-448f-8251-a215010e8b3a || de4a5f2b-b3c7-4369-9020-dcc807bb315b || 5bc05b2e-6b7d-4270-b799-9d29ed174d14 || 3e059541-8504-4163-a05b-ede4202b7675 | T9: Bristow v The Secretary of State for Justice & Anor [2015] EWCA Civ 1170 || The Howard League for Penal Reform and Prisoners' Advice Service v The Lord Chancellor || Pearce, R (On the Application Of) v Parole Board of England and Wales & Anor [2022] EWCA Civ 4 || C3 & Anor v The Secretary of State for Foreign, Commonwealth & Development Affairs [2023] EWCA Civ 444 || R (On the Application Of) v Secretary of State for the Home Department (Rev1) [2022] EWCA Civ 30 || AAA (Syria) & Ors v Secretary of State for the Home Department [2023] EWCA Civ 266 || Richards, R (On the Application Of) v The Environment Agency [2022] EWCA Civ 26 || Elkundi, R (On the Application Of) v Birmingham City Council [2022] EWCA Civ 601 || MD & Anor v Secretary of State for the Home Department [2022] EWCA Civ 336 || Cleeland, R (On the Application Of) v Criminal Cases Review Commission [2022] EWCA Civ 5 | U9: R1 | V9: partial | W9: pp. 381G–382C ([2000] 1 WLR 377) | X9: The Court of Appeal held that a trial judge must give sufficient reasons to explain the decision, particularly why one expert’s evidence was preferred. However, Flannery concerns judicial decisions and does not itself establish a general duty for administrative decision-makers. | Y9: no | Z9: 1dbb4242-42ac-456f-989f-5098066d87ca_legal_classification; d60a5323-796e-4110-a6de-012ec16860c1_case_analysis; the remaining retrieved passages contain procedural history only. | AA9: None of the retrieved passages mentions Flannery or provides a premise concerning adequate reasons, transparency, or explaining administrative decisions. General references to administrative law, rights, or systemic fairness are insufficient. | AB9: 4 | AC9: 46251 | AD9: R2 | AE9: partial | AF9: [2000] 1 WLR 377 at 381G-382C (Henry LJ, four general comments); duty-holder passage citing R v Knightsbridge Crown Court ex p International Sporting Club | AG9: Ratio is the professional judge's general duty to give reasons, arising in a valuer's negligence claim; Henry LJ notes exceptions including magistrates and summary costs discretion, and the extent of the duty depends on subject-matter (comment 3). Flannery concerns judicial reasons, not administrative decision-making. Extending the duty to "administrative settings" is a decontextualised extension the judgment does not make, though the judgment cites administrative-law authority (ex p Dave, ex p International Sporting Club, De Smith) as the source of the general duty, so the extension is not wholly unsupported. "Adequately" also imports the later English v Emery Reimbold standard. | AH9: no | AI9: search cmmc48b4h000b04jxrxrp3idf (shared with citation_index 1); 10 records; cited authority absent and not in corpus registry; 8/10 procedural_history, 1 legal_classification (rank 1 Bristow v SSJ), 1 case_analysis (rank 2 Howard League); sim band 0.678-0.697 | AJ9: Flannery absent from retrieval and not in corpus registry. Eight of ten records matched on procedural_history chunks, which list court, lower court, judges, case number and hearing dates only, and contain no legal content of any kind (Pearce, C3, AAA (Syria), Richards, Elkundi, MD, Cleeland). Rank 1 Bristow is an Article 14 / Repatriation of Prisoners Act classification chunk and rank 2 Howard League concerns legal aid and access to justice. Nothing in the retrieval addresses a duty to give reasons or transparency in administrative decision-making, so no premise supports the application. | AK9: 4 | AL9: 46251 | AO9: =IF(OR(V9="",AE9=""),"",IF(V9=AE9,"agree","disagree")) -> agree | AP9: =IF(OR(Y9="",AH9=""),"",IF(Y9=AH9,"agree","disagree")) -> agree | AQ9: partial | AR9: no | AS9: Holding (partial): Ratio is the professional judge's general duty to give reasons, arising in a valuer's negligence claim; Henry LJ notes exceptions including… Grounding (no): Flannery absent from retrieval and not in corpus registry. Eight of ten records matched on procedural_history chunks, which list court, lower court, judges, case number and hearing… | AT9: =IF(B9="no","not sampled",IF(AND(V9<>"",Y9<>""),"complete","pending")) -> complete
A10: 6 | B10: yes | C10: cms1u865i000904jxu5huyjg5 | D10: ca-2024-001541-the-king-on-the-application-of-respondent-skeleton | E10: real | F10: 1 | G10: [2002] EWCA Civ 605 | H10: case_law | I10: Adequacy of reasons in judgments. | J10: Requires that judicial decisions are supported by clear and substantiated reasoning to maintain accountability. | K10: binding | L10: in_corpus_not_retrieved | M10: no | N10: yes | O10: yes | P10: yes | Q10: https://www.bailii.org/ew/cases/EWCA/Civ/2002/605.html | R10: cms1u714o000304jxq0x5fnl6 | S10: d60a5323-796e-4110-a6de-012ec16860c1 || f157dc58-8d24-4561-9b20-3df67da80a73 || 7cce4927-35a4-4b74-90f4-ac2262bb34d7 || beff2d5f-922f-42e5-9aaa-8b70d7179f71 || f5a5b44e-fcf0-40c0-9bf9-69f026b1b438 || 22266eeb-429f-4bfb-806c-1f324f15797d || 970ca77e-942d-4dd9-93e4-6d8ed2dcb401 || 6b2e2714-ca39-4378-966c-1b3ff6b417b2 || 148abf64-4d41-4cef-af10-c9c9986896a1 || 7fe05ee5-91a6-43b5-ad81-c04b7cce8482 || 776a8070-aa6f-410e-b91e-2e1fcadadb9b || 6cd7db33-7ee1-44c0-9219-b2cc7d57d88b || 2081f703-fbd5-4bdc-b8b8-0a8424eb00b1 || ee81f896-3f6e-4a8c-86e9-7169799031ba || 5bc05b2e-6b7d-4270-b799-9d29ed174d14 || 8bf594df-88d1-4791-89f3-b2699310ed7a || ed07cee8-284a-4c88-9681-37d30f80d1a1 || b47f516d-ad2e-4917-8acd-6c8206ffb6c5 || 215b4f1f-c45b-4b5a-83c7-d9ecf0c27585 || b293e967-2f36-4ecf-b32f-db6614193b8b | T10: The Howard League for Penal Reform and Prisoners' Advice Service v The Lord Chancellor || The Good Law Project, R (On the Application Of) v Minister for the Cabinet Office [2022] EWCA Civ 21 || C7 v Secretary of State for the Home Department [2023] EWCA Civ 265 || Secretary of State for Communities and Local Government v West Berkshire District Council & Anor [2016] EWCA Civ 441 (11 May 2016) || London Borough of Enfield, R (on the application of) v Secretary of State for Transport & Ors [2016] EWCA Civ 480 || The Project Management Institute, R (On the Application Of) v The Minister for the Cabinet Office & Ors [2016] EWCA Civ 21 (22 January 2016) || Public and Commercial Services Union & Ors, R (On the Application Of) v Secretary of State for the Home Department [2022] EWCA Civ 840 || QX v Secretary of State for the Home Department [2022] EWCA Civ 1541 || Kanu, R (On the Application Of) v Secretary of State for Foreign, Commonwealth and Development Affairs [2023] EWCA Civ 796 || Ali, R (on the application of) v The Secretary of State for the Home Department & Anor || Sheakh, R (On the Application Of) v London Borough of Lambeth Council [2022] EWCA Civ 457 (05 April 2022) || Smith v Secretary of State for Levelling Up, Housing & Communities & Anor [2022] EWCA Civ 1391 || Roche Registration Ltd, R (on the application of) v The Secretary of State for Health || Green & Ors v The Commissioner of Police of the Metropolis [2022] EWCA Civ 1686 || MD & Anor v Secretary of State for the Home Department [2022] EWCA Civ 336 || Aviva Insurance Limited and Swiss Reinsurance Company Limited v Secretary of State for Work and Pensions [2022] EWCA Civ 15 || National AIDS Trust v National Health Service Commissioning Board (NHS England) & Ors (EWCA Civ 1100) – PrEP and NHS England power to commission preventive HIV treatment || Re B (Children: Police Investigation) [2022] EWCA Civ 982 || R3 v Secretary of State for the Home Department [2023] EWCA Civ 169 || DJ (Pakistan) v Secretary of State for the Home Department [2022] EWCA Civ 1057 | U10: R1 | V10: yes | W10: [15]–[21], especially [16], [19]–[21]; [118] | X10: English v Emery Reimbold & Strick Ltd confirms that judges must give reasons sufficient for the parties to understand why they won or lost and for an appellate court to identify the reasoning essential to the decision. Reasons need not address every argument or evidential factor. | Y10: no | Z10: No supporting passage was retrieved. The closest item, 2081f703-fbd5-4bdc-b8b8-0a8424eb00b1_citations_precedents, merely lists R v SSHD ex p Doody among cited authorities; it does not state a reason-giving principle. The other linked chunks are also citation lists. | AA10: English v Emery was not retrieved for the linked generation. None of the 20 retrieved chunks supplies the premise that judicial decisions require clear or adequate reasoning. Citation lists alone do not clearly support the generated application. | AB10: 5 | AC10: 46251 | AD10: R2 | AE10: yes | AF10: [16], [19]; see also [25] | AG10: Correctly identifies the subject-matter of the authority: adequacy of reasons in judgments is precisely what English decides (Lord Phillips MR at [16], [19] - the judgment must make apparent to the parties why one won and the other lost, adequacy depending on the nature of the case). The principle is a bare topic label rather than a stated rule, so it asserts nothing capable of being inaccurate. No wrong context, duty-holder or doctrine introduced. Labelled yes on the narrow ground that nothing attributed is unfaithful; note the near-vacuity as a limitation of the field rather than as an inaccuracy. | AH10: no | AI10: search cms1u714o000304jxq0x5fnl6 (shared with citation_index 2); 20 records, 20/20 citations_precedents; cited authority in corpus registry but not retrieved; ranks 1-5 Howard League, Good Law Project, C7 v SSHD, SSCLG v West Berkshire, Enfield v SST; sim band 0.648-0.686 | AJ10: English is in the corpus registry but was not retrieved for the linked generation. All 20 records matched on citations_precedents chunks, which are bare inventories of neutral citations, law reports and referenced cases with a citation count, and state no propositions at all. The retrieved cases are public-law and judicial-review matters (legal aid, procurement, SIAC costs, planning, PSED, deprivation of citizenship) and none concerns adequacy of judicial reasons or accountability through reasoning. No premise in the linked retrieval supports the application. | AK10: 3 | AL10: 46251 | AO10: =IF(OR(V10="",AE10=""),"",IF(V10=AE10,"agree","disagree")) -> agree | AP10: =IF(OR(Y10="",AH10=""),"",IF(Y10=AH10,"agree","disagree")) -> agree | AQ10: yes | AR10: no | AS10: Holding (yes): Correctly identifies the subject-matter of the authority: adequacy of reasons in judgments is precisely what English decides (Lord Phillips MR at… Grounding (no): English is in the corpus registry but was not retrieved for the linked generation. All 20 records matched on citations_precedents chunks, which are bare inventories of neutral… | AT10: =IF(B10="no","not sampled",IF(AND(V10<>"",Y10<>""),"complete","pending")) -> complete
A11: 6 | B11: yes | C11: cms1u865i000904jxu5huyjg5 | D11: ca-2024-001541-the-king-on-the-application-of-respondent-skeleton | E11: real | F11: 2 | G11: [2000] 1 WLR 377 | H11: case_law | I11: Duty to give reasons. | J11: Mandates that parties be informed of the rationale behind a decision, particularly in administrative cases where rights are substantially affected. | K11: binding | L11: not_found_in_corpus_registry | M11: no | N11: no | O11: yes | P11: yes | Q11: https://www.bailii.org/ew/cases/EWCA/Civ/1999/811.html | R11: cms1u714o000304jxq0x5fnl6 | S11: d60a5323-796e-4110-a6de-012ec16860c1 || f157dc58-8d24-4561-9b20-3df67da80a73 || 7cce4927-35a4-4b74-90f4-ac2262bb34d7 || beff2d5f-922f-42e5-9aaa-8b70d7179f71 || f5a5b44e-fcf0-40c0-9bf9-69f026b1b438 || 22266eeb-429f-4bfb-806c-1f324f15797d || 970ca77e-942d-4dd9-93e4-6d8ed2dcb401 || 6b2e2714-ca39-4378-966c-1b3ff6b417b2 || 148abf64-4d41-4cef-af10-c9c9986896a1 || 7fe05ee5-91a6-43b5-ad81-c04b7cce8482 || 776a8070-aa6f-410e-b91e-2e1fcadadb9b || 6cd7db33-7ee1-44c0-9219-b2cc7d57d88b || 2081f703-fbd5-4bdc-b8b8-0a8424eb00b1 || ee81f896-3f6e-4a8c-86e9-7169799031ba || 5bc05b2e-6b7d-4270-b799-9d29ed174d14 || 8bf594df-88d1-4791-89f3-b2699310ed7a || ed07cee8-284a-4c88-9681-37d30f80d1a1 || b47f516d-ad2e-4917-8acd-6c8206ffb6c5 || 215b4f1f-c45b-4b5a-83c7-d9ecf0c27585 || b293e967-2f36-4ecf-b32f-db6614193b8b | T11: The Howard League for Penal Reform and Prisoners' Advice Service v The Lord Chancellor || The Good Law Project, R (On the Application Of) v Minister for the Cabinet Office [2022] EWCA Civ 21 || C7 v Secretary of State for the Home Department [2023] EWCA Civ 265 || Secretary of State for Communities and Local Government v West Berkshire District Council & Anor [2016] EWCA Civ 441 (11 May 2016) || London Borough of Enfield, R (on the application of) v Secretary of State for Transport & Ors [2016] EWCA Civ 480 || The Project Management Institute, R (On the Application Of) v The Minister for the Cabinet Office & Ors [2016] EWCA Civ 21 (22 January 2016) || Public and Commercial Services Union & Ors, R (On the Application Of) v Secretary of State for the Home Department [2022] EWCA Civ 840 || QX v Secretary of State for the Home Department [2022] EWCA Civ 1541 || Kanu, R (On the Application Of) v Secretary of State for Foreign, Commonwealth and Development Affairs [2023] EWCA Civ 796 || Ali, R (on the application of) v The Secretary of State for the Home Department & Anor || Sheakh, R (On the Application Of) v London Borough of Lambeth Council [2022] EWCA Civ 457 (05 April 2022) || Smith v Secretary of State for Levelling Up, Housing & Communities & Anor [2022] EWCA Civ 1391 || Roche Registration Ltd, R (on the application of) v The Secretary of State for Health || Green & Ors v The Commissioner of Police of the Metropolis [2022] EWCA Civ 1686 || MD & Anor v Secretary of State for the Home Department [2022] EWCA Civ 336 || Aviva Insurance Limited and Swiss Reinsurance Company Limited v Secretary of State for Work and Pensions [2022] EWCA Civ 15 || National AIDS Trust v National Health Service Commissioning Board (NHS England) & Ors (EWCA Civ 1100) – PrEP and NHS England power to commission preventive HIV treatment || Re B (Children: Police Investigation) [2022] EWCA Civ 982 || R3 v Secretary of State for the Home Department [2023] EWCA Civ 169 || DJ (Pakistan) v Secretary of State for the Home Department [2022] EWCA Civ 1057 | U11: R1 | V11: partial | W11: pp. 381G–382C ([2000] 1 WLR 377) | X11: Flannery confirms that a professional judge generally has a duty to explain why a decision was reached, with the required detail depending on the subject matter. “Duty to give reasons” captures the core idea but omits its judicial context, qualifications and exceptions. The case does not establish a universal duty on administrative decision-makers. | Y11: no | Z11: No supporting passage was retrieved. All 20 linked chunks are citations_precedents lists. The closest, 2081f703-fbd5-4bdc-b8b8-0a8424eb00b1_citations_precedents, merely lists R v SSHD ex p Doody without stating any reason-giving rule. | AA11: Flannery was not retrieved and was not found as a standalone corpus record. None of the linked passages states that administrative parties must be informed of a decision’s rationale when their rights are substantially affected. The generated administrative-law extension therefore lacks retrieved support. | AB11: 5 | AC11: 46251 | AD11: R2 | AE11: yes | AF11: [2000] 1 WLR 377 at 381G-382C (Henry LJ, four general comments); duty-holder passage citing R v Knightsbridge Crown Court ex p International Sporting Club | AG11: Correctly identifies the subject-matter: the duty to give reasons is what Flannery decides (Henry LJ, four general comments at 381G-382C; the duty is a function of due process, want of reasons may be a self-standing ground of appeal, extent depends on subject-matter). The principle is a bare topic label rather than a stated rule, so nothing is overstated, decontextualised or misattributed. Labelled yes on the same narrow convention applied at citation_index 1 of this draft. Note that the administrative-context extension appears in the application field rather than the principle, so it falls to be assessed under grounding rather than here. | AH11: no | AI11: search cms1u714o000304jxq0x5fnl6 (shared with citation_index 1); 20 records, 20/20 citations_precedents; cited authority absent and not in corpus registry; nearest material rank 13 Roche Registration (chunk lists ex p Doody among referenced cases) and rank 1 Howard League (lists ex p Tarrant, Coughlan); sim band 0.648-0.686 | AJ11: Flannery absent from retrieval and not in corpus registry. All 20 records matched on citations_precedents chunks, which are inventories of neutral citations, law reports and referenced cases with a citation count, and state no propositions. Two chunks incidentally list authorities associated with the public-law duty to give reasons (ex p Doody at rank 13; ex p Tarrant and Coughlan at rank 1), but a case name appearing in another judgment's bibliography supplies no premise. Nothing in the linked retrieval addresses informing parties of the rationale for a decision. | AK11: 3 | AL11: 46251 | AO11: =IF(OR(V11="",AE11=""),"",IF(V11=AE11,"agree","disagree")) -> disagree | AP11: =IF(OR(Y11="",AH11=""),"",IF(Y11=AH11,"agree","disagree")) -> agree | AQ11: yes | AR11: no | AS11: Holding (yes): The concise topic label accurately identifies Flannery's judicial duty to give reasons; the administrative extension appears only in the application… Grounding (no): Flannery absent from retrieval and not in corpus registry. All 20 records matched on citations_precedents chunks, which are inventories of neutral citations, law reports and… | AT11: =IF(B11="no","not sampled",IF(AND(V11<>"",Y11<>""),"complete","pending")) -> complete
A12: 7 | B12: yes | C12: cmomnx9nj000304jkyxxg2b0k | D12: greenfields--iow--limited-v-isle-of-wight-council---westridge-village-limited | E12: real | F12: 1 | G12: R (Burkett) v Hammersmith LBC [2002] 1 WLR 1593 | H12: case_law | I12: Public authorities must follow established procedures to avoid unfairness and maintain transparency. | J12: Decision-making procedures must be transparent and fair to avoid allegations of bias. | K12: persuasive | L12: not_found_in_corpus_registry | M12: no | N12: no | O12: yes | P12: yes | Q12: https://publications.parliament.uk/pa/ld200102/ldjudgmt/jd020523/burket-1.htm | R12: cmmxtwenv000304jr7vxcmpae | S12: 379d4f20-62f5-403b-a082-fa36b82fe1c1 || a1b35831-8ed8-43ad-bc7e-488100344627 || f42492fd-8832-4f70-b315-d7597c15a5ef || 76e6ffcd-af03-4155-a667-51d98a79d1d7 || 235388cd-5994-4cf3-b7e7-c349382ef164 || 776a8070-aa6f-410e-b91e-2e1fcadadb9b || 6cd7db33-7ee1-44c0-9219-b2cc7d57d88b || 7f44d9a8-2459-4f6a-84fc-e475bb8f169a || 76cd3a35-03e9-4300-b6c9-27ac34a88301 || 3bdf2d7a-d886-4bb3-ba30-9c4b472a4f7c || 8d10f639-afdd-4cee-893d-c3b4fbaefe7b || 1d957476-2c0d-4578-8a43-679ec600e382 || 3fae9752-b3e5-4a98-a0e5-5ade79ee3e8d || 9034c8de-ac8c-45a1-9a63-569c390554ca || 90743ee0-c75d-4140-93eb-89a3938f7523 || 1f4a0cfb-5359-49da-93e8-89cbb817ebca || 3ff34419-ffbc-40f9-a087-a1cb1371d0e1 || aa66d157-e659-4b1f-9c8a-39b98d92a107 || 0642e885-86b3-4c0b-84a2-2005424f4309 || c370bf30-4fed-4187-beea-6476e69f964f | T12: Regina v. London Borough of Hammersmith and Fulham (Burkett) [2002] UKHL 23 || Corbett v Cornwall Council [2022] EWCA Civ 1069 || Cherkley Campaign Ltd, R (on the application of) v Mole Valley District Council & Anor || Arnold White Estates Ltd v The Forestry Commission [2022] EWCA Civ 1304 || Save Britain's Heritage, R (On the Application Of) v Davies (Rev1) [2023] EWCA Civ 723 || Sheakh, R (On the Application Of) v London Borough of Lambeth Council [2022] EWCA Civ 457 (05 April 2022) || Smith v Secretary of State for Levelling Up, Housing & Communities & Anor [2022] EWCA Civ 1391 || Secretary of State for Levelling Up, Housing and Communities v Smith & Anor [2023] EWCA Civ 514 || Ashburton Trading Ltd v Secretary of State for Communities And Local Government & Anor [2014] EWCA Civ 378 || Gardiner v Hertsmere Borough Council & Anor [2022] EWCA Civ 1162 || Tesco Stores Ltd v Forest of Dean District Council [2015] EWCA Civ 800 || Wyatt v Fareham Borough Council (Rev1) [2022] EWCA Civ 983 || East Quayside 12 LLP v The Council of the City of Newcastle upon Tyne [2023] EWCA Civ 359 || Thurston Parish Council, R (On the Application Of) v Mid Suffolk District Council & Anor [2022] EWCA Civ 1417 || Devine v Secretary of State for Levelling Up, Housing and Communities [2023] EWCA Civ 601 || Whitley Parish Council, R (On the Application Of) v North Yorkshire County Council & Anor [2023] EWCA Civ 92 || Vicente & Anor v Secretary of State for Communities and Local Government & Anor [2014] EWCA Civ 1555 || CAB Housing Limited v Secretary of State for Levelling Up, Housing and Communities & Anor [2023] EWCA Civ 194 || Sahota, R (On the Application Of) v Herefordshire Council [2022] EWCA Civ 1640 || Braithwaite and Melton Meadows Properties Ltd, R (On the Application Of) v East Suffolk Council [2022] EWCA Civ 1716 | U12: R1 | V12: no | W12: [5], [30]–[51], especially [37] and [51] | X12: Burkett principally concerns the time limit for judicial review of planning permission. The House of Lords held that, when the formal grant is challenged, time runs from the date planning permission is granted rather than the earlier resolution. It did not establish the attributed general rule concerning procedural transparency, unfairness or bias. | Y12: partial | Z12: 379d4f20-62f5-403b-a082-fa36b82fe1c1_metadata_summary states the correct Burkett rule concerning the starting date for judicial-review time limits. 3ff34419-ffbc-40f9-a087-a1cb1371d0e1_legal_classification identifies procedural unfairness, inadequate notification and lack of an opportunity to participate in Vicente. | AA12: he Vicente passage supplies some support for the application’s procedural-fairness component. However, neither it nor the retrieved Burkett summary supports the additional claims about transparency or avoiding allegations of bias. The application is therefore only partially grounded. | AB12: 5 | AC12: 46251 | AD12: R2 | AE12: no | AF12: [6]-[9], [39]-[46] (Lord Steyn) - HL judgment on time limits; verify pinpoints | AG12: Burkett decides a narrow procedural question: when time begins to run for judicial review of a planning permission. The House of Lords held the period runs from the date of the actual grant of permission, not from the earlier resolution to permit development. The generated principle attributes a general obligation on public authorities to follow established procedures to avoid unfairness and maintain transparency. That proposition is not established by the judgment, which concerns the claimant's time limit rather than any duty owed by the authority. Different doctrine; §4 no. | AH12: no | AI12: search cmmxtwenv000304jr7vxcmpae; 20 records; rank 1 IS the cited authority - Burkett [2002] UKHL 23, metadata_summary chunk, sim 0.761 - contradicting citation_in_linked_retrieval = no in column M; remainder 15/20 procedural_history, 4/20 legal_classification; rank 17 Vicente (legal_classification: procedural unfairness, opportunity to participate) | AJ12: The cited authority was retrieved at rank 1, but the matched chunk is a metadata_summary: a case overview stating that the time limit for judicial review runs from the grant of permission rather than the resolution. That is the only proposition available from it, and it does not support the application's claim that decision-making procedures must be transparent and fair to avoid allegations of bias. Of the remaining records, 15 are procedural_history listings with no legal content and 4 are classification taxonomies; rank 17 Vicente names procedural unfairness as a legal issue but states no test. Retrieval contained the right case and still supplied no premise for the reasoning advanced. | AK12: 4 | AL12: 46251 | AO12: =IF(OR(V12="",AE12=""),"",IF(V12=AE12,"agree","disagree")) -> agree | AP12: =IF(OR(Y12="",AH12=""),"",IF(Y12=AH12,"agree","disagree")) -> disagree | AQ12: no | AR12: no | AS12: Holding (no): Burkett decides a narrow procedural question: when time begins to run for judicial review of a planning permission. The House of Lords held the period… Grounding (no): The cited authority was retrieved at rank 1, but the matched chunk is a metadata_summary: a case overview stating that the time limit for judicial review runs from the grant of… | AT12: =IF(B12="no","not sampled",IF(AND(V12<>"",Y12<>""),"complete","pending")) -> complete
A13: 7 | B13: yes | C13: cmomnx9nj000304jkyxxg2b0k | D13: greenfields--iow--limited-v-isle-of-wight-council---westridge-village-limited | E13: real | F13: 2 | G13: Flannery v Halifax Estate Agencies Ltd [2000] 1 WLR 377 | H13: case_law | I13: Parties must be given reasons for decisions affecting their rights. | J13: Failure to provide reasons can invalidate planning decisions if it leads to procedural impropriety. | K13: binding | L13: not_found_in_corpus_registry | M13: no | N13: no | O13: yes | P13: yes | Q13: https://www.bailii.org/ew/cases/EWCA/Civ/1999/811.html | R13: cmmxtwenv000304jr7vxcmpae | S13: 379d4f20-62f5-403b-a082-fa36b82fe1c1 || a1b35831-8ed8-43ad-bc7e-488100344627 || f42492fd-8832-4f70-b315-d7597c15a5ef || 76e6ffcd-af03-4155-a667-51d98a79d1d7 || 235388cd-5994-4cf3-b7e7-c349382ef164 || 776a8070-aa6f-410e-b91e-2e1fcadadb9b || 6cd7db33-7ee1-44c0-9219-b2cc7d57d88b || 7f44d9a8-2459-4f6a-84fc-e475bb8f169a || 76cd3a35-03e9-4300-b6c9-27ac34a88301 || 3bdf2d7a-d886-4bb3-ba30-9c4b472a4f7c || 8d10f639-afdd-4cee-893d-c3b4fbaefe7b || 1d957476-2c0d-4578-8a43-679ec600e382 || 3fae9752-b3e5-4a98-a0e5-5ade79ee3e8d || 9034c8de-ac8c-45a1-9a63-569c390554ca || 90743ee0-c75d-4140-93eb-89a3938f7523 || 1f4a0cfb-5359-49da-93e8-89cbb817ebca || 3ff34419-ffbc-40f9-a087-a1cb1371d0e1 || aa66d157-e659-4b1f-9c8a-39b98d92a107 || 0642e885-86b3-4c0b-84a2-2005424f4309 || c370bf30-4fed-4187-beea-6476e69f964f | T13: Regina v. London Borough of Hammersmith and Fulham (Burkett) [2002] UKHL 23 || Corbett v Cornwall Council [2022] EWCA Civ 1069 || Cherkley Campaign Ltd, R (on the application of) v Mole Valley District Council & Anor || Arnold White Estates Ltd v The Forestry Commission [2022] EWCA Civ 1304 || Save Britain's Heritage, R (On the Application Of) v Davies (Rev1) [2023] EWCA Civ 723 || Sheakh, R (On the Application Of) v London Borough of Lambeth Council [2022] EWCA Civ 457 (05 April 2022) || Smith v Secretary of State for Levelling Up, Housing & Communities & Anor [2022] EWCA Civ 1391 || Secretary of State for Levelling Up, Housing and Communities v Smith & Anor [2023] EWCA Civ 514 || Ashburton Trading Ltd v Secretary of State for Communities And Local Government & Anor [2014] EWCA Civ 378 || Gardiner v Hertsmere Borough Council & Anor [2022] EWCA Civ 1162 || Tesco Stores Ltd v Forest of Dean District Council [2015] EWCA Civ 800 || Wyatt v Fareham Borough Council (Rev1) [2022] EWCA Civ 983 || East Quayside 12 LLP v The Council of the City of Newcastle upon Tyne [2023] EWCA Civ 359 || Thurston Parish Council, R (On the Application Of) v Mid Suffolk District Council & Anor [2022] EWCA Civ 1417 || Devine v Secretary of State for Levelling Up, Housing and Communities [2023] EWCA Civ 601 || Whitley Parish Council, R (On the Application Of) v North Yorkshire County Council & Anor [2023] EWCA Civ 92 || Vicente & Anor v Secretary of State for Communities and Local Government & Anor [2014] EWCA Civ 1555 || CAB Housing Limited v Secretary of State for Levelling Up, Housing and Communities & Anor [2023] EWCA Civ 194 || Sahota, R (On the Application Of) v Herefordshire Council [2022] EWCA Civ 1640 || Braithwaite and Melton Meadows Properties Ltd, R (On the Application Of) v East Suffolk Council [2022] EWCA Civ 1716 | U13: R1 | V13: partial | W13: pp. 381G–382C ([2000] 1 WLR 377) | X13: Flannery establishes that professional judges generally must give sufficient reasons so the parties understand why they won or lost and an appeal remains effective. The generated principle captures this core idea but overgeneralises it to all decisions affecting rights and omits the judicial context and qualifications. | Y13: partial | Z13: 379d4f20-62f5-403b-a082-fa36b82fe1c1_metadata_summary concerns judicial review of planning permission and citizens’ ability to challenge planning decisions. 3ff34419-ffbc-40f9-a087-a1cb1371d0e1_legal_classification identifies procedural unfairness concerning notification and residents’ opportunity to participate. | AA13: The retrieved material supports the general relevance of procedural fairness to challenges against planning decisions. However, no retrieved passage states that failure to give reasons constitutes procedural impropriety or invalidates a planning decision. The essential reason-giving premise is therefore unsupported. | AB13: 4 | AC13: 46251 | AD13: R2 | AE13: partial | AF13: [2000] 1 WLR 377 at 381G-382C (Henry LJ, four general comments); duty-holder passage citing R v Knightsbridge Crown Court ex p International Sporting Club | AG13: Ratio is the professional judge's general duty to give reasons, arising in a valuer's negligence claim; comment 1 states the duty is a function of due process and that the losing party should be left in no doubt why they lost, which the generated principle captures in substance. But the principle omits the duty-holder: Flannery concerns the court's obligation in delivering judgment, not a general entitlement of parties against any decision-maker affecting their rights, and Henry LJ notes exceptions (magistrates, summary costs discretion) and that extent depends on subject-matter (comment 3). Closer to the ratio than the "administrative settings" formulations at rows 5 and 6 because it does not relocate the duty, but the decontextualisation from judicial reasons to decisions generally is material. | AH13: no | AI13: search cmmxtwenv000304jr7vxcmpae (shared with citation_index 1); 20 records; cited authority absent and not in corpus registry; 15/20 procedural_history, 4/20 legal_classification, 1 metadata_summary (rank 1 Burkett); rank 5 Save Britain's Heritage v Davies present but matched on procedural_history; rank 17 Vicente (legal_classification: procedural unfairness, opportunity to participate) | AJ13: Flannery absent from retrieval and not in corpus registry. Fifteen of twenty records matched on procedural_history chunks listing court, lower court, judges, case number and hearing duration only, with no legal content. Four legal_classification chunks are planning-law taxonomies (Cherkley, Ashburton, Tesco Stores, Vicente); rank 17 Vicente names procedural unfairness and opportunity to participate as legal issues but states no test. Rank 5 Save Britain's Heritage v Davies is on point in its actual subject-matter (reasons for planning decisions) but the chunk retrieved is its procedural history, supplying no proposition. Nothing in the linked retrieval supports the claim that failure to give reasons can invalidate a planning decision for procedural impropriety. | AK13: 3 | AL13: 46251 | AO13: =IF(OR(V13="",AE13=""),"",IF(V13=AE13,"agree","disagree")) -> agree | AP13: =IF(OR(Y13="",AH13=""),"",IF(Y13=AH13,"agree","disagree")) -> disagree | AQ13: partial | AR13: no | AS13: Holding (partial): Ratio is the professional judge's general duty to give reasons, arising in a valuer's negligence claim; comment 1 states the duty is a function of due… Grounding (no): Flannery absent from retrieval and not in corpus registry. Fifteen of twenty records matched on procedural_history chunks listing court, lower court, judges, case number and… | AT13: =IF(B13="no","not sampled",IF(AND(V13<>"",Y13<>""),"complete","pending")) -> complete
... A99: 50 | B99: yes | C99: cmmjsmua2000q04jstd4i8p7c | D99: ca-2024-000255-ellis-v-ssj-appellant-skeleton | E99: real | F99: 1 | G99: English v Emery Reimbold & Strick Ltd [2002] EWCA Civ 605 | H99: case_law | I99: Judgements must provide adequate reasoning for legal conclusions. | J99: This applies to the determination of the adequacy of the findings in relation to A2P1 in this case. | K99: binding | L99: in_corpus_not_retrieved | M99: no | N99: yes | O99: yes | P99: yes | Q99: https://www.bailii.org/ew/cases/EWCA/Civ/2002/605.html | R99: cmmjsjnvz000k04js5ptftolc | S99: dfa97e6e-7e32-4c80-9f6f-5e4f398f9d82 || d60a5323-796e-4110-a6de-012ec16860c1 || facdee26-7310-4355-9ef5-1fd21f107f72 || c5a5edf0-4845-4195-a969-082c8b5afa2a || 36166c1f-7b4e-4e19-9f3e-ba06d04ac22a || da4b6be7-2b22-4bd1-af6b-a68873f0af8d || 7e8929e7-4b3c-4492-b8b5-e01b9ccfcf2c || 464b6335-7623-49ec-8536-df2bb3ae5a4d || b15fdd53-0222-49df-98a5-84e25904f9fd || 90f8b18f-1e00-4177-9cfb-1304fdbc0a97 || 80701211-fe03-4dc0-972a-b2e5467876b9 || 1ed4938a-8018-45b9-bf99-465d1697ff0b || cd2db340-265d-46ef-86dd-180d07c4fea9 || 57d5bf6b-b5e4-4a29-8fe8-fc6caf7108e9 || 522b4f69-32d0-44e3-9bb5-92859e5efde0 || d43e9179-fec2-4fc9-a5b0-3113b6e57fb4 || 037fedaf-bb6c-4013-9ebb-6bc7192c7525 || 0c4144ef-9642-4280-9526-95be21a99f19 || 22f5a58b-4272-4bb0-8476-e2d0333f5032 || 7614b7b3-9102-4127-baa4-ed60bb7a82ed | T99: Velyo Velev v. Bulgaria (Application No. 16032/07) || The Howard League for Penal Reform and Prisoners' Advice Service v The Lord Chancellor || Kalda v. Estonia - Access to Information Rights for Prisoners || BK & Anor v The Secretary of State for Justice [2015] EWCA Civ 1259 || Smith v Secretary of State for Justice & Ors [2014] EWCA Civ 380 || Bright & Anor v The Secretary of State for Justice || Zenati v Police of the Metropolis & Anor [2015] EWCA Civ 80 || Parratt, R (on the application of) v Parole Board || Use of Languages in Education in Belgium || Bayliss v The Parole Board of England & Wales [2014] EWCA Civ 1268 || Idira, R (On the Application Of) v The Secretary of State for the Home Department (Rev 1) [2015] EWCA Civ 1187 || AA (Poland) v Secretary of State for the Home Department [2016] EWCA Civ 620 (11 May 2016) || AE (Algeria) v Secretary of State for the Home Department || Abedin, R (On the Application Of) v Secretary of State for the Home Department [2016] EWCA Civ 296 (10 March 2016) || Catan and Others v. Moldova and Russia || Coll v Secretary of State for Justice [2015] EWCA Civ 328 || Tabbakh, R (On the Application Of) v Staffordshire And West Midlands Probation Trust & Anor || Bayliss v The Parole Board of England And Wales & Anor [2014] EWCA Civ 1631 || BB, PP, W, U & Ors v Secretary of State for the Home Department || Rowan, R (On the Application Of) v Governor of His Majesty's Prison Berwyn & Anor [2023] EWCA Civ 27 | U99: R1 | V99: yes | W99: [2002] EWCA Civ 605, [15]–[21] | X99: Judgments must provide adequate reasons for their legal conclusions. Applying that general principle to A2P1 findings is legally plausible. | Y99: partial | Z99: Velyo Velev, chunk dfa97e6e-7e32-4c80-9f6f-5e4f398f9d82_case_analysis, and Howard League concern prisoners’ Convention and education rights. | AA99: The retrieval supports the rights and A2P1 context but does not provide the English v Emery reason-giving rule. | AB99: 5 | AC99: 46250 | AD99: R2 | AE99: yes | AF99: [15]–[20], especially [16] and [19] | AG99: The judgment confirms a contextual duty to give reasons sufficient to show why the judge reached the decision; it does not require discussion of every argument. | AH99: no | AI99: Top linked retrievals: 1. Velyo Velev v. Bulgaria (Application No. 16032/07) — Analysis of the significance and implications of the ruling for future cases and legal interpretations. | 2. The Howard League for Penal Reform and Prisoners' Advice Service v The Lord Chancellor — Analysis of the case's precedent value and implications for future legal contexts. | 3. Kalda v. Estonia - Access to Information Rights for Prisoners — Analyzing the implications of the case's ruling on future legal interpretations of rights under the Convention, especially concerning prisoners.. The cited authority itself was not retrieved. | AJ99: Linked search cmmjsjnvz000k04js5ptftolc did not retrieve the cited authority. Under Codebook §5, this warrants reasoning_grounding = no; the returned chunks do not supply the relied-upon authority for this application. | AK99: 4 | AL99: 46250 | AO99: =IF(OR(V99="",AE99=""),"",IF(V99=AE99,"agree","disagree")) -> agree | AP99: =IF(OR(Y99="",AH99=""),"",IF(Y99=AH99,"agree","disagree")) -> disagree | AQ99: yes | AR99: no | AS99: Holding (yes): The judgment confirms a contextual duty to give reasons sufficient to show why the judge reached the decision; it does not require discussion of every… Grounding (no): Linked search cmmjsjnvz000k04js5ptftolc did not retrieve the cited authority. Under Codebook §5, this warrants reasoning_grounding = no; the returned chunks do not supply the… | AT99: =IF(B99="no","not sampled",IF(AND(V99<>"",Y99<>""),"complete","pending")) -> complete
B100: no | C100: cmlzrzxca000304l2qk1vevzx | D100: skeleton-args-ca2023002207-ce0aafdf6d7e5716 | E100: synthetic | F100: 1 | G100: [2004] 1 WLR 1057 | H100: case_law | I100: Duty of care in highway maintenance and inspections evaluated. | J100: The principles established guide the expectations for highway authority inspections. | K100: binding | L100: retrieved_id_citation_mismatch | M100: no | N100: yes | O100: yes | P100: yes | Q100: https://publications.parliament.uk/pa/ld200304/ldjudgmt/jd040401/gorr-1.htm | R100: cmlzry90i000b04laxzwy3gcm | S100: 70d43223-0ec6-458b-b052-bdc295e0d6ec || 3b14442e-37b0-455c-a24f-a53a55c9f700 || 4685ad0e-87e7-4f59-8991-823ab27d9393 || 29b57846-31cd-4592-b0bb-d49f37fcc7bb || e16d7203-6f9e-4896-96e0-d021cb6f5579 || 9289473a-6889-4929-925d-2d6d66b75e86 || 7351e867-1c92-49d6-a602-686678f60a5f || 26a8199d-2c00-43b8-815c-036d01dbe2a6 || 6948a4df-0a45-4ddc-ae3d-8eafee44976a || 1ae781af-c482-402d-b18c-8d4c33432b24 | T100: Brown & Ors v South West Lakes Trust & Ors [2022] EWCA Civ 18 || Humphrey v Aegis Defence Services Ltd & Anor [2016] EWCA Civ 11 || Tindall & Anor v Chief Constable of Thames Valley Police & Anor [2022] EWCA Civ 25 || Dean and Chapter of Rochester Cathedral v Debell [2016] EWCA Civ 1094 || Edwards v London Borough of Sutton [2016] EWCA Civ 1005 || Secretary of State for Justice v Black [2016] EWCA Civ 125 || Howmet Limited v Economy Devices Limited & Ors [2016] EWCA Civ 847 || English Heritage v Taylor [2016] EWCA Civ 448 || Scott v Gavigan [2016] EWCA Civ 544 || HXA v Surrey County Council; YXA v Wolverhampton City Council (England and Wales Court of Appeal (Civil Division)) | AO100: =IF(OR(V100="",AE100=""),"",IF(V100=AE100,"agree","disagree")) | AP100: =IF(OR(Y100="",AH100=""),"",IF(Y100=AH100,"agree","disagree")) | AT100: =IF(B100="no","not sampled",IF(AND(V100<>"",Y100<>""),"complete","pending")) -> not sampled
B101: no | C101: cmlzrzxca000304l2qk1vevzx | D101: skeleton-args-ca2023002207-ce0aafdf6d7e5716 | E101: synthetic | F101: 2 | G101: [2015] UKSC 5 | H101: case_law | I101: Contributory negligence principles delineated in examining claimant's actions prior to incidents. | J101: Guiding conclusions on responsibility of claimants when injuries occur. | K101: binding | L101: retrieved_id_citation_mismatch | M101: no | N101: yes | O101: yes | P101: yes | Q101: https://www.supremecourt.uk/cases/uksc-2014-0070 | R101: cmlzry90i000b04laxzwy3gcm | S101: 70d43223-0ec6-458b-b052-bdc295e0d6ec || 3b14442e-37b0-455c-a24f-a53a55c9f700 || 4685ad0e-87e7-4f59-8991-823ab27d9393 || 29b57846-31cd-4592-b0bb-d49f37fcc7bb || e16d7203-6f9e-4896-96e0-d021cb6f5579 || 9289473a-6889-4929-925d-2d6d66b75e86 || 7351e867-1c92-49d6-a602-686678f60a5f || 26a8199d-2c00-43b8-815c-036d01dbe2a6 || 6948a4df-0a45-4ddc-ae3d-8eafee44976a || 1ae781af-c482-402d-b18c-8d4c33432b24 | T101: Brown & Ors v South West Lakes Trust & Ors [2022] EWCA Civ 18 || Humphrey v Aegis Defence Services Ltd & Anor [2016] EWCA Civ 11 || Tindall & Anor v Chief Constable of Thames Valley Police & Anor [2022] EWCA Civ 25 || Dean and Chapter of Rochester Cathedral v Debell [2016] EWCA Civ 1094 || Edwards v London Borough of Sutton [2016] EWCA Civ 1005 || Secretary of State for Justice v Black [2016] EWCA Civ 125 || Howmet Limited v Economy Devices Limited & Ors [2016] EWCA Civ 847 || English Heritage v Taylor [2016] EWCA Civ 448 || Scott v Gavigan [2016] EWCA Civ 544 || HXA v Surrey County Council; YXA v Wolverhampton City Council (England and Wales Court of Appeal (Civil Division)) | AO101: =IF(OR(V101="",AE101=""),"",IF(V101=AE101,"agree","disagree")) | AP101: =IF(OR(Y101="",AH101=""),"",IF(Y101=AH101,"agree","disagree")) | AT101: =IF(B101="no","not sampled",IF(AND(V101<>"",Y101<>""),"complete","pending")) -> not sampled
B102: no | C102: cmm3b1g6j000j04jt8w2u9z6w | D102: skeleton-args-ca2025000412-e17d5e10793fe216 | E102: synthetic | F102: 1 | G102: Flannery v Halifax Estate Agencies Ltd [2000] 1 WLR 377 | H102: case_law | I102: Duty to provide adequate reasons for decisions that may affect individual rights. | J102: Relevant to ensuring justifications for educational restrictions are properly articulated based on rights impact. | K102: binding | L102: not_found_in_corpus_registry | M102: no | N102: no | O102: yes | P102: yes | Q102: https://www.bailii.org/ew/cases/EWCA/Civ/1999/811.html | R102: cmm3azb8t000d04jtx7he2awl | S102: 02409749-c305-4c56-ad34-3447c9c2371b || 7614b7b3-9102-4127-baa4-ed60bb7a82ed || 250a2de0-32f3-4ce2-8b1f-ee964131ee78 || 36166c1f-7b4e-4e19-9f3e-ba06d04ac22a || 57d5bf6b-b5e4-4a29-8fe8-fc6caf7108e9 || 88f81617-3d05-4cec-a001-5edf306bd117 || 9cd8bb4c-43ff-49b2-8bc4-b8df5f3727d6 || 51cdf21d-2e8d-4694-805d-5758e7941b6e || 47e733e4-8b4c-42d7-a983-6af18563acb8 || 720cde29-16c8-41e8-9899-7ac2abcb1cc1 | T102: Tigere, R (On the Application Of) v Secretary of State for Business, Innovation And Skills || Rowan, R (On the Application Of) v Governor of His Majesty's Prison Berwyn & Anor [2023] EWCA Civ 27 || Brooks, R (on the application of) v The Independent Adjudicator & Anor [2016] EWCA Civ 1033 || Smith v Secretary of State for Justice & Ors [2014] EWCA Civ 380 || Abedin, R (On the Application Of) v Secretary of State for the Home Department [2016] EWCA Civ 296 (10 March 2016) || R (on the application of) SPM v Secretary of State for the Home Department [2023] EWCA Civ 764 || Weddle (R on the application of) v The Secretary of State for Justice [2016] EWCA Civ 38 (Court of Appeal, Civil Division) || Hallam & Anor, R (on the applications of) v The Secretary of State for Justice (rev 1) [2016] EWCA Civ 355 || Public and Commercial Services Union (and others) v Secretary of State for the Home Department || FI v Secretary of State for the Home Department [2014] EWCA Civ 1272 | AO102: =IF(OR(V102="",AE102=""),"",IF(V102=AE102,"agree","disagree")) | AP102: =IF(OR(Y102="",AH102=""),"",IF(Y102=AH102,"agree","disagree")) | AT102: =IF(B102="no","not sampled",IF(AND(V102<>"",Y102<>""),"complete","pending")) -> not sampled
B103: no | C103: cmm3b1g6j000j04jt8w2u9z6w | D103: skeleton-args-ca2025000412-e17d5e10793fe216 | E103: synthetic | F103: 2 | G103: English v Emery Reimbold & Strick Ltd [2002] EWCA Civ 605 | H103: case_law | I103: Adequacy of reasons in judgments. | J103: Relevant to the necessity for transparency in decisions affecting prisoner education in light of restrictive measures. | K103: binding | L103: in_corpus_not_retrieved | M103: no | N103: yes | O103: yes | P103: yes | Q103: https://www.bailii.org/ew/cases/EWCA/Civ/2002/605.html | R103: cmm3azb8t000d04jtx7he2awl | S103: 02409749-c305-4c56-ad34-3447c9c2371b || 7614b7b3-9102-4127-baa4-ed60bb7a82ed || 250a2de0-32f3-4ce2-8b1f-ee964131ee78 || 36166c1f-7b4e-4e19-9f3e-ba06d04ac22a || 57d5bf6b-b5e4-4a29-8fe8-fc6caf7108e9 || 88f81617-3d05-4cec-a001-5edf306bd117 || 9cd8bb4c-43ff-49b2-8bc4-b8df5f3727d6 || 51cdf21d-2e8d-4694-805d-5758e7941b6e || 47e733e4-8b4c-42d7-a983-6af18563acb8 || 720cde29-16c8-41e8-9899-7ac2abcb1cc1 | T103: Tigere, R (On the Application Of) v Secretary of State for Business, Innovation And Skills || Rowan, R (On the Application Of) v Governor of His Majesty's Prison Berwyn & Anor [2023] EWCA Civ 27 || Brooks, R (on the application of) v The Independent Adjudicator & Anor [2016] EWCA Civ 1033 || Smith v Secretary of State for Justice & Ors [2014] EWCA Civ 380 || Abedin, R (On the Application Of) v Secretary of State for the Home Department [2016] EWCA Civ 296 (10 March 2016) || R (on the application of) SPM v Secretary of State for the Home Department [2023] EWCA Civ 764 || Weddle (R on the application of) v The Secretary of State for Justice [2016] EWCA Civ 38 (Court of Appeal, Civil Division) || Hallam & Anor, R (on the applications of) v The Secretary of State for Justice (rev 1) [2016] EWCA Civ 355 || Public and Commercial Services Union (and others) v Secretary of State for the Home Department || FI v Secretary of State for the Home Department [2014] EWCA Civ 1272 | AO103: =IF(OR(V103="",AE103=""),"",IF(V103=AE103,"agree","disagree")) | AP103: =IF(OR(Y103="",AH103=""),"",IF(Y103=AH103,"agree","disagree")) | AT103: =IF(B103="no","not sampled",IF(AND(V103<>"",Y103<>""),"complete","pending")) -> not sampled
B104: no | C104: cmmdkjytd000304jl24cdxqvp | D104: skeleton-args-ca2023004634-299a4a730fe1f43a | E104: synthetic | F104: 1 | G104: English v Emery Reimbold & Strick Ltd [2002] EWCA Civ 605 | H104: case_law | I104: A decision requires a clear reasoning process showcasing why conclusions were reached. | J104: The necessity for comprehensive reasons for judicial conclusions supports claims in landlord-tenant disputes regarding possession. | K104: binding | L104: in_corpus_not_retrieved | M104: no | N104: yes | O104: yes | P104: yes | Q104: https://www.bailii.org/ew/cases/EWCA/Civ/2002/605.html | R104: cmmdjmbqo000b04js13axm03c | S104: 18a014eb-e365-4420-b07a-dfdd42f053ec || 00167e1d-845c-4a1d-b17c-1c91c10b2c37 || b8f5594c-ac32-4dd3-804a-fd0c938c4401 || 39df6304-6d5c-4744-8f1a-adcd4015ef46 || 945cd74c-6126-4ef5-ae71-7c0099a28f2b || 093c1223-0ae8-4284-9849-0aa54158efc1 || 263eee40-14b4-40aa-8b6d-47da6b0fa9b3 || 7079fc72-6050-4668-ac32-14c3ce1d3b5c || 84abacd4-ac9e-4547-9c6c-c9f49ad1f96d || 63c13b59-95b3-46e6-bcfd-eef08df13985 || ccb176da-f583-47e8-b2a6-cc3aadd7833c || 1b3f1357-0731-4894-9c17-a958eecd366a || f0cad471-e222-49db-b138-c99f671aff4f || 20883fdd-3d62-402d-b87e-d07099a0aace || d9167d92-3e2d-462b-b1dd-0c42056c65b9 || f12362ca-9214-46d6-8a2a-5ddadac29884 || 2702fe29-d7f0-4cc6-8c3f-b840406bb7a2 || 98a141f0-f889-4521-86c4-1b8648867286 || 38228566-f138-413e-98cf-b8c35fe9afaa || 5315bcf1-31e2-4c09-9977-ecd80a7a8ec7 | T104: Freifeld & Anor v West Kensington Court Ltd [2015] EWCA Civ 806 || Bank of New York Mellon (International) Limited v Cine-UK Limited [2022] EWCA Civ 1021 || Topland Portfolio No 1 Ltd v Smiths News Trading Ltd [2014] EWCA Civ 18 || Nizami v Dezyanian [2015] EWCA Civ 632 || Bishop v Chhokar [2015] EWCA Civ 24 || Hough v Greathall Ltd [2015] EWCA Civ 23 || Youssefi v Mussellwhite [2014] EWCA Civ 885 || Tibber v Buckley & Anor [2015] EWCA Civ 1294 || Anselm v Buckle & Anor [2014] EWCA Civ 311 || SWA Developments Ltd v Burke [2016] EWCA Civ 389 || Marks And Spencer Plc v BNP Paribas Securities Services Trust Company (Jersey) Ltd & Anor [2014] EWCA Civ 603 || Magnic Ltd v Ul-Hassan & Anor [2015] EWCA Civ 224 || Cawsand Fort Management Company v Kane & Ors [2015] EWCA Civ 1520 || Morshead Mansions Ltd v Di Marco || Chaplair Ltd v Kumari [2015] EWCA Civ 798 || Innerspaces Self Storage Ltd v Harding & Ors [2014] EWCA Civ 46 || Peel Land and Property (Ports No. 3) Ltd v TS Sheerness Ltd || Silver Fern Microlights Ltd v Jones & Ors [2016] EWCA Civ 277 || Erimus Housing Ltd v Barclays Wealth Trustees (Jersey) Ltd & Ors [2014] EWCA Civ 303 || South Essex Partnership University NHS Foundation Trust v Laindon Holdings Ltd [2016] EWCA Civ 377 | AO104: =IF(OR(V104="",AE104=""),"",IF(V104=AE104,"agree","disagree")) | AP104: =IF(OR(Y104="",AH104=""),"",IF(Y104=AH104,"agree","disagree")) | AT104: =IF(B104="no","not sampled",IF(AND(V104<>"",Y104<>""),"complete","pending")) -> not sampled
B105: no | C105: cmmdkjytd000304jl24cdxqvp | D105: skeleton-args-ca2023004634-299a4a730fe1f43a | E105: synthetic | F105: 2 | G105: Flannery v Halifax Estate Agencies Ltd [2000] 1 WLR 377 | H105: case_law | I105: Parties must receive clarity on judicial reasons to understand the basis for decisions. | J105: Ensures that parties to tenancy agreements can discern from rulings how particular facts led to determinations on breaches. | K105: binding | L105: not_found_in_corpus_registry | M105: no | N105: no | O105: yes | P105: yes | Q105: https://www.bailii.org/ew/cases/EWCA/Civ/1999/811.html | R105: cmmdjmbqo000b04js13axm03c | S105: 18a014eb-e365-4420-b07a-dfdd42f053ec || 00167e1d-845c-4a1d-b17c-1c91c10b2c37 || b8f5594c-ac32-4dd3-804a-fd0c938c4401 || 39df6304-6d5c-4744-8f1a-adcd4015ef46 || 945cd74c-6126-4ef5-ae71-7c0099a28f2b || 093c1223-0ae8-4284-9849-0aa54158efc1 || 263eee40-14b4-40aa-8b6d-47da6b0fa9b3 || 7079fc72-6050-4668-ac32-14c3ce1d3b5c || 84abacd4-ac9e-4547-9c6c-c9f49ad1f96d || 63c13b59-95b3-46e6-bcfd-eef08df13985 || ccb176da-f583-47e8-b2a6-cc3aadd7833c || 1b3f1357-0731-4894-9c17-a958eecd366a || f0cad471-e222-49db-b138-c99f671aff4f || 20883fdd-3d62-402d-b87e-d07099a0aace || d9167d92-3e2d-462b-b1dd-0c42056c65b9 || f12362ca-9214-46d6-8a2a-5ddadac29884 || 2702fe29-d7f0-4cc6-8c3f-b840406bb7a2 || 98a141f0-f889-4521-86c4-1b8648867286 || 38228566-f138-413e-98cf-b8c35fe9afaa || 5315bcf1-31e2-4c09-9977-ecd80a7a8ec7 | T105: Freifeld & Anor v West Kensington Court Ltd [2015] EWCA Civ 806 || Bank of New York Mellon (International) Limited v Cine-UK Limited [2022] EWCA Civ 1021 || Topland Portfolio No 1 Ltd v Smiths News Trading Ltd [2014] EWCA Civ 18 || Nizami v Dezyanian [2015] EWCA Civ 632 || Bishop v Chhokar [2015] EWCA Civ 24 || Hough v Greathall Ltd [2015] EWCA Civ 23 || Youssefi v Mussellwhite [2014] EWCA Civ 885 || Tibber v Buckley & Anor [2015] EWCA Civ 1294 || Anselm v Buckle & Anor [2014] EWCA Civ 311 || SWA Developments Ltd v Burke [2016] EWCA Civ 389 || Marks And Spencer Plc v BNP Paribas Securities Services Trust Company (Jersey) Ltd & Anor [2014] EWCA Civ 603 || Magnic Ltd v Ul-Hassan & Anor [2015] EWCA Civ 224 || Cawsand Fort Management Company v Kane & Ors [2015] EWCA Civ 1520 || Morshead Mansions Ltd v Di Marco || Chaplair Ltd v Kumari [2015] EWCA Civ 798 || Innerspaces Self Storage Ltd v Harding & Ors [2014] EWCA Civ 46 || Peel Land and Property (Ports No. 3) Ltd v TS Sheerness Ltd || Silver Fern Microlights Ltd v Jones & Ors [2016] EWCA Civ 277 || Erimus Housing Ltd v Barclays Wealth Trustees (Jersey) Ltd & Ors [2014] EWCA Civ 303 || South Essex Partnership University NHS Foundation Trust v Laindon Holdings Ltd [2016] EWCA Civ 377 | AO105: =IF(OR(V105="",AE105=""),"",IF(V105=AE105,"agree","disagree")) | AP105: =IF(OR(Y105="",AH105=""),"",IF(Y105=AH105,"agree","disagree")) | AT105: =IF(B105="no","not sampled",IF(AND(V105<>"",Y105<>""),"complete","pending")) -> not sampled
B106: no | C106: cmmdkjytd000304jl24cdxqvp | D106: skeleton-args-ca2023004634-299a4a730fe1f43a | E106: synthetic | F106: 3 | G106: Senior Courts Act 1981, s.35A | H106: legislation_or_rule | I106: This section provides legal authority for interest to be applied in cases of debt recovery. | J106: Applicable in claims for arrears and damages arising from breach of lease contracts. | K106: binding | L106: not_applicable_non_case_reference | M106: no | N106: no | O106: n/a | P106: yes | Q106: https://www.legislation.gov.uk/ukpga/1981/54/section/35A | R106: cmmdjmbqo000b04js13axm03c | S106: 18a014eb-e365-4420-b07a-dfdd42f053ec || 00167e1d-845c-4a1d-b17c-1c91c10b2c37 || b8f5594c-ac32-4dd3-804a-fd0c938c4401 || 39df6304-6d5c-4744-8f1a-adcd4015ef46 || 945cd74c-6126-4ef5-ae71-7c0099a28f2b || 093c1223-0ae8-4284-9849-0aa54158efc1 || 263eee40-14b4-40aa-8b6d-47da6b0fa9b3 || 7079fc72-6050-4668-ac32-14c3ce1d3b5c || 84abacd4-ac9e-4547-9c6c-c9f49ad1f96d || 63c13b59-95b3-46e6-bcfd-eef08df13985 || ccb176da-f583-47e8-b2a6-cc3aadd7833c || 1b3f1357-0731-4894-9c17-a958eecd366a || f0cad471-e222-49db-b138-c99f671aff4f || 20883fdd-3d62-402d-b87e-d07099a0aace || d9167d92-3e2d-462b-b1dd-0c42056c65b9 || f12362ca-9214-46d6-8a2a-5ddadac29884 || 2702fe29-d7f0-4cc6-8c3f-b840406bb7a2 || 98a141f0-f889-4521-86c4-1b8648867286 || 38228566-f138-413e-98cf-b8c35fe9afaa || 5315bcf1-31e2-4c09-9977-ecd80a7a8ec7 | T106: Freifeld & Anor v West Kensington Court Ltd [2015] EWCA Civ 806 || Bank of New York Mellon (International) Limited v Cine-UK Limited [2022] EWCA Civ 1021 || Topland Portfolio No 1 Ltd v Smiths News Trading Ltd [2014] EWCA Civ 18 || Nizami v Dezyanian [2015] EWCA Civ 632 || Bishop v Chhokar [2015] EWCA Civ 24 || Hough v Greathall Ltd [2015] EWCA Civ 23 || Youssefi v Mussellwhite [2014] EWCA Civ 885 || Tibber v Buckley & Anor [2015] EWCA Civ 1294 || Anselm v Buckle & Anor [2014] EWCA Civ 311 || SWA Developments Ltd v Burke [2016] EWCA Civ 389 || Marks And Spencer Plc v BNP Paribas Securities Services Trust Company (Jersey) Ltd & Anor [2014] EWCA Civ 603 || Magnic Ltd v Ul-Hassan & Anor [2015] EWCA Civ 224 || Cawsand Fort Management Company v Kane & Ors [2015] EWCA Civ 1520 || Morshead Mansions Ltd v Di Marco || Chaplair Ltd v Kumari [2015] EWCA Civ 798 || Innerspaces Self Storage Ltd v Harding & Ors [2014] EWCA Civ 46 || Peel Land and Property (Ports No. 3) Ltd v TS Sheerness Ltd || Silver Fern Microlights Ltd v Jones & Ors [2016] EWCA Civ 277 || Erimus Housing Ltd v Barclays Wealth Trustees (Jersey) Ltd & Ors [2014] EWCA Civ 303 || South Essex Partnership University NHS Foundation Trust v Laindon Holdings Ltd [2016] EWCA Civ 377 | AO106: =IF(OR(V106="",AE106=""),"",IF(V106=AE106,"agree","disagree")) | AP106: =IF(OR(Y106="",AH106=""),"",IF(Y106=AH106,"agree","disagree")) | AT106: =IF(B106="no","not sampled",IF(AND(V106<>"",Y106<>""),"complete","pending")) -> not sampled
B107: no | C107: cmsbr6p4p001704l4z7u6108h | D107: ca-2024-000806-hippodrome-casino-ltd-v-hmrc-appellant-skeleton | E107: real | F107: 1 | G107: HMRC v Volkswagen Financial Services | H107: case_law | I107: Conditions under which departure from the standard method is permitted. | J107: Assessment of dual-use implications in VAT recovery. | K107: binding | L107: not_found_in_corpus_registry | M107: no | N107: no | O107: yes | P107: yes | Q107: https://infocuria.curia.europa.eu/tabs/redirect/juris/liste.jsf?num=C-153%2F17 | R107: cmsbr5rlu001104l45rnkob9p | S107: b9498527-3250-49cd-9d8e-ed7c0dda200e || 4ce131bd-2742-476d-a37a-0727c7980ebc || cd495d17-4a70-4b1a-ad32-713927ce6d8e || bfa85128-3daf-4206-8d8f-d2dc5f32ab27 || 5be7238d-b78e-4194-90ec-c036be53b377 || 88bb4a5f-a731-48de-9e0d-c8537ea915a0 || 5c2719bb-df7d-4d55-a473-dd5087c1d2e8 || 38eac6a9-6018-40fe-9d73-ab111162e65d || 52d1be75-0d9f-4b51-b6fc-183cfce77220 || 3d0c1d2a-8c23-4f19-a7ba-587826b75f45 || 53011b43-2d84-4830-953a-1b5b550f4f67 || 2f2ce488-73d0-4422-abcd-2b014a9e52d1 || d18a7e9c-a930-43c5-a32d-bc205ffe00f8 || dc715706-f35f-4a5c-8ad7-a824c23f5260 || ff706e01-2911-4522-b7e2-4cb4ed7e3992 || fb90f1ad-6132-491d-be89-35324c43b367 || 690f2978-b410-456d-8745-0fd24cea8bf6 || 34f65455-ab57-4843-8247-69713c6d5d1d || c009622e-9e72-4c9c-a114-e74deba95ac2 || 7253e952-4693-4c28-8c6d-f176b4e6f194 | T107: Volkswagen Financial Services (UK) Ltd v HM Revenue & Customs || Revenue and Customs v Mercedes-Benz Financial Services UK Ltd || Birmingham Hippodrome Theatre Trust Ltd v Revenue And Customs || Regency Factors Plc v HM Revenue & Customs (Rev1) [2022] EWCA Civ 103 || Leeds City Council v HM Revenue and Customs [2015] EWCA Civ 1293 || Littlewoods Ltd & Ors v HM Revenue and Customs [2015] EWCA Civ 515 || Reed Employment Ltd v HM Revenue and Customs || ING Intermediate Holdings Ltd v HM Revenue and Customs [2017] EWCA Civ 2111 || Tower Bridge GP Ltd v Revenue And Customs [2022] EWCA Civ 998 (18 July 2022) || University of Huddersfield Higher Education Corporation v HM Revenue and Customs || The Quentin Skinner 2015 Settlement L & Ors v HM Revenue and Customs (Entrepeneurs' Relief) [2022] EWCA Civ 1222 || Totel Limited v HM Revenue and Customs [2016] EWCA Civ 1310 || SAE Education Ltd v Revenue And Customs || Associated Newspapers Ltd v HM Revenue & Customs [2017] EWCA Civ 54 || Revenue And Customs v The Open University [2016] EWCA Civ 114 || HM Revenue and Customs v Brockenhurst College [2015] EWCA Civ 1196 || Greenspace (UK) Ltd v Commissioners for HM Revenue and Customs [2023] EWCA Civ 106 || Iveco Ltd v Revenue And Customs || Revenue and Customs (HMRC) v London Clubs Management Ltd || HMRC v GMAC (UK) Plc [2016] EWCA Civ 1015 (Court of Appeal, Civil Division) | AO107: =IF(OR(V107="",AE107=""),"",IF(V107=AE107,"agree","disagree")) | AP107: =IF(OR(Y107="",AH107=""),"",IF(Y107=AH107,"agree","disagree")) | AT107: =IF(B107="no","not sampled",IF(AND(V107<>"",Y107<>""),"complete","pending")) -> not sampled
B108: no | C108: cmsbsp3em001104ji2u62id7q | D108: ca-2024-000624 and ca-2024-000625-the-royal-embassy-of-saudi-arabia-appellant-skeleton | E108: real | F108: 1 | G108: [2002] EWCA Civ 605 | H108: case_law | I108: Adequacy of reasons in judgments are essential for meaningful appellate review. | J108: Judgments should thoroughly clarify the rationale for outcomes to support further appeals. | K108: binding | L108: in_corpus_not_retrieved | M108: no | N108: yes | O108: yes | P108: yes | Q108: https://www.bailii.org/ew/cases/EWCA/Civ/2002/605.html | R108: cmsbso1ez000v04jiujckeft7 | S108: 99e499ed-5641-4f75-8c33-a3c4e6031823 || 2e88bc46-6293-4125-beac-79bb041f2d4c || 48a6c9aa-6aaf-46f0-a0a1-db486992f637 || f1db17d9-c809-4f44-a350-a7c506f9683c || 47b7ca59-4dae-4e38-9b19-66a4d28a1d9e || d2d218fb-5cb2-4d42-9835-3e293c334cd3 || ee5ed42e-d552-49f7-ae34-ee6ddf99593b || 56ebcb77-2936-4ffe-9d4e-4334c394df46 || 95a09909-d350-4cc6-8e33-4153cfe28a7f || f867230d-587a-4c73-ba9b-3ab93ed9d9d7 || 53e4e4d6-7fe9-4d97-a56c-d55311748151 || ce109720-ac8c-4042-bd77-82733a79fb6c || 215b4f1f-c45b-4b5a-83c7-d9ecf0c27585 || 7650f4cb-dc69-470f-a3c0-941784304d41 || 806f118b-d6b0-4939-ad11-753dafd57638 || 7107ec67-0fe1-4e2a-a665-6949d1c2b554 || ef2a3b5f-c840-4290-9574-fe29eee1c165 || 7cce4927-35a4-4b74-90f4-ac2262bb34d7 || 3a069494-6968-477a-a4ad-002ee5f30904 || 015f5896-7d13-46d4-8c6d-5c7317ecf054 | T108: Argentum Exploration Limited v The Silver and all persons claiming to be interested in and/or to have rights in respect of, the Silver [2022] EWCA Civ 1318 || Sayn-Wittgenstein-Sayn v HM Juan Carlos Alfonso Victor María de Borbón y Borbón (Rev1) [2022] EWCA Civ 1595 || Benkharbouche & Anor v Embassy of the Republic of Sudan || Reyes & Anor v Al-Malki & Anor || Belhaj & Anor v Straw & Ors [2014] EWCA Civ 1394 || HRH Prince Abdul Aziz Bin Fahd Bin Abdul Aziz v Harb || The United States of America v Nolan || IPCO (Nigeria) Ltd v Nigerian National Petroleum Corporation [2015] EWCA Civ 1144 || Bestfort Developments LLP & Ors v Ras Al Khaimah Investment Authority & Ors [2016] EWCA Civ 1099 || Zubaydah v Foreign and Commonwealth Office & Ors [2022] EWCA Civ 334 (Court of Appeal, Civil Division) || Yapp v Foreign and Commonwealth Office || London Borough of Croydon v Y [2016] EWCA Civ 398 || R3 v Secretary of State for the Home Department [2023] EWCA Civ 169 || Al-Saadoon & Ors v The Secretary of State for Defence & Ors; Rahmatullah & Anr v Secretary of State for Defence & Anr [2016] EWCA Civ 811 (Admin Court of Appeal, Civil Division) || Nayif v The High Commission of Brunei Darussalam [2014] EWCA Civ 1521 || Sayn-Wittgenstein-Sayn v His Majesty Juan Carlos Alfonso Victor Maria de Borbón y Borbón [2022] EWCA Civ 1052 || Secretary of State for the Home Department v Lisa Smith [2023] EWCA Civ 376 || C7 v Secretary of State for the Home Department [2023] EWCA Civ 265 || Ali v Washwood Heath Technology College & Ors [2014] EWCA Civ 97 || Al-Juffali v Estrada [2016] EWCA Civ 176 | AO108: =IF(OR(V108="",AE108=""),"",IF(V108=AE108,"agree","disagree")) | AP108: =IF(OR(Y108="",AH108=""),"",IF(Y108=AH108,"agree","disagree")) | AT108: =IF(B108="no","not sampled",IF(AND(V108<>"",Y108<>""),"complete","pending")) -> not sampled
B109: no | C109: cmsbsp3em001104ji2u62id7q | D109: ca-2024-000624 and ca-2024-000625-the-royal-embassy-of-saudi-arabia-appellant-skeleton | E109: real | F109: 2 | G109: [2000] 1 WLR 377 | H109: case_law | I109: Expectations on judges to provide adequate reasons under general accident and common law principles. | J109: Effective reason-giving could substantially shape the interpretations of immunity applications vis-à-vis employment claims. | K109: binding | L109: not_found_in_corpus_registry | M109: no | N109: no | O109: yes | P109: yes | Q109: https://www.bailii.org/ew/cases/EWCA/Civ/1999/811.html | R109: cmsbso1ez000v04jiujckeft7 | S109: 99e499ed-5641-4f75-8c33-a3c4e6031823 || 2e88bc46-6293-4125-beac-79bb041f2d4c || 48a6c9aa-6aaf-46f0-a0a1-db486992f637 || f1db17d9-c809-4f44-a350-a7c506f9683c || 47b7ca59-4dae-4e38-9b19-66a4d28a1d9e || d2d218fb-5cb2-4d42-9835-3e293c334cd3 || ee5ed42e-d552-49f7-ae34-ee6ddf99593b || 56ebcb77-2936-4ffe-9d4e-4334c394df46 || 95a09909-d350-4cc6-8e33-4153cfe28a7f || f867230d-587a-4c73-ba9b-3ab93ed9d9d7 || 53e4e4d6-7fe9-4d97-a56c-d55311748151 || ce109720-ac8c-4042-bd77-82733a79fb6c || 215b4f1f-c45b-4b5a-83c7-d9ecf0c27585 || 7650f4cb-dc69-470f-a3c0-941784304d41 || 806f118b-d6b0-4939-ad11-753dafd57638 || 7107ec67-0fe1-4e2a-a665-6949d1c2b554 || ef2a3b5f-c840-4290-9574-fe29eee1c165 || 7cce4927-35a4-4b74-90f4-ac2262bb34d7 || 3a069494-6968-477a-a4ad-002ee5f30904 || 015f5896-7d13-46d4-8c6d-5c7317ecf054 | T109: Argentum Exploration Limited v The Silver and all persons claiming to be interested in and/or to have rights in respect of, the Silver [2022] EWCA Civ 1318 || Sayn-Wittgenstein-Sayn v HM Juan Carlos Alfonso Victor María de Borbón y Borbón (Rev1) [2022] EWCA Civ 1595 || Benkharbouche & Anor v Embassy of the Republic of Sudan || Reyes & Anor v Al-Malki & Anor || Belhaj & Anor v Straw & Ors [2014] EWCA Civ 1394 || HRH Prince Abdul Aziz Bin Fahd Bin Abdul Aziz v Harb || The United States of America v Nolan || IPCO (Nigeria) Ltd v Nigerian National Petroleum Corporation [2015] EWCA Civ 1144 || Bestfort Developments LLP & Ors v Ras Al Khaimah Investment Authority & Ors [2016] EWCA Civ 1099 || Zubaydah v Foreign and Commonwealth Office & Ors [2022] EWCA Civ 334 (Court of Appeal, Civil Division) || Yapp v Foreign and Commonwealth Office || London Borough of Croydon v Y [2016] EWCA Civ 398 || R3 v Secretary of State for the Home Department [2023] EWCA Civ 169 || Al-Saadoon & Ors v The Secretary of State for Defence & Ors; Rahmatullah & Anr v Secretary of State for Defence & Anr [2016] EWCA Civ 811 (Admin Court of Appeal, Civil Division) || Nayif v The High Commission of Brunei Darussalam [2014] EWCA Civ 1521 || Sayn-Wittgenstein-Sayn v His Majesty Juan Carlos Alfonso Victor Maria de Borbón y Borbón [2022] EWCA Civ 1052 || Secretary of State for the Home Department v Lisa Smith [2023] EWCA Civ 376 || C7 v Secretary of State for the Home Department [2023] EWCA Civ 265 || Ali v Washwood Heath Technology College & Ors [2014] EWCA Civ 97 || Al-Juffali v Estrada [2016] EWCA Civ 176 | AO109: =IF(OR(V109="",AE109=""),"",IF(V109=AE109,"agree","disagree")) | AP109: =IF(OR(Y109="",AH109=""),"",IF(Y109=AH109,"agree","disagree")) | AT109: =IF(B109="no","not sampled",IF(AND(V109<>"",Y109<>""),"complete","pending")) -> not sampled
B110: no | C110: cmsbsqcqm001d04ji3ses9ih9 | D110: ca-2024-000624 and ca-2024-000625-the-royal-embassy-of-saudi-arabia-appellant-skeleton | E110: real | F110: 1 | G110: Benkharbouche v Embassy of the Republic of Sudan [2017] ICR 1327 | H110: case_law | I110: Distinction between governmental and non-governmental functions relevant to claims against foreign entities. | J110: Applicable in determining state immunity for employment functions, particularly in the embassy context. | K110: binding | L110: retrieved_and_cited | M110: yes | N110: yes | O110: yes | P110: yes | Q110: https://www.supremecourt.uk/cases/uksc-2015-0063 | R110: cmsbsp6wa001704jitdvkybp9 | S110: 99e499ed-5641-4f75-8c33-a3c4e6031823 || 2e88bc46-6293-4125-beac-79bb041f2d4c || 48a6c9aa-6aaf-46f0-a0a1-db486992f637 || f1db17d9-c809-4f44-a350-a7c506f9683c || 47b7ca59-4dae-4e38-9b19-66a4d28a1d9e || d2d218fb-5cb2-4d42-9835-3e293c334cd3 || ee5ed42e-d552-49f7-ae34-ee6ddf99593b || 56ebcb77-2936-4ffe-9d4e-4334c394df46 || 95a09909-d350-4cc6-8e33-4153cfe28a7f || f867230d-587a-4c73-ba9b-3ab93ed9d9d7 || 53e4e4d6-7fe9-4d97-a56c-d55311748151 || ce109720-ac8c-4042-bd77-82733a79fb6c || 215b4f1f-c45b-4b5a-83c7-d9ecf0c27585 || 7650f4cb-dc69-470f-a3c0-941784304d41 || 806f118b-d6b0-4939-ad11-753dafd57638 || 7107ec67-0fe1-4e2a-a665-6949d1c2b554 || ef2a3b5f-c840-4290-9574-fe29eee1c165 || 7cce4927-35a4-4b74-90f4-ac2262bb34d7 || 3a069494-6968-477a-a4ad-002ee5f30904 || 015f5896-7d13-46d4-8c6d-5c7317ecf054 | T110: Argentum Exploration Limited v The Silver and all persons claiming to be interested in and/or to have rights in respect of, the Silver [2022] EWCA Civ 1318 || Sayn-Wittgenstein-Sayn v HM Juan Carlos Alfonso Victor María de Borbón y Borbón (Rev1) [2022] EWCA Civ 1595 || Benkharbouche & Anor v Embassy of the Republic of Sudan || Reyes & Anor v Al-Malki & Anor || Belhaj & Anor v Straw & Ors [2014] EWCA Civ 1394 || HRH Prince Abdul Aziz Bin Fahd Bin Abdul Aziz v Harb || The United States of America v Nolan || IPCO (Nigeria) Ltd v Nigerian National Petroleum Corporation [2015] EWCA Civ 1144 || Bestfort Developments LLP & Ors v Ras Al Khaimah Investment Authority & Ors [2016] EWCA Civ 1099 || Zubaydah v Foreign and Commonwealth Office & Ors [2022] EWCA Civ 334 (Court of Appeal, Civil Division) || Yapp v Foreign and Commonwealth Office || London Borough of Croydon v Y [2016] EWCA Civ 398 || R3 v Secretary of State for the Home Department [2023] EWCA Civ 169 || Al-Saadoon & Ors v The Secretary of State for Defence & Ors; Rahmatullah & Anr v Secretary of State for Defence & Anr [2016] EWCA Civ 811 (Admin Court of Appeal, Civil Division) || Nayif v The High Commission of Brunei Darussalam [2014] EWCA Civ 1521 || Sayn-Wittgenstein-Sayn v His Majesty Juan Carlos Alfonso Victor Maria de Borbón y Borbón [2022] EWCA Civ 1052 || Secretary of State for the Home Department v Lisa Smith [2023] EWCA Civ 376 || C7 v Secretary of State for the Home Department [2023] EWCA Civ 265 || Ali v Washwood Heath Technology College & Ors [2014] EWCA Civ 97 || Al-Juffali v Estrada [2016] EWCA Civ 176 | AO110: =IF(OR(V110="",AE110=""),"",IF(V110=AE110,"agree","disagree")) | AP110: =IF(OR(Y110="",AH110=""),"",IF(Y110=AH110,"agree","disagree")) | AT110: =IF(B110="no","not sampled",IF(AND(V110<>"",Y110<>""),"complete","pending")) -> not sampled
B111: no | C111: cmsbszs77002304ji6ldkbjce | D111: ca-2024-0023525 & ca-2024-002295-modernatx-inc-v-pfizer-limited-others-respondent-skeleton | E111: real | F111: 1 | G111: English v Emery Reimbold & Strick Ltd [2002] EWCA Civ 605 | H111: case_law | I111: Adequacy of reasons in judgments is critical to ensure fair proceedings and proper appeals. | J111: The requirement for clear reasoning in judicial decisions aids in establishing grounds for appeal. | K111: binding | L111: in_corpus_not_retrieved | M111: no | N111: yes | O111: yes | P111: yes | Q111: https://www.bailii.org/ew/cases/EWCA/Civ/2002/605.html | R111: cmsbsuhsv001r04jiv19ukl8u | S111: 9c4e33c9-91d3-464b-b025-a46e5f3673af || 1c816bf0-70b4-46bd-9a31-9d036faff956 || 71033cf6-55d5-450b-8f5c-b4e0192b644a || cb8c8a45-aef5-4216-9a7b-d3b254e3b53a || d2737a8b-f6d7-473c-83e0-4e50adcfcdc4 || a1a08eab-f66f-48ea-a2b4-e885be7c07df || 024940b7-32ce-4a89-be24-ef0977f9eecd || 08ccb4b2-db3c-4132-87d7-ba219d5957a0 || 7311cc70-1cfb-4513-97ab-71a6251af9db || c0f3fdb2-6414-4841-8590-b7c4efeabf5e || 6ba97045-0b3f-40c9-b06f-d6c5cc32ad55 || 466ad3d5-2323-4234-9361-33c5f1c8d976 || f462ecd6-c4d2-4d24-997f-71bddff50aab || 33d3386d-e19e-4140-bd36-3e7d208b6e5a || ce8d542e-c788-49dc-95c2-e97c961e144e || 5484c0b3-68e5-4332-8ca9-7879a400b8de || 11464556-955b-4142-86d7-0d80daa5ca11 || df131dd9-a363-4ffe-8782-01767cbb4625 || 220f5941-b918-42be-ba08-5254bcf34586 || 9a6c35d9-2f41-4d9b-bdea-d545c0053749 | T111: Philip Morris Products, S.A. v Nicoventures Trading Limited & Anor (Re Invalidity of Patents) [2022] EWCA Civ 1638 || Idenix Pharmaceuticals Inc v Gilead Sciences Inc & Ors [2016] EWCA Civ 1089 || Hospira UK Limited v Genentech, Inc. [2016] EWCA Civ 1185 || Warner-Lambert Company LLC v Generics (UK) Ltd (t/a Mylan) & Ors [2016] EWCA Civ 1006 || Nokia Technologies OY & Anor v OnePlus Technology (Shenzhen) Co Ltd & Ors || Synthon BV v Teva Pharmaceutical Industries Ltd [2017] EWCA Civ 148 || Neurim Pharmaceuticals (1991) Limited & Flynn Pharma Limited v Generics (UK) Limited & Viatris UK Healthcare Limited [2022] EWCA Civ 699 || Interdigital Technology Corporation & Ors v Lenovo Group Ltd & Ors [2023] EWCA Civ 57 || Interdigital Technology Corporation & Ors v Lenovo Group Ltd & Ors [2023] EWCA Civ 105 || Neurim Pharmaceuticals (1991) Limited & Anor v Generics (UK) Limited & Anor [2022] EWCA Civ 370 || Teva UK Limited & Teva Pharmaceutical Industries Limited v Novartis AG & Novartis Pharmaceuticals UK Limited [2022] EWCA Civ 1617 || Optis Cellular Technology LLC & Ors v Apple Retail UK Ltd & Ors [2023] EWCA Civ 758 || Sandoz Limited v Bristol-Myers Squibb Holdings Ireland Unlimited Company (Re Patent - Plausibility when determining validity) [2023] EWCA Civ 472 || Alcon Research LLC & Anor v Pharmathen SA & Anor [2022] EWCA Civ 845 (28 June 2022) || Optis Cellular Technology LLC et al v Apple Retail UK Ltd et al [2023] EWCA Civ 438 || Optis Cellular Technology LLC & Ors v Apple Retail UK Ltd & Ors [2022] EWCA Civ 1411 || Dr Reddy's Laboratories (UK) Ltd & Ors v Warner-Lambert Company LLC [2023] EWCA Civ 73 (Court of Appeal, Civil Division) || Optis Cellular Technology LLC & Ors v Apple Retail UK Limited & Ors [2022] EWCA Civ 792 || Hospira (UK) Ltd v Genentech, Inc. || Novartis AG and Novartis Pharmaceuticals UK Limited v Teva UK Ltd & Ors [2022] EWCA Civ 775 | AO111: =IF(OR(V111="",AE111=""),"",IF(V111=AE111,"agree","disagree")) | AP111: =IF(OR(Y111="",AH111=""),"",IF(Y111=AH111,"agree","disagree")) | AT111: =IF(B111="no","not sampled",IF(AND(V111<>"",Y111<>""),"complete","pending")) -> not sampled
... B116: no | C116: cmst4fdgx001l04l7p4wrw7w7 | D116: skeleton-args-ca2025001247-4e7222cd1e12236a | E116: synthetic | F116: 2 | G116: Royal Mail Ltd v Jhuti (2019) EWCA Civ 1632 | H116: case_law | I116: The causation mechanism links disclosures to subsequent treatment by employers. | J116: Relevant in assessing whether Dr. Thornton's dismissal was influenced by her disclosures. | K116: binding | L116: retrieved_case_name_citation_conflict | M116: yes | N116: yes | O116: yes | P116: no | Q116: https://www.supremecourt.uk/cases/uksc-2017-0207 | R116: cmst4drgk001f04l70ut5a3k0 | S116: 8b6843e2-a05d-4712-8f61-9132cd4bb585 || 27be67b1-3e6c-4a07-90e1-cbb8420b8cee || 384e0c8e-cdd6-4cc9-b403-66e1f4f34acd || 66ef0e4f-af5f-406d-9033-1d688a8ab299 || 0b85ba33-95d2-4cf3-a08d-ed6833230187 || f23c3571-33ba-4a67-b917-2c6f40b74593 || 3054ae89-4fdf-4879-a9ae-0e7c8a19d90e || b95f1402-e7e1-473c-80dc-2f1763e8cc02 || 58d08b20-69c9-47be-8f81-5be69b31e088 || abcffa50-4a75-4ad4-9667-e3dfe47a4411 || 0845a137-08c0-4495-8d95-5cb333f9d947 || b28ef1e1-4ef7-4015-9008-5cb657f48023 || 979b8f09-db67-4037-bb54-2a5a9cc60534 || b09fb158-eea2-4246-afa6-9a119107834a || 126904c3-76e4-4116-9766-06699aedc5c8 || 7ebe446f-f92d-4a1c-9bb1-3a15dfc2675a || 9365ac87-002c-4767-beb5-daa394718251 || 7a524f94-2932-4f6f-895d-481394129f94 || 24cdd790-fb66-4e79-895a-0d7f73047839 || 7b9b0d5a-dc61-43d4-9626-d82e18f8c8dd | T116: Chesterton Global Ltd & Anor v Nurmohamed & Anor || Beatt v Croydon Health Services NHS Trust || Royal Mail Ltd v Jhuti [2017] EWCA Civ 1632 || Ojikutu v London Borough of Camden [2014] EWCA Civ 978 || Co-Operative Group Ltd v Baddeley [2014] EWCA Civ 658 || Barnes v London Borough of Lewisham [2016] EWCA Civ 582 || Clifford v Millicom Services UK Ltd & Ors [2023] EWCA Civ 50 || Edwards v Parabis Law LLP t/a Cogent Law [2016] EWCA Civ 35 || Kuznetsov v The Royal Bank of Scotland Plc || O'Brien v Bolton St Catherine's Academy [2017] EWCA Civ 145 || Kong v Gulf International Bank (UK) Limited [2022] EWCA Civ 941 || Rodgers v Leeds Laser Cutting Ltd [2022] EWCA Civ 1659 || Lawson v the Governing Body of Aylesford School & Anr [2014] EWCA Civ 491 || Phipps v Priory Education Services Ltd [2023] EWCA Civ 652 (Court of Appeal, Civil Division) || Pimlico Plumbers Ltd & Anor v Smith || Vining v London Borough of Wandsworth [2017] EWCA Civ 1092 || Adeshina v St. George's University Hospitals NHS Foundation Trust & Ors [2017] EWCA Civ 257 || Athanasopoulos v The Institute for Orthodox Christian Studies || Halawi v WDFG UK Ltd (t/a World Duty Free) [2014] EWCA Civ 1387 || South Wales Police Authority v Johnson [2014] EWCA Civ 73 | AO116: =IF(OR(V116="",AE116=""),"",IF(V116=AE116,"agree","disagree")) | AP116: =IF(OR(Y116="",AH116=""),"",IF(Y116=AH116,"agree","disagree")) | AT116: =IF(B116="no","not sampled",IF(AND(V116<>"",Y116<>""),"complete","pending")) -> not sampled

Sheet Retrieved Evidence
A1: search_id | B1: retrieval_rank | C1: retrieved_case_id | D1: retrieved_case_title | E1: court | F1: case_year | G1: overall_similarity | H1: best_chunk_id | I1: best_chunk_type | J1: best_chunk_similarity | K1: chunk_summary | L1: chunk_content | M1: cited_cases | N1: relevance_explanation
A2: cmlzp9luh000304l29ip4sjki | B2: 1 | C2: d23d9f9f-4d0a-455a-bab1-0ce1a023b722 | D2: Altrad Services Ltd & Anor v Commissioners for HMRC [2023] EWCA Civ 474 (03 May 2023) | E2: England and Wales Court of Appeal (Civil Division) | F2: 2023 | G2: 0.68272364 | H2: d23d9f9f-4d0a-455a-bab1-0ce1a023b722_legal_classification | I2: legal_classification | J2: 0.68272364 | K2: Classification of legal framework: tax law, capital allowances, and the Ramsay principle, with focus on statutory sections relevant to the dispute and the appellate process. | L2: Legal Classification: Primary Category: Tax Law / Civil Appeal Legal Areas: Taxation, Capital Allowances, Statutory Interpretation, Contractual Finance Leases, Ramsay Doctrine, Procedural Rules on Appeals Jurisdiction: England and Wales Court Level: Court of Appeal (Civil Division) Legal Issues: Whether disposal of assets for capital allowances purposes occurred under s61(1)(a) CAA 2001 (Ramsay principle). Whether reacquisition of assets constitutes qualifying expenditure under s11 CAA 2001 in the context of a long funding finance lease and associated s70E/YE calculations. Whether Put/Call option arrangements can be treated as a scheme to generate extra capital allowances without real economic cost. Whether Ground 2 was properly pleaded and raised in the FTT/UT proceedings and thus properly before the CA (procedural issue). Whether the UT’s reversal on Issue 1 should stand in light of the Court’s procedural ruling on Ground 2 Keywords: capital allowances, Ramsay principle, CAA 2001, section 61(1)(a), section 11, composite transactions, Court of Appeal (Civil Division), tax litigation, Upper Tribunal, First-tier Tribunal | M2: Ramsay || Tower || BMBF || Ensign | N2: This case shows 68% similarity based on legal classification analysis.
A3: cmlzp9luh000304l29ip4sjki | B3: 2 | C3: 16f61521-59b6-4c57-8af3-c654be05eab0 | D3: BPP Holdings v Revenue And Customs [2016] EWCA Civ 121 | E3: England and Wales Court of Appeal (Civil Division) | F3: 2016 | G3: 0.67462647 | H3: 16f61521-59b6-4c57-8af3-c654be05eab0_procedural_history | I3: procedural_history | J3: 0.67462647 | K3: Procedural history: FtT decision (Judge Mosedale) and UT decision (Judge Bishopp) concerning a debarment issue; CA appeal on 01 Mar 2016; hearing held 16 Dec 2015; reflection on rule 8 and case management practices. | L3: Procedural History: Court: England and Wales Court of Appeal (Civil Division) Lower Court: First-tier Tribunal (Tax Chamber) Judges: Lord Justice Moore-Bick, Lord Justice Richards, The Senior President of Tribunals Case Number: A3/2014/4240 Last Hearing Date: 01 March 2016 Duration: 60 days | M3: McCarthy & Stone || Leeds || Mitchell || Denton | N3: This case shows 67% similarity based on procedural history analysis.
A4: cmlzp9luh000304l29ip4sjki | B4: 3 | C4: 2f2ce488-73d0-4422-abcd-2b014a9e52d1 | D4: Totel Limited v HM Revenue and Customs [2016] EWCA Civ 1310 | E4: England and Wales Court of Appeal (Civil Division) | F4: 2016 | G4: 0.67187154 | H4: 2f2ce488-73d0-4422-abcd-2b014a9e52d1_procedural_history | I4: procedural_history | J4: 0.67187154 | K4: Procedural history: Case progresses from the Upper Tribunal to the Court of Appeal; case number A3/2015/1980; hearing on 21-22 November 2016; decision delivered 20 December 2016. | L4: Procedural History: Court: England and Wales Court of Appeal (Civil Division) Lower Court: Upper Tribunal (Tax and Chancery Chamber) FTC 67/2013, [2014] UKUT 485 (TCC) Judges: Lady Justice Arden, Lord Justice Irwin, Lord Justice Henderson Case Number: A3/2015/1980 Last Hearing Date: 20 December 2016 Duration: 2 days | M4: UKUT 485 (TCC) || Marks & Spencer || Littlewoods | N4: This case shows 67% similarity based on procedural history analysis.
A5: cmlzp9luh000304l29ip4sjki | B5: 4 | C5: 53011b43-2d84-4830-953a-1b5b550f4f67 | D5: The Quentin Skinner 2015 Settlement L & Ors v HM Revenue and Customs (Entrepeneurs' Relief) [2022] EWCA Civ 1222 | E5: England and Wales Court of Appeal (Civil Division) | F5: 2022 | G5: 0.6712979 | H5: 53011b43-2d84-4830-953a-1b5b550f4f67_procedural_history | I5: procedural_history | J5: 0.6712979 | K5: Procedural history: appeal from the Upper Tribunal (Tax and Chancery) to the Court of Appeal; hearing date and hand-down date recorded, with the panel listed. | L5: Procedural History: Court: England and Wales Court of Appeal (Civil Division) Lower Court: Upper Tribunal (Tax and Chancery Chamber) [2020] UKUT 29 (TCC) Judges: Lord Justice Lewison, Lord Justice Snowden, Sir Launcelot Henderson Case Number: CA-2021-0007111 / A3/2021/1394 Last Hearing Date: 16 September 2022 Duration: 75 days | N5: This case shows 67% similarity based on procedural history analysis.
A6: cmlzp9luh000304l29ip4sjki | B6: 5 | C6: 5f096d49-2a17-4252-839a-438cd198b444 | D6: Dawson's (Wales) Ltd v Revenue & Customs [2023] EWCA Civ 332 | E6: England and Wales Court of Appeal (Civil Division) | F6: 2023 | G6: 0.6697735 | H6: 5f096d49-2a17-4252-839a-438cd198b444_procedural_history | I6: procedural_history | J6: 0.6697735 | K6: Chronology of proceedings from HMRC assessment to FTT, UT and CA, including the framing of preliminary issues and the stay/policy references. | L6: Procedural History: Court: England and Wales Court of Appeal (Civil Division) Lower Court: Upper Tribunal Tax and Chancery Chamber [2019] UKUT 296 (TCC) Judges: Lady Justice Asplin, Lord Justice Arnold, Lady Justice Elisabeth Laing Case Number: CA-2019-001534 Last Hearing Date: 28 March 2023 Duration: 4350 days | M6: Davison & Robinson || Perfect || WR | N6: This case shows 67% similarity based on procedural history analysis.
A7: cmlzp9luh000304l29ip4sjki | B7: 6 | C7: 7253e952-4693-4c28-8c6d-f176b4e6f194 | D7: HMRC v GMAC (UK) Plc [2016] EWCA Civ 1015 (Court of Appeal, Civil Division) | E7: England and Wales Court of Appeal (Civil Division) | F7: 2016 | G7: 0.6695423 | H7: 7253e952-4693-4c28-8c6d-f176b4e6f194_procedural_history | I7: procedural_history | J7: 0.6695423 | K7: Procedural progression: FTT decision (2010) and UT decision (2012) leading to CA hearing (2016); detailed timeline of appeals and judgments in the VAT bad debt relief context. | L7: Procedural History: Court: England and Wales Court of Appeal (Civil Division) Lower Court: Upper Tribunal (Tax and Chancery Chamber) and First-tier Tribunal (Tax Chamber) Judges: Lord Justice Floyd, Lady Justice Arden DBE, Mrs Justice Theis DBE Case Number: A3/2015/0785 Last Hearing Date: 25 October 2016 Duration: 2 days | M7: BT CA (EWCA Civ 433) | N7: This case shows 67% similarity based on procedural history analysis.
A8: cmlzp9luh000304l29ip4sjki | B8: 7 | C8: f2e312b7-9979-4341-a687-c55ade7d7fac | D8: IFX Investment Company Ltd and Ors v Revenue and Customs [2016] EWCA Civ 436 | E8: England and Wales Court of Appeal (Civil Division) | F8: 2016 | G8: 0.6665889 | H8: f2e312b7-9979-4341-a687-c55ade7d7fac_procedural_history | I8: procedural_history | J8: 0.6665889 | K8: Procedural path from FTT to UT to CA; hearing on 8 April 2016; CA judgment delivered 4 May 2016; case No A3/2014/3908. | L8: Procedural History: Court: England and Wales Court of Appeal (Civil Division) Lower Court: Upper Tribunal (Tax and Chancery Chamber) [2014] UKUT 398 (TCC) Judges: Lady Justice Arden, Lord Justice Tomlinson, Mr Justice Morgan Case Number: A3/2014/3908 Last Hearing Date: 2016-05-04 Duration: 1 days | M8: UKUT 398 (TCC) [2014] | N8: This case shows 67% similarity based on procedural history analysis.
A9: cmlzp9luh000304l29ip4sjki | B9: 8 | C9: f088dcd9-a86b-4857-941b-1ba09d92fbc6 | D9: Revenue & Customs v Gray & Farrar International LLP [2023] EWCA Civ 121 | E9: England and Wales Court of Appeal (Civil Division) | F9: 2023 | G9: 0.6665688 | H9: f088dcd9-a86b-4857-941b-1ba09d92fbc6_procedural_history | I9: procedural_history | J9: 0.6665688 | K9: Procedural path: FTT decision dismissing G&F appeal (2019); UT remaking decision (2021) in HMRC’s favour; CA appeal (CA 2022/000203) with hearings on 17-18 January 2023 and judgment handed 13 February 2023. | L9: Procedural History: Court: England and Wales Court of Appeal (Civil Division) Lower Court: Upper Tribunal Tax & Chancery Division [2021] UKUT 0293 (TCC) Judges: Lord Justice Lewison, Lord Justice Newey, Lady Justice Simler Case Number: CA 2022/000203 Last Hearing Date: 13 February 2023 Duration: 2 days | M9: UKUT 2021 || UKFTT 2019 | N9: This case shows 67% similarity based on procedural history analysis.
A10: cmlzp9luh000304l29ip4sjki | B10: 9 | C10: c905ed54-034f-425d-908f-4d0fc7437e71 | D10: Naghshineh v Commissioners for HM Revenue and Customs [2022] EWCA Civ 19 | E10: England and Wales Court of Appeal (Civil Division) | F10: 2022 | G10: 0.66280985 | H10: c905ed54-034f-425d-908f-4d0fc7437e71_outcome_holding | I10: outcome_holding | J10: 0.66280985 | K10: Summary of the outcome as described: HMRC's position upheld; sideways relief denied for the disputed years by UT. | L10: Case Outcome: Holding: The Upper Tribunal’s construction of section 68(3)(b) denied sideways relief for the years in dispute, affirming HMRC’s position on the test and its application. The Court of Appeal is addressing an overarching statutory construction issue, including how to apply the two-limb test and whether predecessor legislation informs the current provision. Outcome: defendant Precedent Strength: 9/10 Complexity Score: 9/10 Damages: 0 Legal Significance: Landmark case with exceptional legal significance | N10: This case shows 66% similarity based on outcome holding analysis.
A11: cmlzp9luh000304l29ip4sjki | B11: 10 | C11: 99e499ed-5641-4f75-8c33-a3c4e6031823 | D11: Argentum Exploration Limited v The Silver and all persons claiming to be interested in and/or to have rights in respect of, the Silver [2022] EWCA Civ 1318 | E11: England and Wales Court of Appeal (Civil Division) | F11: 2022 | G11: 0.66141564 | H11: 99e499ed-5641-4f75-8c33-a3c4e6031823_case_analysis | I11: case_analysis | J11: 0.66141564 | K11: Assesses the potential precedent value and complexity of the Argentum v Silver appeal in shaping state-immunity and salvage-law jurisprudence. | L11: Case Analysis and Reasoning: Precedent Strength Assessment (7/10): • The issue engages a high-level, frequently cited domain of private international law (state immunity) with a clear statutory framework (State Immunity Act 1978) and significant maritime context (Admiralty in rem). • The Court of Appeal sits at a high level of authority to interpret the immunity exceptions, potentially shaping future in rem salvage proceedings involving state-owned cargo. • The presence of a clear statutory trigger (s10(4)) and the need to interpret 'commercial purposes' confers strong doctrinal value, as long as the holding remains stable and widely adopted. • However, the final holding is not in the provided text; if the Court of Appeal remanded for further fact-finding or if the decision ultimately favors immunity, the precedential impact may be more limited. • Potential for subsequent citation by courts facing similar state-immunity/Salvage Convention issues, but contingent on the final ratio decidendi being clear and broadly applicable. Confidence: 70% Complexity Score Assessment (8/10): • Multiple intertwined issues: in rem procedure, state immunity, commercial-use interpretation, ownership of wreck, and salvage-time-bar. • Cross-jurisdictional (UK statute, international Salvage Convention) with reliance on common-law history of immunity (two forms) and statute interpretation. • Extensive factual matrix: historic sinking (1942), wartime arrangements, salvage operations (2017), Receiver of Wreck decisions, and post-salvage ownership disputes. • Parties include state, private owners, salvors, and government interveners, adding procedural and evidentiary layers. • The decision hinges on nuanced readings of statutory phrases (eg, 'commercial purposes') and complex maritime-law concepts, increasing the technical require­ment and interpretive effort. Confidence: 75% Legal Significance: Important case with notable legal impact | N11: This case shows 66% similarity based on case analysis analysis.
A12: cmlzpfjvk000b04jtl1v4uh8a | B12: 1 | C12: 34dfb3bd-01bb-45bf-b18a-fce4ecb24b45 | D12: White & Anor v Amirtharaja & Anor [2022] EWCA Civ 11 | E12: England and Wales Court of Appeal (Civil Division) | F12: 2022 | G12: 0.65815496 | H12: 34dfb3bd-01bb-45bf-b18a-fce4ecb24b45_case_analysis | I12: case_analysis | J12: 0.65815496 | K12: Provides assessment of the case’s precedent value and its complexity, including how it affects future appeals and land-registration practice. | L12: Case Analysis and Reasoning: Precedent Strength Assessment (7/10): • The decision sits within a Court of Appeal framework and engages well-established principles on adverse possession and registering errors. • Judicial reasoning is thorough, drawing on LRA 2002 provisions, prior case law on possession and paper title, and the proper approach to new evidence on appeal (Ladd v Marshall). • The holding is moderately broad in its treatment of possessory vs. paper title issues but remains fact-specific, limiting broad, universal application. • Potential for citation exists in similar disputes regarding challenging a register or relying on possessory rights; however, the precise procedural posture (new point raised on appeal) limits universal adoption. • The score is not higher due to the case’s narrow procedural context and reliance on specific evidentiary findings rather than a sweeping doctrinal shift. Confidence: 72% Complexity Score Assessment (8/10): • Multiple intertwined issues: adverse possession, intent to possess, registration errors, and the possibility of new evidence on appeal. • Heavy reliance on procedural rules (Ladd v Marshall) regarding admissibility of fresh evidence and pleading requirements, adding procedural complexity. • Involves analysis of hearsay weight and the interpretation of statutory declarations, with causation between acts and possession. • Involves interpretation of Land Registration Act 2002 provisions, including s.9 and the concept of possessory vs absolute title. • Moderate to high complexity due to the number of parties, long chain of title history, and the cross-application of older authorities to a modern register framework. Confidence: 74% Legal Significance: Important case with notable legal impact | N12: This case shows 66% similarity based on case analysis analysis.
A13: cmlzpfjvk000b04jtl1v4uh8a | B13: 2 | C13: f4d639ad-f27c-47ba-a62c-bfc0c4c9430e | D13: Healey v Fraine & Ors [2023] EWCA Civ 549 | E13: England and Wales Court of Appeal (Civil Division) | F13: 2023 | G13: 0.6543503 | H13: f4d639ad-f27c-47ba-a62c-bfc0c4c9430e_legal_reasoning | I13: legal_reasoning | J13: 0.6543503 | K13: Appellate reasoning on Ground 1: pleading amendments must be proper and not salvage defective pleadings; analysis of the permissible scope and timing of amendments. | L13: Legal Analysis: Legal Issues: Whether the Defendants should be permitted to amend their Defence and Counterclaim (discretion in case management and pleading amendments).. Whether an adverse possession claim under the Land Registration Act 2002 can be pleaded in a case involving registered land and a claimed licensee.. Whether the pleadings properly defined the issues, and whether a wholesale amendment could be allowed when parts of it would fail as a matter of law.. Impact of agency/authority assertions (Maloney and Quinn) on the Defendants’ alleged possession and permission to occupy.. The interaction between licensee status and adverse possession in the context of registered land. Reasoning: The Court of Appeal held that the lower court’s broad permission to amend (which would allow an amendment containing a point of law the court deemed misconceived) was improper. Issues must be defined by pleadings, and permitting a wholesale amendment to include a legally doomed claim (adverse possession on the stated theory) was inappropriate. The panel discussed the limits of partial amendments and the need for a clear, properly drafted text before granting permission. On Ground 2, the court began a structured review of adverse possession in the LRA 2002 regime, noting the significant changes to the law and indicating a thorough examination of unregistered land, then registered land (LRA 1925 and LRA 2002), before reaching conclusions. The outcome on Ground 2 remains unresolved in the provided excerpt. Keywords: second appeal, pleading amendments, possession claim, registered land, adverse possession, LRA 2002, land registration, Court of Appeal, England and Wales | N13: This case shows 65% similarity based on legal reasoning analysis.
A14: cmlzpfjvk000b04jtl1v4uh8a | B14: 3 | C14: 6e8e988c-074c-4ab1-9e37-5c84673b441b | D14: Secretary of State for the Home Department v Cox & Ors [2023] EWCA Civ 551 (19 May 2023) | E14: England and Wales Court of Appeal (Civil Division) | F14: 2023 | G14: 0.63672197 | H14: 6e8e988c-074c-4ab1-9e37-5c84673b441b_procedural_history | I14: procedural_history | J14: 0.63672197 | K14: Procedural path from High Court decisions to Court of Appeal with hearings in March 2023. | L14: Procedural History: Court: England and Wales Court of Appeal (Civil Division) Lower Court: High Court (QB) – [2022] EWHC 680 (QB); [2022] EWHC 1626 (QB); [2022] EWHC 3188 (KB) Judges: Lord Justice Underhill (Vice-President of the Court of Appeal (Civil Division)), Lord Justice Stuart-Smith, Lord Justice Lewis Case Number: CA-2022-000689; CA-2022-001397; CA-2023-000010 Last Hearing Date: 19 May 2023 Duration: 2 days | N14: This case shows 64% similarity based on procedural history analysis.
A15: cmlzpfjvk000b04jtl1v4uh8a | B15: 4 | C15: 4fb69c0f-f93b-4540-a62b-7db9f10a32aa | D15: Heaney v Kirkby [2016] EWCA Civ 689 | E15: England and Wales Court of Appeal (Civil Division) | G15: 0.6361747 | H15: 4fb69c0f-f93b-4540-a62b-7db9f10a32aa_legal_classification | I15: legal_classification | J15: 0.6361747 | K15: Classification of the case within civil appellate procedure and its principal areas of law. | L15: Legal Classification: Primary Category: Appeal (Civil) / Property/Land Law Legal Areas: Property Law, Land Law, Adverse Possession, Evidence Law, Tribunal Procedure Jurisdiction: England and Wales Court Level: Court of Appeal (Civil Division) Legal Issues: Whether the verge was acquired by adverse possession in the circumstances of a neighbours' dispute.. Admissibility of new evidence under Ladd v Marshall (two limbs) in the context of a tribunal appeal.. Whether the Upper Tribunal and First-tier Tribunal correctly applied adverse possession principles to the facts.. Whether the appeal to the Court of Appeal satisfies the second appeals test (point of principle or compelling reason).. Impact of timing and dating evidence (planning officer discussion and photograph dating) on the possession claim. Keywords: adverse possession, verge ownership, neighbours dispute, EWCA Civ 689, second appeals test, Ladd v Marshall, admissibility of evidence, First-tier Tribunal, Upper Tribunal | N15: This case shows 64% similarity based on legal classification analysis.
A16: cmlzpfjvk000b04jtl1v4uh8a | B16: 5 | C16: 63ef2757-1a67-40a3-a684-a4901ad74648 | D16: Ely v Robson [2016] EWCA Civ 774 | E16: England and Wales Court of Appeal (Civil Division) | F16: 2016 | G16: 0.62874985 | H16: 63ef2757-1a67-40a3-a684-a4901ad74648_case_analysis | I16: case_analysis | J16: 0.62874985 | K16: Assessment of the case's broader legal significance, its precedent value, and the factors contributing to or limiting its complexity. | L16: Case Analysis and Reasoning: Precedent Strength Assessment (8/10): • This is a Court of Appeal decision reinforcing that an oral agreement may be binding where terms are clear and intention to create legal relations is demonstrated, allowing for constructive trust or proprietary estoppel even where the Law of Property Act 1989 writing requirements would typically apply. • The judgment engages Cobbe and Herbert v Doyle as comparative authorities, acknowledging the need for certainty of terms but allowing binding effect when a common understanding exists and reliance is evident. • The decision is unlikely to broaden the rule to all property transactions, as it emphasizes particular factual circumstances (long-standing cohabitation, explicit discussions, and clear terms in August 2007). • However, it strengthens practical guidance for disputes where parties negotiate and act on imperfect or informal settlements regarding beneficial interests in land. Confidence: 88% Complexity Score Assessment (7/10): • Multiple doctrinal theories (constructive trust, proprietary estoppel) and statutory constraints (s2(1) and s2(5) of the 1989 Act) interact with a factual mosaic (cohabitation, contributions to purchase, occupancy rights, and subsequent conduct). • Issues include the certainty of terms, whether an oral agreement suffices, and what constitutes binding intent and reliance in the context of land. • There are procedural layers (Part 8 and Part 7 procedures, directions, vacating hearings, and smooth transition to a declaratory relief action). • Presence of third-party interests (Vera Ellis and Peggy Robson) and the potential for multiple disputed interpretations of “equal shares” and “occupancy rights” add to the complexity. Confidence: 80% Legal Significance: Important case with notable legal impact | M16: Cobbe v Yeoman's Row Management Ltd || Herbert v Doyle || Ramsden v Dyson | N16: This case shows 63% similarity based on case analysis analysis.
A17: cmlzpfjvk000b04jtl1v4uh8a | B17: 6 | C17: d34db962-c7f4-46f4-9a77-df6d760ca7c4 | D17: Watts v Stewart & Ors [2016] EWCA Civ 1247 | E17: England and Wales Court of Appeal (Civil Division) | F17: 2016 | G17: 0.6258596 | H17: d34db962-c7f4-46f4-9a77-df6d760ca7c4_citations_precedents | I17: citations_precedents | J17: 0.6258596 | K17: Cited authorities and precedents underpinning the Court of Appeal’s reasoning on occupancy status, human rights, and charity governance. | L17: Citations and Authorities: Neutral Citations: [2016] EWCA Civ 1247, [2016] WLR(D) 666, [2018] Ch 423, [2017] L&TR 24, [2017] 2 WLR 1107, [2017] L &TR 24, [2017] 1 P &CR DG18, [2017] HLR 8 Law Reports: Gray v Taylor [1998] 1 WLR 1093, Street v Mountford [1985] 1 AC 809, Allan v Liverpool Overseers (1873-74) LR 9 QB 180, Errington v Errington [1952] 1 KB 291, Radaich v Smith (1959) 101 CLR 209, Megarry & Wade, The Law of Real Property, Earl of Pomfret v Lord Windsor (1752) 2 Ves Sen 472, Southward Housing Co-operative Ltd v Walker [2016] Ch 443, McDonald v McDonald [2015] Ch /Page 2015 UKSC 28, Larkos v Cyprus (1999) 30 EHRR 597, Harman: Blecic v Croatia (2005) 41 EHRR 13, Manchester City Council v Pinnock [2011] 2 AC 104, Secretary of State for Defence v Blake [2013] EWHC 2945 (Ch), RJM v Sec of State for Work and Pensions [2009] 1 AC 311, Clift v Secretary of State for the Home Department [2007] 1 AC 484, Southward Housing Co-operative Ltd v Walker (2016) Negotiating cite] Referenced Cases: Street v Mountford [1985] 1 AC 809, Gray v Taylor [1998] 1 WLR 1093, Allan v Liverpool Overseers (1873-74) LR 9 QB 180, Errington v Errington [1952] 1 KB 291, Radaich v Smith (1959) 101 CLR 209, Megarry & Wade, The Law of Real Property, Earl of Pomfret v Lord Windsor (1752) 2 Ves Sen 472, Southward Housing Co-operative Ltd v Walker [2016] Ch 443, McDonald v McDonald [2016] UKSC 28, Larkos v Cyprus (1999) 30 EHRR 597, Manchester City Council v Pinnock [2011] 2 AC 104, Secretary of State for Defence v Blake [2013] EWHC 2945 (Ch), RJM v SSWP [2009] 1 AC 311, Clift v Secretary of State for the Home Department [2007] 1 AC 484, Blécic v Croatia (2005) 41 EHRR 13, Harrow LBC v Qazi [2002] HLR 14, McDonald v McDonald [2014] EWCA Civ 1049, Southward Housing Co-operative Ltd v Walker [2016] Ch 443 Citation Count: 18 | M17: Street v Mountford || Gray v Taylor || Errington v Errington || Allan v Liverpool Overseers || Radaich v Smith || Southward Housing Co-operative v Walker || McDonald v McDonald || Larkos v Cyprus | N17: This case shows 63% similarity based on citations precedents analysis.
A18: cmlzpfjvk000b04jtl1v4uh8a | B18: 7 | C18: 5c0afba6-3b82-4ab2-9363-8c570514d87d | D18: Doyle v M&D Foundations & Building Services Ltd [2022] EWCA Civ 927 | E18: England and Wales Court of Appeal (Civil Division) | F18: 2022 | G18: 0.62310684 | H18: 5c0afba6-3b82-4ab2-9363-8c570514d87d_procedural_history | I18: procedural_history | J18: 0.62310684 | K18: Procedural history: from county court decisions through a first appeal, permission for a second appeal, to the Court of Appeal judgment delivered on 8 July 2022. | L18: Procedural History: Court: England and Wales Court of Appeal (Civil Division) Lower Court: County Court at Sheffield Judges: Lord Justice Baker, Lord Justice Phillips, Lord Justice Edis Case Number: CA-2021-000557 (formerly A2/2021/0729) Last Hearing Date: 8 July 2022 Duration: 2 days | M18: Solomon v Cromwell || Adelekun v Ho | N18: This case shows 62% similarity based on procedural history analysis.
A19: cmlzpfjvk000b04jtl1v4uh8a | B19: 8 | C19: 52adf3bc-8b19-4f24-9782-4fb618e86779 | D19: Candey Ltd v Bosheh & Anor [2022] EWCA Civ 1103 (01 August 2022) | E19: England and Wales Court of Appeal (Civil Division) | F19: 2022 | G19: 0.62303036 | H19: 52adf3bc-8b19-4f24-9782-4fb618e86779_procedural_history | I19: procedural_history | J19: 0.62303036 | K19: Procedural trajectory from the High Court decision to the Court of Appeal hearing and the issues on appeal. | L19: Procedural History: Court: England and Wales Court of Appeal (Civil Division) Lower Court: [2021] EWHC 3409 (Comm) (High Court) Judges: Lord Justice Coulson, Lord Justice Arnold, Lord Justice Phillips Case Number: CA-2022-000280 Last Hearing Date: 2022-08-01 Duration: 2 days | M19: Imerman v Tchenquiz || Mustard v Flowers | N19: This case shows 62% similarity based on procedural history analysis.
A20: cmlzpfjvk000b04jtl1v4uh8a | B20: 9 | C20: 73b3dc25-5f3f-4b55-a036-6843967dbba7 | D20: SO, R (On the Application Of) v Thanet District Council (Re Costs) [2023] EWCA Civ 526 | E20: England and Wales Court of Appeal (Civil Division) | F20: 2023 | G20: 0.62245166 | H20: 73b3dc25-5f3f-4b55-a036-6843967dbba7_procedural_history | I20: procedural_history | J20: 0.62245166 | K20: Procedural trajectory: appeal from the High Court, rolled-up hearing, and the denial of permission on grounds 1–3 with ground 4 not renewed. | L20: Procedural History: Court: England and Wales Court of Appeal (Civil Division) Lower Court: High Court (CO/4149/2021) Judges: LORD JUSTICE UNDERHILL, LORD JUSTICE ARNOLD, LORD JUSTICE EDIS Case Number: CA-2022-001378 Last Hearing Date: 16/05/2023 Duration: 1 days | M20: [2023] EWCA Civ 526 | N20: This case shows 62% similarity based on procedural history analysis.
A21: cmlzpfjvk000b04jtl1v4uh8a | B21: 10 | C21: 948fc767-31a4-4c63-b735-df551b7244eb | D21: Al-Rawas & Anor v Hassan Khan & Co & Anor [2022] EWCA Civ 671 (17 May 2022) | E21: England and Wales Court of Appeal (Civil Division) | F21: 2022 | G21: 0.6220471 | H21: 948fc767-31a4-4c63-b735-df551b7244eb_procedural_history | I21: procedural_history | J21: 0.6220471 | K21: Procedural trajectory: appellate appeal from QB Division; hearing and dismissal of the appeal; procedural steps for indemnity-cost submissions and the timeline for response. | L21: Procedural History: Court: England and Wales Court of Appeal (Civil Division) Lower Court: Queen's Bench Division Judges: Lord Justice Coulson, Lord Justice Arnold, Lord Justice Phillips Case Number: CA-2021-003286/7 Last Hearing Date: 17 May 2022 Duration: 20 days | M21: [2022] EWCA Civ 671 | N21: This case shows 62% similarity based on procedural history analysis.
A22: cmlzry90i000b04laxzwy3gcm | B22: 1 | C22: 70d43223-0ec6-458b-b052-bdc295e0d6ec | D22: Brown & Ors v South West Lakes Trust & Ors [2022] EWCA Civ 18 | E22: England and Wales Court of Appeal (Civil Division) | F22: 2022 | G22: 0.6996171 | H22: 70d43223-0ec6-458b-b052-bdc295e0d6ec_legal_classification | I22: legal_classification | J22: 0.6996171 | K22: Classification of legal categories, governing statutes, and court hierarchy applicable to the case. | L22: Legal Classification: Primary Category: Tort / Civil liability Legal Areas: Occupiers' Liability Act 1984, Tort law, Personal injury / road traffic accident, Highway law, Civil procedure: summary judgment, CRoW Act 2000 Jurisdiction: England and Wales Court Level: Court of Appeal (Civil Division) Legal Issues: Whether the occupiers of land adjoining a highway owe a duty under the Occupiers' Liability Act 1984 to a person injured in a road-traffic context.. Whether there is a real prospect of success against the highway authority and occupiers under the 1984 Act, considering summary judgment principles.. What, if any, role the Countryside and Rights of Way Act 2000 plays in limiting or shaping such duties. Keywords: occupiers' liability 1984, road traffic accident, land adjoining highway, highway authority, summary judgment, Court of Appeal (Civil Division), CRoW Act 2000, case law: Okpabi, Donoghue, Tomlinson | M22: Okpabi v Royal Dutch Shell plc [2021] UKSC 3 || Donoghue v Folkestone Properties Ltd [2003] EWCA Civ 231 | N22: This case shows 70% similarity based on legal classification analysis.
A23: cmlzry90i000b04laxzwy3gcm | B23: 2 | C23: 3b14442e-37b0-455c-a24f-a53a55c9f700 | D23: Humphrey v Aegis Defence Services Ltd & Anor [2016] EWCA Civ 11 | E23: England and Wales Court of Appeal (Civil Division) | F23: 2016 | G23: 0.6941479 | H23: 3b14442e-37b0-455c-a24f-a53a55c9f700_citations_precedents | I23: citations_precedents | J23: 0.6941479 | K23: Details the authorities cited in the decision, illustrating the doctrinal framework for assessing negligence with social utility and risk considerations. | L23: Citations and Authorities: Neutral Citations: [2016] EWCA Civ 11, [2017] 1 WLR 2937, 19 ITELR 1021, [2017] 2 All ER 235 Law Reports: Referenced Cases: Tomlinson v Congleton Borough Council [2003] UKHL 47, [2004] 1 AC 46, Daborn v Bath Tramways Motor Co. Ltd [1946] 2 All ER 333, Trevor Smithee? (as cited) [1946] 2 All ER 333, Jolley v Sutton London Borough Council [2000] 1 WLR 1082, Bolton v Stone [1951] AC 850, King v Sussex Ambulance Service NHS Trust [2002] EWCA Civ 953, As per Tomlinson and Daborn authorities quoted by the judge Citation Count: 7 | M23: Tomlinson v Congleton || Daborn v Bath Tramways || Jolley v Sutton || Bolton v Stone || King v Sussex Ambulance Service | N23: This case shows 69% similarity based on citations precedents analysis.
A24: cmlzry90i000b04laxzwy3gcm | B24: 3 | C24: 4685ad0e-87e7-4f59-8991-823ab27d9393 | D24: Tindall & Anor v Chief Constable of Thames Valley Police & Anor [2022] EWCA Civ 25 | E24: England and Wales Court of Appeal (Civil Division) | F24: 2022 | G24: 0.68254423 | H24: 4685ad0e-87e7-4f59-8991-823ab27d9393_citations_precedents | I24: citations_precedents | J24: 0.68254423 | K24: Key authorities cited regarding duty of care, omissions vs. positive actions, and public authority liability. | L24: Citations and Authorities: Neutral Citations: [2022] EWCA Civ 25, [2022] PIQR P10, [2022] 4 WLR 104, [2022] 4 All ER 372, [2022] RTR 16 Law Reports: [2022] EWCA Civ 25, [2022] PIQR P10, [2022] 4 WLR 104, [2022] 4 All ER 372, [2022] RTR 16 Referenced Cases: Michael and Ors v Chief Constable of South Wales Police and Anor [2015] UKSC 2, [2015] AC 1732, Robinson v Chief Constable of West Yorkshire Police [2018] UKSC 4, [2018] AC 736, N and Anor v Poole Borough Council [2019] UKSC 25, [2020] AC 720, Gorringe (authorities cited in the context of duty of care in public interventions), Sandhar (Court of Appeal guidance on public authority duty to prevent harm), Anns v Merton London Borough Council, Dorset Yacht Co Ltd v Surrey County Council, Hedley Byrne & Co Ltd v Heller & Partners Ltd Citation Count: 8 | M24: Michael v South Wales Police || Robinson v West Yorkshire Police || N and Anor v Poole Borough Council || Gorringe || Sandhar || Anns v Merton LBC || Dorset Yacht || Hedley Byrne | N24: This case shows 68% similarity based on citations precedents analysis.
A25: cmlzry90i000b04laxzwy3gcm | B25: 4 | C25: 29b57846-31cd-4592-b0bb-d49f37fcc7bb | D25: Dean and Chapter of Rochester Cathedral v Debell [2016] EWCA Civ 1094 | E25: England and Wales Court of Appeal (Civil Division) | F25: 2016 | G25: 0.679224 | H25: 29b57846-31cd-4592-b0bb-d49f37fcc7bb_citations_precedents | I25: citations_precedents | J25: 0.679224 | K25: Citations and authorities: key precedents and authorities relied upon to frame the duty to remediate and the standard of foreseeability in premises liability. | L25: Citations and Authorities: Neutral Citations: [2016] EWCA Civ 1094 Law Reports: Referenced Cases: Mills v Barnsley Metropolitan Borough Council [1992] 1 P.I.Q.R P291, James v Preseli Pembrokeshire District Council [1993] P.I.Q.R. P114, Rider v Rider [1973] 1 Q.B. 506, Brett v London Borough of Lewisham [1999], Jones v Rhondda Cynon Taff CBC [2008] EWCA Civ 1497; [2009] RT R 13, Galloway v London Borough of Richmond Upon Thames [2003] (Eady J), May also rely on general principles from Mills and related cases Citation Count: 7 | M25: Mills v Barnsley Metropolitan Borough Council [1992] 1 P.I.Q.R P291 || James v Preseli Pembrokeshire District Council [1993] P.I.Q.R. P114 || Rider v Rider [1973] 1 Q.B. 506 || Brett v London Borough of Lewisham [1999] || Jones v Rhondda Cynon Taff CBC [2008] EWCA Civ 1497 || Galloway v London Borough of Richmond Upon Thames [2003] | N25: This case shows 68% similarity based on citations precedents analysis.
A26: cmlzry90i000b04laxzwy3gcm | B26: 5 | C26: e16d7203-6f9e-4896-96e0-d021cb6f5579 | D26: Edwards v London Borough of Sutton [2016] EWCA Civ 1005 | E26: England and Wales Court of Appeal (Civil Division) | F26: 2016 | G26: 0.6787658 | H26: e16d7203-6f9e-4896-96e0-d021cb6f5579_citations_precedents | I26: citations_precedents | J26: 0.6787658 | K26: This chunk enumerates authorities cited in the decision on duty, foreseeability, and risk balancing, including Hughes, Tomlinson, Staples, McGivney, Japp, Uren, Nicholls, and Cotton. | L26: Citations and Authorities: Neutral Citations: [2016] EWCA Civ 1005 Law Reports: Referenced Cases: Hughes v Lord Advocate [1963] AC 837, Tomlinson v Congleton BC [2004] 1 AC 46, Staples v W Dorset DC [1995] PIQR 439, McGivney v Golderslea Limited [1997], Japp v Virgin Holidays Ltd [2013] EWCA Civ 1371, Uren v Corporate Leisure (UK) Ltd [2011] EWCA Civ 66, Nicholls v Ladbrokes Betting & Gaming Ltd [2013] EWCA Civ 1963, Cotton v Derbyshire Dales District Council (unreported) 1994, Corbett v Cumbria Kart Racing Club [2013] EWHC 1362 Citation Count: 9 | M26: Hughes v Lord Advocate || Tomlinson v Congleton BC || Staples v W Dorset DC || McGivney v Golderslea Ltd || Japp v Virgin Holidays Ltd || Uren v Corporate Leisure (UK) Ltd || Nicholls v Ladbrokes Betting & Gaming Ltd || Cotton v Derbyshire Dales District Council || Corbett v Cumbria Kart Racing Club | N26: This case shows 68% similarity based on citations precedents analysis.
A27: cmlzry90i000b04laxzwy3gcm | B27: 6 | C27: 9289473a-6889-4929-925d-2d6d66b75e86 | D27: Secretary of State for Justice v Black [2016] EWCA Civ 125 | E27: England and Wales Court of Appeal (Civil Division) | F27: 2016 | G27: 0.674535 | H27: 9289473a-6889-4929-925d-2d6d66b75e86_citations_precedents | I27: citations_precedents | J27: 0.674535 | K27: List of authorities cited to ground Crown immunity and necessary implication doctrines, including long-standing Crown-exemption jurisprudence and modern statutory interpretation cases. | L27: Citations and Authorities: Neutral Citations: [2016] EWCA Civ 125, [2016] 3 WLR 28, [2016] EWCA Civ 125, [2016] 3 All ER 30, (2016) 150 BMLR 457, [2016] QB 1060, [2016] WLR(D) 130, 150 BMLR 457 Law Reports: Referenced Cases: Gorton Local Board v Prison Commissioners, Cooper v Hawkins, Public Health Act 1875, Hornsey UDC v Hennell, Province of Bombay v Municipal Corporation of the City of Bombay, Lord Advocate v Dunbarton District Council, R (Revenue and Customs Commissioners) v Liverpool Coroner [2015] QB 481, BBC v Johns [1965] Ch 32, Attorney General of Belize v Belize Telecom Ltd [2009] 1 WLR 1988, Liverpool Coroner v Revenue and Customs Commissioners (paras 44-49) Citation Count: 10 | M27: Gorton Local Board v Prison Commissioners || Cooper v Hawkins || Province of Bombay v Municipal Corporation of the City of Bombay || R (Revenue and Customs Commissioners) v Liverpool Coroner || BBC v Johns || Lord Advocate v Dunbarton District Council | N27: This case shows 67% similarity based on citations precedents analysis.
... A36: cmlzy6by600ft04i8cpz0rrjt | B36: 5 | C36: 774ce56b-3a21-4d9a-be0f-2e4cd8924a73 | D36: Solar Century Holdings Ltd & Ors v Secretary of State for Energy and Climate Change [2016] EWCA Civ 117 | E36: England and Wales Court of Appeal (Civil Division) | F36: 2016 | G36: 0.67992246 | H36: 774ce56b-3a21-4d9a-be0f-2e4cd8924a73_citations_precedents | I36: citations_precedents | J36: 0.67992246 | K36: Authorities cited or relied upon in the decision, spanning case law and statutory instruments. | L36: Citations and Authorities: Neutral Citations: [2016] EWCA Civ 117 Law Reports: Referenced Cases: Bhatt Murphy v Independent Assessor [2008] EWCA Civ 755, Secretary of State for Energy & Climate Change v Friends of the Earth and Others [2012] EWCA Civ 28, Secretary of State for Energy & Climate Change v Friends of the Earth and others [2012] EWCA Civ 28, Bennion on Statutory Interpretation (6th ed), Electricity Act 1989 ss. 32LA, 32LB, 32K, Energy Act 2013, Renewables Obligation Close Order 2014, Renewables Obligation Closure (Amendment) Order 2015, Electricity Market Reform White Paper (July 2011), EMR White Paper: Planning our Electric Future Citation Count: 10 | M36: Bhatt Murphy v Independent Assessors [2008] EWCA Civ 755 || Secretary of State for Energy & Climate Change v Friends of the Earth [2012] EWCA Civ 28 | N36: This case shows 68% similarity based on citations precedents analysis.
A37: cmlzy6by600ft04i8cpz0rrjt | B37: 6 | C37: a86c8039-4dcd-41c2-bbee-f72673a10ba2 | D37: Rotherham Borough Council & Ors v Secretary of State for Business, Innovation And Skills | E37: England and Wales Court of Appeal (Civil Division) | F37: 2014 | G37: 0.6791068 | H37: a86c8039-4dcd-41c2-bbee-f72673a10ba2_outcome_holding | I37: outcome_holding | J37: 0.6791068 | K37: Court ruled in favor of the Secretary of State, finding no breach of EU law principles. | L37: Case Outcome: Holding: The Court of Appeal upheld the Secretary of State's funding decisions, concluding that the decisions were within legal bounds and appropriately considered regional disparities. Outcome: dismissed Precedent Strength: 7/10 Complexity Score: 8/10 Damages: 0 Legal Significance: Important case with notable legal impact | N37: This case shows 68% similarity based on outcome holding analysis.
A38: cmlzy6by600ft04i8cpz0rrjt | B38: 7 | C38: f52b20b0-a55d-4039-a67d-35811badb24b | D38: Cuciurean v Secretary of State for Transport & Anor [2022] EWCA Civ 1519 | E38: England and Wales Court of Appeal (Civil Division) | F38: 2022 | G38: 0.67299545 | H38: f52b20b0-a55d-4039-a67d-35811badb24b_citations_precedents | I38: citations_precedents | J38: 0.67299545 | K38: Authorities cited by the court in reasoning and decision | L38: Citations and Authorities: Neutral Citations: [2022] EWCA Civ 1519 Law Reports: Referenced Cases: [2020] EWHC 2614 (Ch), [2021] EWCA Civ 357, [2020] EWHC 829 (Admin), [2022] EWHC 736 (Admin), [2022] EWHC 2457 (KB), [2022] EWCA Civ 1519, Packham v Secretary of State for Transport and Others [2020] EWHC 829 (Admin) Citation Count: 7 | M38: Packham v SoS Transport [2020] EWHC 829 (Admin) || [2022] EWHC 736 (Admin) || [2020] EWHC 2614 (Ch) || [2021] EWCA Civ 357 || [2022] EWHC 2457 (KB) || [2022] EWCA Civ 1519 | N38: This case shows 67% similarity based on citations precedents analysis.
A39: cmlzy6by600ft04i8cpz0rrjt | B39: 8 | C39: 1bbfccbb-15e3-41bb-a970-7167b43b0267 | D39: Northern Gas Networks Ltd v Commissioners for HMRC [2022] EWCA Civ 910 | E39: England and Wales Court of Appeal (Civil Division) | F39: 2022 | G39: 0.6714672 | H39: 1bbfccbb-15e3-41bb-a970-7167b43b0267_citations_precedents | I39: citations_precedents | J39: 0.6714672 | K39: Authorities cited in the case: primary statutory and appellate authorities including UKUT 157 (TCC) and related law reports. | L39: Citations and Authorities: Neutral Citations: [2022] EWCA Civ 910, [2023] Env LR 6, [2022] BTC 20, [2022] STC 1241 Law Reports: [2023] Env LR 6, [2022] BTC 20, [2022] STC 1241 Referenced Cases: [2022] EWCA Civ 910, [2023] Env LR 6, [2022] BTC 20, [2022] STC 1241, [2021] UKUT 157 (TCC) Citation Count: 5 | M39: [2021] UKUT 157 (TCC) || [2022] EWCA Civ 910 || [2023] Env LR 6 || [2022] BTC 20 || [2022] STC 1241 | N39: This case shows 67% similarity based on citations precedents analysis.
A40: cmlzy6by600ft04i8cpz0rrjt | B40: 9 | C40: 4c3b8da7-6c82-4056-ab98-dea339f7af1d | D40: Ashchurch Rural Parish Council, R (On the Application Of) v Tewkesbury Borough Council [2023] EWCA Civ 101 | E40: England and Wales Court of Appeal (Civil Division) | F40: 2023 | G40: 0.6675079 | H40: 4c3b8da7-6c82-4056-ab98-dea339f7af1d_citations_precedents | I40: citations_precedents | J40: 0.6675079 | K40: Authorities and statutory references underpinning the Court of Appeal’s reasoning. | L40: Citations and Authorities: Neutral Citations: [2023] EWCA Civ 101, [2023] WLR(D) 95 Law Reports: [2023] WLR(D) 95, [2023] EWCA Civ 101 Referenced Cases: R (Samuel Smith Old Brewery) v North Yorkshire CC [2020] UKSC 3, [2020] PTSR 221, Town and Country Planning (Environmental Impact Assessment) Regulations 2017, [2023] EWCA Civ 101, [2023] WLR(D) 95 Citation Count: 4 | M40: R (Samuel Smith Old Brewery) v North Yorkshire CC [2020] UKSC 3 || Town and Country Planning (Environmental Impact Assessment) Regulations 2017 | N40: This case shows 67% similarity based on citations precedents analysis.
A41: cmlzy6by600ft04i8cpz0rrjt | B41: 10 | C41: f157dc58-8d24-4561-9b20-3df67da80a73 | D41: The Good Law Project, R (On the Application Of) v Minister for the Cabinet Office [2022] EWCA Civ 21 | E41: England and Wales Court of Appeal (Civil Division) | F41: 2022 | G41: 0.6634462 | H41: f157dc58-8d24-4561-9b20-3df67da80a73_citations_precedents | I41: citations_precedents | J41: 0.6634462 | K41: Compilation of authorities and statutes cited or relied upon in the judgment. | L41: Citations and Authorities: Neutral Citations: [2022] EWCA Civ 21, 200 Con LR 57, [2022] WLR(D) 54, [2022] PTSR 933 Law Reports: Referenced Cases: Public Contracts Regulations 2015 reg 32(2)(c), R v Rand [1866] LQR 1 B 230, Porter v. Magill [2001] UKHL 67, R (ex p Kirkstall Valley Campaign Ltd) v Secretary of State for the Environment [1996] 3 All ER 304, Locabail (UK) Ltd v Bayfield Properties Ltd [2000] QB 351, R v Bow Street Metropolitan Stipendiary Magistrate, ex p Pinochet Ugarte No.2 [2000] 1 AC 199, R v Secretary of the Home Department ex parte Fayed [2001] Imm AR 134, Helow v. Secretary of State for the Home Department [2008] UKHL 62, Almazeedi v. Penner and others (Cayman Island) [2018] UKPC 3, Gillies v. Secretary of State for Work and Pensions [2006] UKHL 2, R (Lewis) v. Redcar & Cleveland Borough Council [2008] EWCA Civ 746, R (Royal Brompton and Harefield NHS Foundation Trust) v Joint Committee of Primary Care Trusts [2012] EWCA Civ 472 Citation Count: 12 | M41: R v Rand (1866) || Porter v. Magill || R (ex p Kirkstall Valley Campaign Ltd) || Locabail (UK) Ltd v Bayfield Properties Ltd || R v Bow Street Magistrate ex p Pinochet Ugarte No.2 || R v Secretary of the Home Department ex parte Fayed || Helow v. Secretary of State for the Home Department || Almazeedi v. Penner and others || Gillies v. Secretary of State for Work and Pensions || R (Lewis) v. Redcar & Cleveland Borough Council || R (Royal Brompton and Harefield NHS Foundation Trust) v Joint Committee of Primary Care Trusts | N41: This case shows 66% similarity based on citations precedents analysis.
A42: cmm0b91t5000e04ibf7gf6ujr | B42: 1 | C42: e050e594-d197-45f1-ba15-7d110c0d93c4 | D42: Great Lakes Reinsurance (UK) SE v Western Trading Ltd [2016] EWCA Civ 1003 (11 October 2016) | E42: England and Wales Court of Appeal (Civil Division) | F42: 2016 | G42: 0.72396386 | H42: e050e594-d197-45f1-ba15-7d110c0d93c4_outcome_holding | I42: outcome_holding | J42: 0.72396386 | K42: Outcome and remedial posture: declaration affirmed with corrected wording, reinstatement cost as the measure of indemnity up to the policy limit; damages not awarded; costs decided. | L42: Case Outcome: Holding: The Court of Appeal held that the measure of indemnity under the Memorandum is the cost of reinstatement (the rebuilding of the property to a condition equal to that when new), up to the policy limits. A declaration addressing indemnity for reinstatement is appropriate, provided the wording accurately reflects insurable interest and non-avoidance. The court varied the declaration’s wording and affirmed that, if reinstatement occurs, the insurer must indemnify up to £2,121,800; damages were not awarded unless necessary. Costs were adjusted to standard costs, and the appeal succeeded in part to refine the declaration and its terms. Outcome: plaintiff Precedent Strength: 8/10 Complexity Score: 9/10 Damages: 0 Legal Significance: Highly significant case with strong precedential value | N42: This case shows 72% similarity based on outcome holding analysis.
A43: cmm0b91t5000e04ibf7gf6ujr | B43: 2 | C43: d38848d5-b685-4b5f-8093-40563114db3b | D43: Shipowners' Mutual Protection and Indemnity Association (Luxembourg) v Containerships Denizcilik Nakliyat ve Ticaret A.S. ("Yusuf Cepnioglu") [2016] EWCA Civ 386 | E43: England and Wales Court of Appeal (Civil Division) | F43: 2016 | G43: 0.6932454 | H43: d38848d5-b685-4b5f-8093-40563114db3b_citations_precedents | I43: citations_precedents | J43: 0.6932454 | K43: Authorities cited: Padre Island, Hari Bhum (No.1), Prestige (No.2), Jay Bola, Charterers' Mutual, Angelic Grace, Hari Bhum, Turner v Grovit, Erich Gasser, Front Comor, Akai, DVA v Voest Alpine and others. | L43: Citations and Authorities: Neutral Citations: [2016] EWCA Civ 386, [2016] Bus LR 755, [2016] WLR(D) 230, [2016] Bus LR 1284 Law Reports: The Padre Island [1984] 2 Lloyd's Rep 408, Through Transport Mutual Insurance Association (Eurasia) Ltd v New India Assurance Co Ltd (The Hari Bhum) (No.1) [2004] EWCA Civ 1598; [2005] 1 Lloyd's Rep 67; [2004] 1 Lloyd's Rep 206, The London Steam Ship Owners Mutual Insurance Association Ltd v The Kingdom of Spain (The Prestige) (No.2) [2013] EWHC 3188 (Comm); [2014] 1 Lloyd's Rep 309; [2015] EWCA Civ 333; [2015] 2 Lloyd's Rep 33, The Padre Island, The Angelic Grace (Aggeliki Charis Compania Maritima S.A. v Pagnan S.p.A.) [1995] 1 Lloyd's Rep 87, The Jay Bola [1997] 2 Lloyd's Rep 279, The Charterers' Mutual Assurance Association v British and Foreign Marine Insurance Co. Ltd [1997] ILP 838, Turner v Grovit [2005] 1 AC 101, Erich Gasser v MISAT Srl (Case C-116/02), Front Comor (CJEU) [2009] AC 1138, Akai Pty Ltd v People's Insurance Ltd [1998] 1 Lloyd's Rep 90, DVA v Voest Alpine Intertrading GmbH (The Jay Bola) [1997] 2 Lloyd's Rep 279, The Hari Bhum (No. 1) [2004] EWCA Civ 1598; [2005] 1 Lloyd's Rep 67; [2004] 1 Lloyd's Rep 206 Referenced Cases: Padre Island (The Padre Island) [1984] 2 Lloyd's Rep 408, Hari Bhum (No.1) Through Transport Mutual Insurance Association Eurasia Ltd v New India Assurance Co Ltd (The Hari Bhum) [2004] EWCA Civ 1598; [2005] 1 Lloyd's Rep 67; [2004] 1 Lloyd's Rep 206, The Jay Bola [1997] 2 Lloyd's Rep 279, Angelic Grace (Aggeliki Charis Compania Maritima S.A. v Pagnan S.p.A.) [1995] 1 Lloyd's Rep 87, The Prestige (No. 2) (London Steam Ship Owners Mutual Insurance Association Ltd v The Kingdom of Spain) [2013] EWHC 3188 (Comm); [2014] 1 Lloyd's Rep 309; [2015] EWCA Civ 333, The Charterers' Mutual Assurance Association v British and Foreign Marine Insurance Co. Ltd [1997] ILP 838, Turner v Grovit [2005] 1 AC 101, Erich Gasser v MISAT Srl Case C-116/02, Front Comor [2009] UKHL 4 (referred to as Front Comor in some sources), Akai Pty Ltd v People's Insurance Ltd [1998] 1 Lloyd's Rep 90, DVA v Voest Alpine Intertrading GmbH (The Jay Bola) [1997] 2 Lloyd's Rep 279 Citation Count: 11 | M43: Padre Island || Hari Bhum No.1 || Prestige No.2 || The Jay Bola || The Charterers' Mutual || Angelic Grace || Turner v Grovit || Erich Gasser || Front Comor || Akai Pty Ltd v People's Insurance || DVA v Voest Alpine | N43: This case shows 69% similarity based on citations precedents analysis.
A44: cmm0b91t5000e04ibf7gf6ujr | B44: 3 | C44: 3fd15e8c-4fa9-4c85-ad33-49768aa69f0b | D44: Bate v Aviva Insurance UK Ltd [2014] EWCA Civ 334 | E44: England and Wales Court of Appeal (Civil Division) | F44: 2014 | G44: 0.6896033 | H44: 3fd15e8c-4fa9-4c85-ad33-49768aa69f0b_case_analysis | I44: case_analysis | J44: 0.6896033 | K44: Analysis discussing the precedent value of the case and its legal implications. | L44: Case Analysis and Reasoning: Precedent Strength Assessment (8/10): • The case involved important aspects of misrepresentation in insurance contracts, underlining the duty of fair disclosure by applicants. • It sets a precedent on insurers' rights to rescind policies based on material misrepresentations, reinforced by the appeal court's analysis of ICOB rules. • The quality of reasoning in the judgment is clear and concise, addressing complex factual backgrounds and legal principles. Confidence: 90% Complexity Score Assessment (7/10): • The case involved multiple legal issues including the nature of misrepresentation and the implications of ICOB guidelines. • The proceedings were complex due to the history of previous claims, the applicant's experience in property insurance, and the various claims about procedural fairness. • However, the issues were fundamentally about the clarity of misrepresentation, making them accessible albeit intricate. Confidence: 85% Legal Significance: Important case with notable legal impact | N44: This case shows 69% similarity based on case analysis analysis.
A45: cmm0b91t5000e04ibf7gf6ujr | B45: 4 | C45: cc794994-d9ff-4e2a-a522-ddb742b52a12 | D45: Quadra Commodities S.A. v XL Insurance Company SE & Ors [2023] EWCA Civ 432 (21 April 2023) | E45: England and Wales Court of Appeal (Civil Division) | F45: 2023 | G45: 0.67706925 | H45: cc794994-d9ff-4e2a-a522-ddb742b52a12_citations_precedents | I45: citations_precedents | J45: 0.67706925 | K45: Key legal authorities cited or discussed in the judgment, including older authorities defining insurable interest and bulk concepts, and statutory references shaping the analysis. | L45: Citations and Authorities: Neutral Citations: [2023] EWCA Civ 432 Law Reports: Referenced Cases: Marine Insurance Act 1906 s.5(2), Sale of Goods Act 1979 ss.16, 20A, 61, Endorsement replacing French law with English law (jurisdiction clause), Chapter 5 – Fraudulent Documents; Chapter 6 – Insured Value/Contingency, Fraudulent Documents Clause, Misappropriation Clause, Feasey v Sun Life Assurance Corporation of Canada [2003] EWCA Civ 885; [2003] Lloyd's Rep IR 637, Lucena v Crauford (1806) 2 Bos & PNR 269, Anderson v Morice (1875) 10 CP 609; (1876) 1 App Cas 713, Macaura v Northern Assurance Co Ltd [1925] AC 619, Wilson v Jones (1867) LR 2 Ex 139, RBG Resources Plc (in liq) v Banque Cantonale Vaudoise [2004] 3 SLR (R) 421, Bridge: The Sale of Goods, 4th ed. para 3.53, Addenda 7, 9, 10; Izmail Elevator; Bastico reports; SGS inspection report (7 December 2018), Amius Group references (context only), Insurance Act 2015 s.13A Citation Count: 16 | M45: Feasey || Lucena || Anderson || Macaura || Wilson || RBG Resources || Bridge || S.20A Law Commission | N45: This case shows 68% similarity based on citations precedents analysis.
A46: cmm0b91t5000e04ibf7gf6ujr | B46: 5 | C46: 426ca317-9dae-45bd-99cb-deb7de4b7766 | D46: Versloot Dredging BV & Anor v HDI Gerling Industrie Versicherung AG & Ors | E46: England and Wales Court of Appeal (Civil Division) | F46: 2014 | G46: 0.67543715 | H46: 426ca317-9dae-45bd-99cb-deb7de4b7766_factual_summary | I46: factual_summary | J46: 0.67543715 | K46: Summarizes the key events leading to the insurance claim and the basis for the court's decision. | L46: Factual Summary: Parties: Versloot Dredging BV v SO DC Merwestone BV v HDI Gerling Industrie Versicherung AG v XL Specialty Insurance Company v Oman Insurance Co. (P.S.C.) v Navigators Insurance Company v Reaal Schadeverzekeringen N.V. v International General Insurance v Mapfre Global Risks Compañia International De Seguros y Reaseguros S.A. Key Facts: Claim involved a marine insurance policy regarding a vessel's flooding due to crew negligence.. The claimants initially succeeded at trial regarding the legitimacy of the claim but were then found to have made a false representation to insurers.. The court addressed the impact of reckless misrepresentation on the recovery of legitimate claims under marine insurance. Case Summary: Versloot Dredging BV and SO DC Merwestone BV (the Owners) appealed a decision by the High Court which held that their marine insurance claim was lost due to a false narrative provided to underwriters. The court analyzed whether the Owners' recklessness in making untruthful statements on a communication form related to the underwater casualty could affect their right to recover the legitimate loss they suffered when their vessel was damaged. The court affirmed that any fraudulent representation, even not fully related to the claim's amount, still led to forfeiture of the entire claim. The appeal was dismissed, and the court confirmed that the Owners' reckless misrepresentation constituted a fraudulent device hindering their right to recover. Procedural Context: England and Wales Court of Appeal (Civil Division) case | N46: This case shows 68% similarity based on factual summary analysis.
A47: cmm0b91t5000e04ibf7gf6ujr | B47: 6 | C47: 794e2a8a-41a9-4839-a6c9-7ce1e812f4f1 | D47: Volcafe Ltd & Ors v Compania Sud Americana De Vapores SA (t/a CSAV) [2016] EWCA Civ 1103 | E47: England and Wales Court of Appeal (Civil Division) | F47: 2016 | G47: 0.67494655 | H47: 794e2a8a-41a9-4839-a6c9-7ce1e812f4f1_citations_precedents | I47: citations_precedents | J47: 0.67494655 | K47: Authorities cited and relied upon in forming the Court of Appeal’s reasoning on burden of proof, inherent vice, sound system, and loading scope. | L47: Citations and Authorities: Neutral Citations: [2016] EWCA Civ 1103, [2017] 3 WLR 1, [2016] WLR (D) 589, [2016] EWCA Civ 1103, [2017] 1 Lloyd’s Rep 32, [2016] WLR(D) 589, [2017] 1 All ER (Comm) 751, [2017] QB 915 Law Reports: [2016] EWCA Civ 1103, [2017] 3 WLR 1, [2016] WLR (D) 589, [2016] EWCA Civ 1103, [2017] 1 Lloyd’s Rep 32, [2016] WLR(D) 589, [2017] 1 All ER (Comm) 751, [2017] QB 915 Referenced Cases: G.H. Renton v Palmyra Trading Corporation [1957] AC 149, Albacora SRL v Westcott & Laurence Line Limited [1966] 2 Lloyd’s Rep 53, The Glendarroch [1894] P 226, The Flowergate [1967] 1 Lloyd’s Rep 1, Gosse Millard v Canadian Government Merchant Marine [1927] 2 KB 432, The Torenia [1983] 2 Lloyd’s Rep 210, Spurling v Bradshaw [1956] 1 WLR 461, Pyrene Co. Ltd. v Scindia Navigation [1954] 2 QB 402, Noten B.V. v Harding [1990] 2 Lloyd’s Rep 283, Soya G.m.b.H v White [1982] 2 Lloyd’s Rep 136, Exportadora Valle de Colina S.A. v A.P. Moller-Maersk A/S [2010] EWHC 3224 (Comm), The Westerdok [1962] 1 Lloyd’s Rep 180, Shaw Savill & Albion Company Ltd v Powley & Co [1949] NZLR 668, Shipping Corporation of India v Gamlen Chemical Co [1980] CLR ..., The Rio Sun [1985] 1 Lloyd’s Rep 350, Gosse Millard v Canadian Government Merchant Marine, Albacora v Westcott & Laurence Line Limited (House of Lords), Albacora (Notable passages) Citation Count: 18 | M47: Gosse Millard v Canadian Government Merchant Marine [1927] 2 KB 432 || Renton v Palmyra Trading [1957] AC 149 || Albacora SRL v Westcott & Laurence Line Limited [1966] 2 Lloyd’s Rep 53 || The Glendarroch [1894] P 226 || The Flowergate [1967] 1 Lloyd’s Rep 1 || Spurling v Bradshaw [1956] 1 WLR 461 || Pyrene Co. Ltd. v Scindia Navigation [1954] 2 QB 402 || Noten B.V. v Harding [1990] 2 Lloyd’s Rep 283 || Soya G.m.b.H v White [1982] 2 Lloyd’s Rep 136 || Exportadora Valle de Colina S.A. v A.P. Moller-Maersk A/S [2010] EWHC 3224 (Comm) || The Westerdok [1962] 1 Lloyd’s Rep 180 || Shaw Savill & Albion Co Ltd v Powley & Co [1949] NZLR 668 | N47: This case shows 67% similarity based on citations precedents analysis.
A48: cmm0b91t5000e04ibf7gf6ujr | B48: 7 | C48: 638613f3-f321-4ccd-8055-aebfec6cec82 | D48: Ted Baker Plc & Anor v Axa Insurance UK Plc & Ors [2014] EWCA Civ 134 | E48: England and Wales Court of Appeal (Civil Division) | F48: 2014 | G48: 0.6715544 | H48: 638613f3-f321-4ccd-8055-aebfec6cec82_legal_classification | I48: legal_classification | J48: 0.6715544 | K48: Classification of legal issues pertinent to the case, focusing on insurance and business law. | L48: Legal Classification: Primary Category: Insurance Legal Areas: Insurance Law, Contract Law Jurisdiction: England and Wales Court Level: Appellate Legal Issues: Proper construction of insurance policy wording. Estoppel by convention regarding coverage. Misrepresentation in securing insurance coverage Keywords: insurance, business interruption, theft, policy construction, estoppel | N48: This case shows 67% similarity based on legal classification analysis.
A49: cmm0b91t5000e04ibf7gf6ujr | B49: 8 | C49: 2f9fd02a-26e6-4859-90a8-5d64d042f0b9 | D49: AIG Europe Ltd v OC320301 LLP & Ors [2016] EWCA Civ 367 | E49: England and Wales Court of Appeal (Civil Division) | F49: 2016 | G49: 0.6616733 | H49: 2f9fd02a-26e6-4859-90a8-5d64d042f0b9_citations_precedents | I49: citations_precedents | J49: 0.6616733 | K49: Compilation of authorities cited to frame aggregation clause interpretation and the unifying factor concept. | L49: Citations and Authorities: Neutral Citations: [2016] EWCA Civ 367, [2016] 2 All ER (Comm) 1058, [2017] 1 All ER 143, [2016] Lloyd's Rep IR 289 Law Reports: Referenced Cases: Lloyds TSB General Insurance Holdings Ltd v Lloyds Bank Group Insurance Co Ltd [2003] UKHL 48, AXA Reinsurance (UK) v Field [1996] 3 All ER 517; [1996] 1 WLR 1026, Municipal Mutual Insurance Ltd v Sea Insurance Co [1998] Lloyd's Rep IR 421, Caudle v Sharp [1995] LRLR 433, Cox v Bankside Members Agency Ltd [1995] 2 Lloyd's Rep 437, AG v Cohen [1937] 1 KB 478 Citation Count: 6 | M49: Lloyds TSB General Insurance Holdings Ltd v Lloyds Bank Group Insurance Co Ltd [2003] UKHL 48 || AXA Reinsurance (UK) v Field [1996] 3 All ER 517 || Municipal Mutual Insurance Ltd v Sea Insurance Co [1998] Lloyd's Rep IR 421 || Caudle v Sharp [1995] LRLR 433 || Cox v Bankside Members Agency Ltd [1995] 2 Lloyd's Rep 437 || AG v Cohen [1937] 1 KB 478 | N49: This case shows 66% similarity based on citations precedents analysis.
A50: cmm0b91t5000e04ibf7gf6ujr | B50: 9 | C50: de6a53c9-c698-4f10-bef4-cf4544410c0e | D50: URS Corporation Limited v BDW Trading Limited (Rev1) [2023] EWCA Civ 189 | E50: England and Wales Court of Appeal (Civil Division) | F50: 2023 | G50: 0.65996414 | H50: de6a53c9-c698-4f10-bef4-cf4544410c0e_factual_summary | I50: factual_summary | J50: 0.65996414 | K50: Factual backdrop: respondents sought to amend to add DP Act 1972 and Civil Liability (Contribution) Act 1978 claims post-Building Safety Act 2022; deputy judge allowed amendments (Nov 8, 2022 and Dec 14, 2022); central issues relate to limitation periods, commencement, and potential relation-back to proceedings. | L50: Factual Summary: Parties: URS Corporation Limited v BDW Trading Limited Key Facts: Appeal from the High Court of Justice (Technology and Construction Court) in Fraser J’s decision ([2022] EWHC 2966 (TCC)) regarding amendments to pleadings.. Respondents sought to amend pleadings to pursue claims under the Defective Premises Act 1972 and the Civil Liability (Contribution) Act 1978 in light of Building Safety Act 2022.. Building Safety Act 2022 introduces new limitation provisions and a commencement date that affects existing and future actions.. Section 135 of the Building Safety Act 2022 and its timing (commencement date) are central to the question of whether the amendmentbacked claims could be treated as having a longer limitation window (30 years) and whether those amendments could relate back to the commencement of proceedings.. The Deputy High Court Judge allowed amendments in two rulings (8 Nov 2022 and 14 Dec 2022); the present appeal concerns whether that allowance was correct and what the final outcome should be. Case Summary: This appeal concerns whether amendments to the pleadings to introduce new statutory claims under the Defective Premises Act 1972 and the Civil Liability (Contribution) Act 1978 are permissible after Building Safety Act 2022 changes, and how these interact with the new limitation framework (including the 30-year retroactive effect via s.135 and the commencement date). The deputy High Court Judge had allowed amendments in two rulings (Nov 2022 and Dec 2022) from the High Court (TCC), and the Court of Appeal’s view on those amendments is sought. The text provided does not include the Court of Appeal’s final ruling on the amendments. Procedural Context: England and Wales Court of Appeal (Civil Division) case | M50: [2022] EWHC 2966 (TCC) || Fraser J | N50: This case shows 66% similarity based on factual summary analysis.
A51: cmm0b91t5000e04ibf7gf6ujr | B51: 10 | C51: 6e8e988c-074c-4ab1-9e37-5c84673b441b | D51: Secretary of State for the Home Department v Cox & Ors [2023] EWCA Civ 551 (19 May 2023) | E51: England and Wales Court of Appeal (Civil Division) | F51: 2023 | G51: 0.6594519 | H51: 6e8e988c-074c-4ab1-9e37-5c84673b441b_procedural_history | I51: procedural_history | J51: 0.6594519 | K51: Procedural path from High Court decisions to Court of Appeal with hearings in March 2023. | L51: Procedural History: Court: England and Wales Court of Appeal (Civil Division) Lower Court: High Court (QB) – [2022] EWHC 680 (QB); [2022] EWHC 1626 (QB); [2022] EWHC 3188 (KB) Judges: Lord Justice Underhill (Vice-President of the Court of Appeal (Civil Division)), Lord Justice Stuart-Smith, Lord Justice Lewis Case Number: CA-2022-000689; CA-2022-001397; CA-2023-000010 Last Hearing Date: 19 May 2023 Duration: 2 days | N51: This case shows 66% similarity based on procedural history analysis.
A52: cmm0ccsa0000304i3ltgu53bg | B52: 1 | C52: e050e594-d197-45f1-ba15-7d110c0d93c4 | D52: Great Lakes Reinsurance (UK) SE v Western Trading Ltd [2016] EWCA Civ 1003 (11 October 2016) | E52: England and Wales Court of Appeal (Civil Division) | F52: 2016 | G52: 0.7239361 | H52: e050e594-d197-45f1-ba15-7d110c0d93c4_outcome_holding | I52: outcome_holding | J52: 0.7239361 | K52: Outcome and remedial posture: declaration affirmed with corrected wording, reinstatement cost as the measure of indemnity up to the policy limit; damages not awarded; costs decided. | L52: Case Outcome: Holding: The Court of Appeal held that the measure of indemnity under the Memorandum is the cost of reinstatement (the rebuilding of the property to a condition equal to that when new), up to the policy limits. A declaration addressing indemnity for reinstatement is appropriate, provided the wording accurately reflects insurable interest and non-avoidance. The court varied the declaration’s wording and affirmed that, if reinstatement occurs, the insurer must indemnify up to £2,121,800; damages were not awarded unless necessary. Costs were adjusted to standard costs, and the appeal succeeded in part to refine the declaration and its terms. Outcome: plaintiff Precedent Strength: 8/10 Complexity Score: 9/10 Damages: 0 Legal Significance: Highly significant case with strong precedential value | N52: This case shows 72% similarity based on outcome holding analysis.
A53: cmm0ccsa0000304i3ltgu53bg | B53: 2 | C53: d38848d5-b685-4b5f-8093-40563114db3b | D53: Shipowners' Mutual Protection and Indemnity Association (Luxembourg) v Containerships Denizcilik Nakliyat ve Ticaret A.S. ("Yusuf Cepnioglu") [2016] EWCA Civ 386 | E53: England and Wales Court of Appeal (Civil Division) | F53: 2016 | G53: 0.6932597 | H53: d38848d5-b685-4b5f-8093-40563114db3b_citations_precedents | I53: citations_precedents | J53: 0.6932597 | K53: Authorities cited: Padre Island, Hari Bhum (No.1), Prestige (No.2), Jay Bola, Charterers' Mutual, Angelic Grace, Hari Bhum, Turner v Grovit, Erich Gasser, Front Comor, Akai, DVA v Voest Alpine and others. | L53: Citations and Authorities: Neutral Citations: [2016] EWCA Civ 386, [2016] Bus LR 755, [2016] WLR(D) 230, [2016] Bus LR 1284 Law Reports: The Padre Island [1984] 2 Lloyd's Rep 408, Through Transport Mutual Insurance Association (Eurasia) Ltd v New India Assurance Co Ltd (The Hari Bhum) (No.1) [2004] EWCA Civ 1598; [2005] 1 Lloyd's Rep 67; [2004] 1 Lloyd's Rep 206, The London Steam Ship Owners Mutual Insurance Association Ltd v The Kingdom of Spain (The Prestige) (No.2) [2013] EWHC 3188 (Comm); [2014] 1 Lloyd's Rep 309; [2015] EWCA Civ 333; [2015] 2 Lloyd's Rep 33, The Padre Island, The Angelic Grace (Aggeliki Charis Compania Maritima S.A. v Pagnan S.p.A.) [1995] 1 Lloyd's Rep 87, The Jay Bola [1997] 2 Lloyd's Rep 279, The Charterers' Mutual Assurance Association v British and Foreign Marine Insurance Co. Ltd [1997] ILP 838, Turner v Grovit [2005] 1 AC 101, Erich Gasser v MISAT Srl (Case C-116/02), Front Comor (CJEU) [2009] AC 1138, Akai Pty Ltd v People's Insurance Ltd [1998] 1 Lloyd's Rep 90, DVA v Voest Alpine Intertrading GmbH (The Jay Bola) [1997] 2 Lloyd's Rep 279, The Hari Bhum (No. 1) [2004] EWCA Civ 1598; [2005] 1 Lloyd's Rep 67; [2004] 1 Lloyd's Rep 206 Referenced Cases: Padre Island (The Padre Island) [1984] 2 Lloyd's Rep 408, Hari Bhum (No.1) Through Transport Mutual Insurance Association Eurasia Ltd v New India Assurance Co Ltd (The Hari Bhum) [2004] EWCA Civ 1598; [2005] 1 Lloyd's Rep 67; [2004] 1 Lloyd's Rep 206, The Jay Bola [1997] 2 Lloyd's Rep 279, Angelic Grace (Aggeliki Charis Compania Maritima S.A. v Pagnan S.p.A.) [1995] 1 Lloyd's Rep 87, The Prestige (No. 2) (London Steam Ship Owners Mutual Insurance Association Ltd v The Kingdom of Spain) [2013] EWHC 3188 (Comm); [2014] 1 Lloyd's Rep 309; [2015] EWCA Civ 333, The Charterers' Mutual Assurance Association v British and Foreign Marine Insurance Co. Ltd [1997] ILP 838, Turner v Grovit [2005] 1 AC 101, Erich Gasser v MISAT Srl Case C-116/02, Front Comor [2009] UKHL 4 (referred to as Front Comor in some sources), Akai Pty Ltd v People's Insurance Ltd [1998] 1 Lloyd's Rep 90, DVA v Voest Alpine Intertrading GmbH (The Jay Bola) [1997] 2 Lloyd's Rep 279 Citation Count: 11 | M53: Padre Island || Hari Bhum No.1 || Prestige No.2 || The Jay Bola || The Charterers' Mutual || Angelic Grace || Turner v Grovit || Erich Gasser || Front Comor || Akai Pty Ltd v People's Insurance || DVA v Voest Alpine | N53: This case shows 69% similarity based on citations precedents analysis.
